Workbook
Name HouseholdMode: Settings!$C$5
Name PersonA: Settings!$C$6
Name PersonB: Settings!$C$7
Name DefaultSplitA: Settings!$C$8
Name Province: Settings!$C$9
Name Configured: Settings!$C$10
Name TransferWindowDays: Settings!$C$11
Name SkipDuplicates: Settings!$C$12
Name Currency: Settings!$C$13
Name AppVersion: Settings!$C$14
Name ReportMonth: Dashboard!$C$6
Name ReportView: Dashboard!$F$6
Name ButtonAnchor: Dashboard!$B$3
Name TxnButtonAnchor: Transactions!$B$3
Name TopMerchants: Dashboard!$B$32:$C$41
Name CoupleBlock: Dashboard!$B$43:$I$53
Name MonthList: Engine!$D$3:$D$38
Name ViewList: Engine!$F$3:$F$5
Name HouseholdOnly: Engine!$F$3
Name OwnerList: Engine!$H$3:$H$5
Name TypeList: Engine!$J$3:$J$6
Name YesNoList: Engine!$L$3:$L$4
Name AccountTypeList: Engine!$N$3:$N$8
Name RuleFieldList: Engine!$P$3:$P$6
Name RuleTestList: Engine!$R$3:$R$8
Name RuleFlowList: Engine!$T$3:$T$5
Name DelimiterList: Engine!$V$3:$V$6
Name AmountModeList: Engine!$X$3:$X$5
Name DateFormatList: Engine!$Z$3:$Z$9
Name ProvinceList: Engine!$AB$3:$AB$15
Name LedgerRows: Engine!$AD$3
Name TaxTagList: Engine!$AF$3:$AF$17
Name GroupList: Engine!$AH$3:$AH$16
Name TaxYear: 'Tax Summary'!$C$3
Name CategoryList: =tblCategories[Category]
Name AccountList: =tblAccounts[Account]

Sheet Dashboard
B1: Canadian Finance Tracker
B2: Type your transactions on the Transactions sheet, then read your month here. Everything stays in this file - nothing is uploaded.
B6: Report month | C6: 2026-08 | E6: View | F6: Household | H6: Needs a category | I6: =COUNTIF(tblTxn[Category],"Uncategorized")
B8: This month at a glance
B9: Money in | C9: =SUMIFS(tblTxn[View Amount],tblTxn[Month],ReportMonth,tblTxn[Type],"Income") | E9: Essential spending | F9: =-SUMIFS(tblTxn[View Amount],tblTxn[Month],ReportMonth,tblTxn[Type],"Expense",tblTxn[Essential],"Yes") | H9: Uncategorized rows distort every number on this page. Filter the Transactions sheet to them and pick a category from the drop-down.
B10: Money out | C10: =-SUMIFS(tblTxn[View Amount],tblTxn[Month],ReportMonth,tblTxn[Type],"Expense") | E10: Discretionary spending | F10: =C10-F9
B11: Saved & invested | C11: =-SUMIFS(tblTxn[View Amount],tblTxn[Month],ReportMonth,tblTxn[Type],"Saving") | E11: Average spend per day | F11: =IFERROR(C10/DAY(EOMONTH(DATE(VALUE(LEFT(ReportMonth,4)),VALUE(RIGHT(ReportMonth,2)),1),0)),"")
B12: Net cash flow | C12: =C9-C10-C11 | E12: Transactions this month | F12: =COUNTIFS(tblTxn[Month],ReportMonth)
B13: Savings rate | C13: =IFERROR((C9-C10)/C9,"") | E13: Left in monthly budget | F13: =IF(SUM(tblCategories[Monthly Budget])=0,"",SUM(tblCategories[Monthly Budget])-C10)
B15: Where the money went
B16: Group | C16: This month | E16: 12-month average
B17: Housing | C17: =-SUMIFS(tblTxn[View Amount],tblTxn[Month],ReportMonth,tblTxn[Group],$B17) | E17: =-SUMIFS(tblTxn[View Amount],tblTxn[Group],$B17,tblTxn[Month],">="&TEXT(EDATE(DATE(VALUE(LEFT(ReportMonth,4)),VALUE(RIGHT(ReportMonth,2)),1),-11),"yyyy-mm"),tblTxn[Month],"<="&ReportMonth)/12
B18: Utilities | C18: =-SUMIFS(tblTxn[View Amount],tblTxn[Month],ReportMonth,tblTxn[Group],$B18) | E18: =-SUMIFS(tblTxn[View Amount],tblTxn[Group],$B18,tblTxn[Month],">="&TEXT(EDATE(DATE(VALUE(LEFT(ReportMonth,4)),VALUE(RIGHT(ReportMonth,2)),1),-11),"yyyy-mm"),tblTxn[Month],"<="&ReportMonth)/12
B19: Food | C19: =-SUMIFS(tblTxn[View Amount],tblTxn[Month],ReportMonth,tblTxn[Group],$B19) | E19: =-SUMIFS(tblTxn[View Amount],tblTxn[Group],$B19,tblTxn[Month],">="&TEXT(EDATE(DATE(VALUE(LEFT(ReportMonth,4)),VALUE(RIGHT(ReportMonth,2)),1),-11),"yyyy-mm"),tblTxn[Month],"<="&ReportMonth)/12
B20: Transportation | C20: =-SUMIFS(tblTxn[View Amount],tblTxn[Month],ReportMonth,tblTxn[Group],$B20) | E20: =-SUMIFS(tblTxn[View Amount],tblTxn[Group],$B20,tblTxn[Month],">="&TEXT(EDATE(DATE(VALUE(LEFT(ReportMonth,4)),VALUE(RIGHT(ReportMonth,2)),1),-11),"yyyy-mm"),tblTxn[Month],"<="&ReportMonth)/12
B21: Health | C21: =-SUMIFS(tblTxn[View Amount],tblTxn[Month],ReportMonth,tblTxn[Group],$B21) | E21: =-SUMIFS(tblTxn[View Amount],tblTxn[Group],$B21,tblTxn[Month],">="&TEXT(EDATE(DATE(VALUE(LEFT(ReportMonth,4)),VALUE(RIGHT(ReportMonth,2)),1),-11),"yyyy-mm"),tblTxn[Month],"<="&ReportMonth)/12
B22: Family | C22: =-SUMIFS(tblTxn[View Amount],tblTxn[Month],ReportMonth,tblTxn[Group],$B22) | E22: =-SUMIFS(tblTxn[View Amount],tblTxn[Group],$B22,tblTxn[Month],">="&TEXT(EDATE(DATE(VALUE(LEFT(ReportMonth,4)),VALUE(RIGHT(ReportMonth,2)),1),-11),"yyyy-mm"),tblTxn[Month],"<="&ReportMonth)/12
B23: Education | C23: =-SUMIFS(tblTxn[View Amount],tblTxn[Month],ReportMonth,tblTxn[Group],$B23) | E23: =-SUMIFS(tblTxn[View Amount],tblTxn[Group],$B23,tblTxn[Month],">="&TEXT(EDATE(DATE(VALUE(LEFT(ReportMonth,4)),VALUE(RIGHT(ReportMonth,2)),1),-11),"yyyy-mm"),tblTxn[Month],"<="&ReportMonth)/12
B24: Personal | C24: =-SUMIFS(tblTxn[View Amount],tblTxn[Month],ReportMonth,tblTxn[Group],$B24) | E24: =-SUMIFS(tblTxn[View Amount],tblTxn[Group],$B24,tblTxn[Month],">="&TEXT(EDATE(DATE(VALUE(LEFT(ReportMonth,4)),VALUE(RIGHT(ReportMonth,2)),1),-11),"yyyy-mm"),tblTxn[Month],"<="&ReportMonth)/12
B25: Travel | C25: =-SUMIFS(tblTxn[View Amount],tblTxn[Month],ReportMonth,tblTxn[Group],$B25) | E25: =-SUMIFS(tblTxn[View Amount],tblTxn[Group],$B25,tblTxn[Month],">="&TEXT(EDATE(DATE(VALUE(LEFT(ReportMonth,4)),VALUE(RIGHT(ReportMonth,2)),1),-11),"yyyy-mm"),tblTxn[Month],"<="&ReportMonth)/12
B26: Financial | C26: =-SUMIFS(tblTxn[View Amount],tblTxn[Month],ReportMonth,tblTxn[Group],$B26) | E26: =-SUMIFS(tblTxn[View Amount],tblTxn[Group],$B26,tblTxn[Month],">="&TEXT(EDATE(DATE(VALUE(LEFT(ReportMonth,4)),VALUE(RIGHT(ReportMonth,2)),1),-11),"yyyy-mm"),tblTxn[Month],"<="&ReportMonth)/12
B27: Saving | C27: =-SUMIFS(tblTxn[View Amount],tblTxn[Month],ReportMonth,tblTxn[Group],$B27) | E27: =-SUMIFS(tblTxn[View Amount],tblTxn[Group],$B27,tblTxn[Month],">="&TEXT(EDATE(DATE(VALUE(LEFT(ReportMonth,4)),VALUE(RIGHT(ReportMonth,2)),1),-11),"yyyy-mm"),tblTxn[Month],"<="&ReportMonth)/12
B28: Other | C28: =-SUMIFS(tblTxn[View Amount],tblTxn[Month],ReportMonth,tblTxn[Group],$B28) | E28: =-SUMIFS(tblTxn[View Amount],tblTxn[Group],$B28,tblTxn[Month],">="&TEXT(EDATE(DATE(VALUE(LEFT(ReportMonth,4)),VALUE(RIGHT(ReportMonth,2)),1),-11),"yyyy-mm"),tblTxn[Month],"<="&ReportMonth)/12
B30: Biggest categories this month
B31: Category | C31: Spent or saved | E31: Share of the month
B32: =IFERROR(IF(LARGE(Reports!$Q$29:$Q$148,1)<0,"",INDEX(Reports!$B$29:$B$148,MATCH(LARGE(Reports!$Q$29:$Q$148,1),Reports!$Q$29:$Q$148,0))),"") | C32: =IFERROR(IF(LARGE(Reports!$Q$29:$Q$148,1)<0,"",INDEX(Reports!$N$29:$N$148,MATCH(LARGE(Reports!$Q$29:$Q$148,1),Reports!$Q$29:$Q$148,0))),"") | E32: =IFERROR(IF(C32="","",C32/(C10+C11)),"") | H32: Spending and saving categories, ranked. The share is of everything that left this month: money out plus money saved.
B33: =IFERROR(IF(LARGE(Reports!$Q$29:$Q$148,2)<0,"",INDEX(Reports!$B$29:$B$148,MATCH(LARGE(Reports!$Q$29:$Q$148,2),Reports!$Q$29:$Q$148,0))),"") | C33: =IFERROR(IF(LARGE(Reports!$Q$29:$Q$148,2)<0,"",INDEX(Reports!$N$29:$N$148,MATCH(LARGE(Reports!$Q$29:$Q$148,2),Reports!$Q$29:$Q$148,0))),"") | E33: =IFERROR(IF(C33="","",C33/(C10+C11)),"")
B34: =IFERROR(IF(LARGE(Reports!$Q$29:$Q$148,3)<0,"",INDEX(Reports!$B$29:$B$148,MATCH(LARGE(Reports!$Q$29:$Q$148,3),Reports!$Q$29:$Q$148,0))),"") | C34: =IFERROR(IF(LARGE(Reports!$Q$29:$Q$148,3)<0,"",INDEX(Reports!$N$29:$N$148,MATCH(LARGE(Reports!$Q$29:$Q$148,3),Reports!$Q$29:$Q$148,0))),"") | E34: =IFERROR(IF(C34="","",C34/(C10+C11)),"")
B35: =IFERROR(IF(LARGE(Reports!$Q$29:$Q$148,4)<0,"",INDEX(Reports!$B$29:$B$148,MATCH(LARGE(Reports!$Q$29:$Q$148,4),Reports!$Q$29:$Q$148,0))),"") | C35: =IFERROR(IF(LARGE(Reports!$Q$29:$Q$148,4)<0,"",INDEX(Reports!$N$29:$N$148,MATCH(LARGE(Reports!$Q$29:$Q$148,4),Reports!$Q$29:$Q$148,0))),"") | E35: =IFERROR(IF(C35="","",C35/(C10+C11)),"")
B36: =IFERROR(IF(LARGE(Reports!$Q$29:$Q$148,5)<0,"",INDEX(Reports!$B$29:$B$148,MATCH(LARGE(Reports!$Q$29:$Q$148,5),Reports!$Q$29:$Q$148,0))),"") | C36: =IFERROR(IF(LARGE(Reports!$Q$29:$Q$148,5)<0,"",INDEX(Reports!$N$29:$N$148,MATCH(LARGE(Reports!$Q$29:$Q$148,5),Reports!$Q$29:$Q$148,0))),"") | E36: =IFERROR(IF(C36="","",C36/(C10+C11)),"")
B37: =IFERROR(IF(LARGE(Reports!$Q$29:$Q$148,6)<0,"",INDEX(Reports!$B$29:$B$148,MATCH(LARGE(Reports!$Q$29:$Q$148,6),Reports!$Q$29:$Q$148,0))),"") | C37: =IFERROR(IF(LARGE(Reports!$Q$29:$Q$148,6)<0,"",INDEX(Reports!$N$29:$N$148,MATCH(LARGE(Reports!$Q$29:$Q$148,6),Reports!$Q$29:$Q$148,0))),"") | E37: =IFERROR(IF(C37="","",C37/(C10+C11)),"")
B38: =IFERROR(IF(LARGE(Reports!$Q$29:$Q$148,7)<0,"",INDEX(Reports!$B$29:$B$148,MATCH(LARGE(Reports!$Q$29:$Q$148,7),Reports!$Q$29:$Q$148,0))),"") | C38: =IFERROR(IF(LARGE(Reports!$Q$29:$Q$148,7)<0,"",INDEX(Reports!$N$29:$N$148,MATCH(LARGE(Reports!$Q$29:$Q$148,7),Reports!$Q$29:$Q$148,0))),"") | E38: =IFERROR(IF(C38="","",C38/(C10+C11)),"")
B39: =IFERROR(IF(LARGE(Reports!$Q$29:$Q$148,8)<0,"",INDEX(Reports!$B$29:$B$148,MATCH(LARGE(Reports!$Q$29:$Q$148,8),Reports!$Q$29:$Q$148,0))),"") | C39: =IFERROR(IF(LARGE(Reports!$Q$29:$Q$148,8)<0,"",INDEX(Reports!$N$29:$N$148,MATCH(LARGE(Reports!$Q$29:$Q$148,8),Reports!$Q$29:$Q$148,0))),"") | E39: =IFERROR(IF(C39="","",C39/(C10+C11)),"")
B40: =IFERROR(IF(LARGE(Reports!$Q$29:$Q$148,9)<0,"",INDEX(Reports!$B$29:$B$148,MATCH(LARGE(Reports!$Q$29:$Q$148,9),Reports!$Q$29:$Q$148,0))),"") | C40: =IFERROR(IF(LARGE(Reports!$Q$29:$Q$148,9)<0,"",INDEX(Reports!$N$29:$N$148,MATCH(LARGE(Reports!$Q$29:$Q$148,9),Reports!$Q$29:$Q$148,0))),"") | E40: =IFERROR(IF(C40="","",C40/(C10+C11)),"")
B41: =IFERROR(IF(LARGE(Reports!$Q$29:$Q$148,10)<0,"",INDEX(Reports!$B$29:$B$148,MATCH(LARGE(Reports!$Q$29:$Q$148,10),Reports!$Q$29:$Q$148,0))),"") | C41: =IFERROR(IF(LARGE(Reports!$Q$29:$Q$148,10)<0,"",INDEX(Reports!$N$29:$N$148,MATCH(LARGE(Reports!$Q$29:$Q$148,10),Reports!$Q$29:$Q$148,0))),"") | E41: =IFERROR(IF(C41="","",C41/(C10+C11)),"")
B43: Couple view (selected month)
C44: =PersonA | E44: =PersonB
B45: Paid from own accounts | C45: =-SUMIFS(tblTxn[Amount],tblTxn[Month],ReportMonth,tblTxn[Type],"Expense",tblTxn[Paid By],PersonA) | E45: =-SUMIFS(tblTxn[Amount],tblTxn[Month],ReportMonth,tblTxn[Type],"Expense",tblTxn[Paid By],PersonB)
B46: Fair share of that spending | C46: =-(SUMIFS(tblTxn[Share A],tblTxn[Month],ReportMonth,tblTxn[Type],"Expense",tblTxn[Paid By],PersonA)+SUMIFS(tblTxn[Share A],tblTxn[Month],ReportMonth,tblTxn[Type],"Expense",tblTxn[Paid By],PersonB)) | E46: =-(SUMIFS(tblTxn[Share B],tblTxn[Month],ReportMonth,tblTxn[Type],"Expense",tblTxn[Paid By],PersonA)+SUMIFS(tblTxn[Share B],tblTxn[Month],ReportMonth,tblTxn[Type],"Expense",tblTxn[Paid By],PersonB))
B47: Balance (paid minus share) | C47: =C45-C46 | E47: =E45-E46
B49: Settlement | C49: =IF(ROUND(C47,2)>0,PersonB&" owes "&PersonA&" "&TEXT(ROUND(C47,2),"$#,##0.00"),IF(ROUND(C47,2)<0,PersonA&" owes "&PersonB&" "&TEXT(-ROUND(C47,2),"$#,##0.00"),"Even for this month"))
B51: Only spending paid from personal accounts is settled - joint accounts are assumed to be funded per the household split already. Change who an expense is for with the Owner column on the Transactions sheet.

Sheet Transactions
B1: Transactions
B2: One row per transaction. Money out is negative, money in is positive. Type the Date, Account, Description and Amount; everything else fills itself in, and can be typed over.
B6: Txn ID | C6: Date | D6: Month | E6: Account | F6: Paid By | G6: Owner | H6: Description | I6: Merchant | J6: Amount | K6: Category | L6: Group | M6: Type | N6: Essential | O6: Tax Tag | P6: Split A % | Q6: Share A | R6: Share B | S6: Reimbursable | T6: Notes | U6: Source File | V6: Batch | W6: Match Key | X6: Tagged By | Y6: View Amount
B7: =IF($C7="","","T"&TEXT(ROW()-ROW(tblTxn[[#Headers],[Txn ID]]),"000000")) | C7: 46082 | D7: =IF($C7="","",TEXT($C7,"yyyy-mm")) | E7: BMO Joint Chequing | F7: =IF($C7="","",IFERROR(INDEX(tblAccounts[Owner],MATCH($E7,tblAccounts[Account],0)),"Joint")) | G7: =IF($C7="","",IF(HouseholdMode="Couple",IFERROR(IF(INDEX(tblCategories[Default Owner],MATCH($K7,tblCategories[Category],0))="",$F7,INDEX(tblCategories[Default Owner],MATCH($K7,tblCategories[Category],0))),$F7),$F7)) | H7: RENT PAYMENT 84 BROADVIEW AVE | I7: =IF($H7="","",$H7) | J7: -2350 | K7: =IF($H7="","",IFERROR(INDEX(tblRules[Category],SUMPRODUCT(MIN((1-((tblRules[Enabled]<>"No")*(tblRules[Pattern]<>"")*(tblRules[Category]<>"")*((tblRules[Flow]="Any")+(tblRules[Flow]="")+((tblRules[Flow]="Money out")*($J7<0))+((tblRules[Flow]="Money in")*($J7>0)))*(((tblRules[Look In]="Account")*ISNUMBER(SEARCH(tblRules[Pattern],$E7)))+((tblRules[Look In]<>"Account")*(((tblRules[Test]="Word")*ISNUMBER(SEARCH(" "&tblRules[Pattern]&" "," "&$H7&" ")))+((tblRules[Test]<>"Word")*ISNUMBER(SEARCH(tblRules[Pattern],$H7))))))>0))*1E+9+ROW(tblRules[Pattern])))-ROW(tblRules[[#Headers],[Pattern]])),"Uncategorized")) | L7: =IF($C7="","",IFERROR(INDEX(tblCategories[Group],MATCH($K7,tblCategories[Category],0)),"Other")) | M7: =IF($C7="","",IFERROR(INDEX(tblCategories[Type],MATCH($K7,tblCategories[Category],0)),IF($J7>0,"Income","Expense"))) | N7: =IF($C7="","",IFERROR(INDEX(tblCategories[Essential],MATCH($K7,tblCategories[Category],0)),"No")) | O7: =IF($C7="","",IFERROR(INDEX(tblCategories[Tax Tag],MATCH($K7,tblCategories[Category],0)),"")) | P7: =IF($C7="","",IF($G7=PersonA,1,IF($G7=PersonB,0,IFERROR(INDEX(tblCategories[Joint Split A],MATCH($K7,tblCategories[Category],0)),DefaultSplitA)))) | Q7: =IF($C7="","",ROUND($J7*N($P7),2)) | R7: =IF($C7="","",ROUND($J7-N($Q7),2)) | U7: sample-data | V7: SAMPLE | W7: 9C39F83E | X7: =IF($C7="","",IFERROR(IF(_xlfn.ISFORMULA($K7),"Rule","Manual"),"")) | Y7: =IF($C7="","",IF(ReportView=PersonA,N($Q7),IF(ReportView=PersonB,N($R7),$J7)))
B8: =IF($C8="","","T"&TEXT(ROW()-ROW(tblTxn[[#Headers],[Txn ID]]),"000000")) | C8: 46084 | D8: =IF($C8="","",TEXT($C8,"yyyy-mm")) | E8: Amex Cobalt (Joint) | F8: =IF($C8="","",IFERROR(INDEX(tblAccounts[Owner],MATCH($E8,tblAccounts[Account],0)),"Joint")) | G8: =IF($C8="","",IF(HouseholdMode="Couple",IFERROR(IF(INDEX(tblCategories[Default Owner],MATCH($K8,tblCategories[Category],0))="",$F8,INDEX(tblCategories[Default Owner],MATCH($K8,tblCategories[Category],0))),$F8),$F8)) | H8: IDP PURCHASE - 4612 CANADIAN TIRE #2196 ON | I8: =IF($H8="","",$H8) | J8: -97.88 | K8: =IF($H8="","",IFERROR(INDEX(tblRules[Category],SUMPRODUCT(MIN((1-((tblRules[Enabled]<>"No")*(tblRules[Pattern]<>"")*(tblRules[Category]<>"")*((tblRules[Flow]="Any")+(tblRules[Flow]="")+((tblRules[Flow]="Money out")*($J8<0))+((tblRules[Flow]="Money in")*($J8>0)))*(((tblRules[Look In]="Account")*ISNUMBER(SEARCH(tblRules[Pattern],$E8)))+((tblRules[Look In]<>"Account")*(((tblRules[Test]="Word")*ISNUMBER(SEARCH(" "&tblRules[Pattern]&" "," "&$H8&" ")))+((tblRules[Test]<>"Word")*ISNUMBER(SEARCH(tblRules[Pattern],$H8))))))>0))*1E+9+ROW(tblRules[Pattern])))-ROW(tblRules[[#Headers],[Pattern]])),"Uncategorized")) | L8: =IF($C8="","",IFERROR(INDEX(tblCategories[Group],MATCH($K8,tblCategories[Category],0)),"Other")) | M8: =IF($C8="","",IFERROR(INDEX(tblCategories[Type],MATCH($K8,tblCategories[Category],0)),IF($J8>0,"Income","Expense"))) | N8: =IF($C8="","",IFERROR(INDEX(tblCategories[Essential],MATCH($K8,tblCategories[Category],0)),"No")) | O8: =IF($C8="","",IFERROR(INDEX(tblCategories[Tax Tag],MATCH($K8,tblCategories[Category],0)),"")) | P8: =IF($C8="","",IF($G8=PersonA,1,IF($G8=PersonB,0,IFERROR(INDEX(tblCategories[Joint Split A],MATCH($K8,tblCategories[Category],0)),DefaultSplitA)))) | Q8: =IF($C8="","",ROUND($J8*N($P8),2)) | R8: =IF($C8="","",ROUND($J8-N($Q8),2)) | U8: sample-data | V8: SAMPLE | W8: 45F839FC | X8: =IF($C8="","",IFERROR(IF(_xlfn.ISFORMULA($K8),"Rule","Manual"),"")) | Y8: =IF($C8="","",IF(ReportView=PersonA,N($Q8),IF(ReportView=PersonB,N($R8),$J8)))
B9: =IF($C9="","","T"&TEXT(ROW()-ROW(tblTxn[[#Headers],[Txn ID]]),"000000")) | C9: 46084 | D9: =IF($C9="","",TEXT($C9,"yyyy-mm")) | E9: BMO Joint Chequing | F9: =IF($C9="","",IFERROR(INDEX(tblAccounts[Owner],MATCH($E9,tblAccounts[Account],0)),"Joint")) | G9: =IF($C9="","",IF(HouseholdMode="Couple",IFERROR(IF(INDEX(tblCategories[Default Owner],MATCH($K9,tblCategories[Category],0))="",$F9,INDEX(tblCategories[Default Owner],MATCH($K9,tblCategories[Category],0))),$F9),$F9)) | H9: GOODLIFE CLUBS PREAUTHORIZED DEBIT | I9: =IF($H9="","",$H9) | J9: -54.22 | K9: =IF($H9="","",IFERROR(INDEX(tblRules[Category],SUMPRODUCT(MIN((1-((tblRules[Enabled]<>"No")*(tblRules[Pattern]<>"")*(tblRules[Category]<>"")*((tblRules[Flow]="Any")+(tblRules[Flow]="")+((tblRules[Flow]="Money out")*($J9<0))+((tblRules[Flow]="Money in")*($J9>0)))*(((tblRules[Look In]="Account")*ISNUMBER(SEARCH(tblRules[Pattern],$E9)))+((tblRules[Look In]<>"Account")*(((tblRules[Test]="Word")*ISNUMBER(SEARCH(" "&tblRules[Pattern]&" "," "&$H9&" ")))+((tblRules[Test]<>"Word")*ISNUMBER(SEARCH(tblRules[Pattern],$H9))))))>0))*1E+9+ROW(tblRules[Pattern])))-ROW(tblRules[[#Headers],[Pattern]])),"Uncategorized")) | L9: =IF($C9="","",IFERROR(INDEX(tblCategories[Group],MATCH($K9,tblCategories[Category],0)),"Other")) | M9: =IF($C9="","",IFERROR(INDEX(tblCategories[Type],MATCH($K9,tblCategories[Category],0)),IF($J9>0,"Income","Expense"))) | N9: =IF($C9="","",IFERROR(INDEX(tblCategories[Essential],MATCH($K9,tblCategories[Category],0)),"No")) | O9: =IF($C9="","",IFERROR(INDEX(tblCategories[Tax Tag],MATCH($K9,tblCategories[Category],0)),"")) | P9: =IF($C9="","",IF($G9=PersonA,1,IF($G9=PersonB,0,IFERROR(INDEX(tblCategories[Joint Split A],MATCH($K9,tblCategories[Category],0)),DefaultSplitA)))) | Q9: =IF($C9="","",ROUND($J9*N($P9),2)) | R9: =IF($C9="","",ROUND($J9-N($Q9),2)) | U9: sample-data | V9: SAMPLE | W9: B1B6FD37 | X9: =IF($C9="","",IFERROR(IF(_xlfn.ISFORMULA($K9),"Rule","Manual"),"")) | Y9: =IF($C9="","",IF(ReportView=PersonA,N($Q9),IF(ReportView=PersonB,N($R9),$J9)))
B10: =IF($C10="","","T"&TEXT(ROW()-ROW(tblTxn[[#Headers],[Txn ID]]),"000000")) | C10: 46084 | D10: =IF($C10="","",TEXT($C10,"yyyy-mm")) | E10: Tangerine Chequing (Sam) | F10: =IF($C10="","",IFERROR(INDEX(tblAccounts[Owner],MATCH($E10,tblAccounts[Account],0)),"Joint")) | G10: =IF($C10="","",IF(HouseholdMode="Couple",IFERROR(IF(INDEX(tblCategories[Default Owner],MATCH($K10,tblCategories[Category],0))="",$F10,INDEX(tblCategories[Default Owner],MATCH($K10,tblCategories[Category],0))),$F10),$F10)) | H10: IDP PURCHASE - 6527 LCBO/RAO #4079 TORONTO ON | I10: =IF($H10="","",$H10) | J10: -28.27 | K10: =IF($H10="","",IFERROR(INDEX(tblRules[Category],SUMPRODUCT(MIN((1-((tblRules[Enabled]<>"No")*(tblRules[Pattern]<>"")*(tblRules[Category]<>"")*((tblRules[Flow]="Any")+(tblRules[Flow]="")+((tblRules[Flow]="Money out")*($J10<0))+((tblRules[Flow]="Money in")*($J10>0)))*(((tblRules[Look In]="Account")*ISNUMBER(SEARCH(tblRules[Pattern],$E10)))+((tblRules[Look In]<>"Account")*(((tblRules[Test]="Word")*ISNUMBER(SEARCH(" "&tblRules[Pattern]&" "," "&$H10&" ")))+((tblRules[Test]<>"Word")*ISNUMBER(SEARCH(tblRules[Pattern],$H10))))))>0))*1E+9+ROW(tblRules[Pattern])))-ROW(tblRules[[#Headers],[Pattern]])),"Uncategorized")) | L10: =IF($C10="","",IFERROR(INDEX(tblCategories[Group],MATCH($K10,tblCategories[Category],0)),"Other")) | M10: =IF($C10="","",IFERROR(INDEX(tblCategories[Type],MATCH($K10,tblCategories[Category],0)),IF($J10>0,"Income","Expense"))) | N10: =IF($C10="","",IFERROR(INDEX(tblCategories[Essential],MATCH($K10,tblCategories[Category],0)),"No")) | O10: =IF($C10="","",IFERROR(INDEX(tblCategories[Tax Tag],MATCH($K10,tblCategories[Category],0)),"")) | P10: =IF($C10="","",IF($G10=PersonA,1,IF($G10=PersonB,0,IFERROR(INDEX(tblCategories[Joint Split A],MATCH($K10,tblCategories[Category],0)),DefaultSplitA)))) | Q10: =IF($C10="","",ROUND($J10*N($P10),2)) | R10: =IF($C10="","",ROUND($J10-N($Q10),2)) | U10: sample-data | V10: SAMPLE | W10: 91FBDF2B | X10: =IF($C10="","",IFERROR(IF(_xlfn.ISFORMULA($K10),"Rule","Manual"),"")) | Y10: =IF($C10="","",IF(ReportView=PersonA,N($Q10),IF(ReportView=PersonB,N($R10),$J10)))
B11: =IF($C11="","","T"&TEXT(ROW()-ROW(tblTxn[[#Headers],[Txn ID]]),"000000")) | C11: 46086 | D11: =IF($C11="","",TEXT($C11,"yyyy-mm")) | E11: Amex Cobalt (Joint) | F11: =IF($C11="","",IFERROR(INDEX(tblAccounts[Owner],MATCH($E11,tblAccounts[Account],0)),"Joint")) | G11: =IF($C11="","",IF(HouseholdMode="Couple",IFERROR(IF(INDEX(tblCategories[Default Owner],MATCH($K11,tblCategories[Category],0))="",$F11,INDEX(tblCategories[Default Owner],MATCH($K11,tblCategories[Category],0))),$F11),$F11)) | H11: IDP PURCHASE - 8060 TIM HORTONS #3324 TORONTO ON | I11: =IF($H11="","",$H11) | J11: -5.8 | K11: =IF($H11="","",IFERROR(INDEX(tblRules[Category],SUMPRODUCT(MIN((1-((tblRules[Enabled]<>"No")*(tblRules[Pattern]<>"")*(tblRules[Category]<>"")*((tblRules[Flow]="Any")+(tblRules[Flow]="")+((tblRules[Flow]="Money out")*($J11<0))+((tblRules[Flow]="Money in")*($J11>0)))*(((tblRules[Look In]="Account")*ISNUMBER(SEARCH(tblRules[Pattern],$E11)))+((tblRules[Look In]<>"Account")*(((tblRules[Test]="Word")*ISNUMBER(SEARCH(" "&tblRules[Pattern]&" "," "&$H11&" ")))+((tblRules[Test]<>"Word")*ISNUMBER(SEARCH(tblRules[Pattern],$H11))))))>0))*1E+9+ROW(tblRules[Pattern])))-ROW(tblRules[[#Headers],[Pattern]])),"Uncategorized")) | L11: =IF($C11="","",IFERROR(INDEX(tblCategories[Group],MATCH($K11,tblCategories[Category],0)),"Other")) | M11: =IF($C11="","",IFERROR(INDEX(tblCategories[Type],MATCH($K11,tblCategories[Category],0)),IF($J11>0,"Income","Expense"))) | N11: =IF($C11="","",IFERROR(INDEX(tblCategories[Essential],MATCH($K11,tblCategories[Category],0)),"No")) | O11: =IF($C11="","",IFERROR(INDEX(tblCategories[Tax Tag],MATCH($K11,tblCategories[Category],0)),"")) | P11: =IF($C11="","",IF($G11=PersonA,1,IF($G11=PersonB,0,IFERROR(INDEX(tblCategories[Joint Split A],MATCH($K11,tblCategories[Category],0)),DefaultSplitA)))) | Q11: =IF($C11="","",ROUND($J11*N($P11),2)) | R11: =IF($C11="","",ROUND($J11-N($Q11),2)) | U11: sample-data | V11: SAMPLE | W11: 76E83383 | X11: =IF($C11="","",IFERROR(IF(_xlfn.ISFORMULA($K11),"Rule","Manual"),"")) | Y11: =IF($C11="","",IF(ReportView=PersonA,N($Q11),IF(ReportView=PersonB,N($R11),$J11)))
B12: =IF($C12="","","T"&TEXT(ROW()-ROW(tblTxn[[#Headers],[Txn ID]]),"000000")) | C12: 46086 | D12: =IF($C12="","",TEXT($C12,"yyyy-mm")) | E12: BMO Joint Chequing | F12: =IF($C12="","",IFERROR(INDEX(tblAccounts[Owner],MATCH($E12,tblAccounts[Account],0)),"Joint")) | G12: =IF($C12="","",IF(HouseholdMode="Couple",IFERROR(IF(INDEX(tblCategories[Default Owner],MATCH($K12,tblCategories[Category],0))="",$F12,INDEX(tblCategories[Default Owner],MATCH($K12,tblCategories[Category],0))),$F12),$F12)) | H12: BELAIRDIRECT INSURANCE PREAUTHORIZED DEBIT | I12: =IF($H12="","",$H12) | J12: -168 | K12: =IF($H12="","",IFERROR(INDEX(tblRules[Category],SUMPRODUCT(MIN((1-((tblRules[Enabled]<>"No")*(tblRules[Pattern]<>"")*(tblRules[Category]<>"")*((tblRules[Flow]="Any")+(tblRules[Flow]="")+((tblRules[Flow]="Money out")*($J12<0))+((tblRules[Flow]="Money in")*($J12>0)))*(((tblRules[Look In]="Account")*ISNUMBER(SEARCH(tblRules[Pattern],$E12)))+((tblRules[Look In]<>"Account")*(((tblRules[Test]="Word")*ISNUMBER(SEARCH(" "&tblRules[Pattern]&" "," "&$H12&" ")))+((tblRules[Test]<>"Word")*ISNUMBER(SEARCH(tblRules[Pattern],$H12))))))>0))*1E+9+ROW(tblRules[Pattern])))-ROW(tblRules[[#Headers],[Pattern]])),"Uncategorized")) | L12: =IF($C12="","",IFERROR(INDEX(tblCategories[Group],MATCH($K12,tblCategories[Category],0)),"Other")) | M12: =IF($C12="","",IFERROR(INDEX(tblCategories[Type],MATCH($K12,tblCategories[Category],0)),IF($J12>0,"Income","Expense"))) | N12: =IF($C12="","",IFERROR(INDEX(tblCategories[Essential],MATCH($K12,tblCategories[Category],0)),"No")) | O12: =IF($C12="","",IFERROR(INDEX(tblCategories[Tax Tag],MATCH($K12,tblCategories[Category],0)),"")) | P12: =IF($C12="","",IF($G12=PersonA,1,IF($G12=PersonB,0,IFERROR(INDEX(tblCategories[Joint Split A],MATCH($K12,tblCategories[Category],0)),DefaultSplitA)))) | Q12: =IF($C12="","",ROUND($J12*N($P12),2)) | R12: =IF($C12="","",ROUND($J12-N($Q12),2)) | U12: sample-data | V12: SAMPLE | W12: 7EA841BF | X12: =IF($C12="","",IFERROR(IF(_xlfn.ISFORMULA($K12),"Rule","Manual"),"")) | Y12: =IF($C12="","",IF(ReportView=PersonA,N($Q12),IF(ReportView=PersonB,N($R12),$J12)))
B13: =IF($C13="","","T"&TEXT(ROW()-ROW(tblTxn[[#Headers],[Txn ID]]),"000000")) | C13: 46086 | D13: =IF($C13="","",TEXT($C13,"yyyy-mm")) | E13: BMO Joint Chequing | F13: =IF($C13="","",IFERROR(INDEX(tblAccounts[Owner],MATCH($E13,tblAccounts[Account],0)),"Joint")) | G13: =IF($C13="","",IF(HouseholdMode="Couple",IFERROR(IF(INDEX(tblCategories[Default Owner],MATCH($K13,tblCategories[Category],0))="",$F13,INDEX(tblCategories[Default Owner],MATCH($K13,tblCategories[Category],0))),$F13),$F13)) | H13: LITTLE MAPLE DAYCARE PREAUTHORIZED DEBIT | I13: =IF($H13="","",$H13) | J13: -880 | K13: =IF($H13="","",IFERROR(INDEX(tblRules[Category],SUMPRODUCT(MIN((1-((tblRules[Enabled]<>"No")*(tblRules[Pattern]<>"")*(tblRules[Category]<>"")*((tblRules[Flow]="Any")+(tblRules[Flow]="")+((tblRules[Flow]="Money out")*($J13<0))+((tblRules[Flow]="Money in")*($J13>0)))*(((tblRules[Look In]="Account")*ISNUMBER(SEARCH(tblRules[Pattern],$E13)))+((tblRules[Look In]<>"Account")*(((tblRules[Test]="Word")*ISNUMBER(SEARCH(" "&tblRules[Pattern]&" "," "&$H13&" ")))+((tblRules[Test]<>"Word")*ISNUMBER(SEARCH(tblRules[Pattern],$H13))))))>0))*1E+9+ROW(tblRules[Pattern])))-ROW(tblRules[[#Headers],[Pattern]])),"Uncategorized")) | L13: =IF($C13="","",IFERROR(INDEX(tblCategories[Group],MATCH($K13,tblCategories[Category],0)),"Other")) | M13: =IF($C13="","",IFERROR(INDEX(tblCategories[Type],MATCH($K13,tblCategories[Category],0)),IF($J13>0,"Income","Expense"))) | N13: =IF($C13="","",IFERROR(INDEX(tblCategories[Essential],MATCH($K13,tblCategories[Category],0)),"No")) | O13: =IF($C13="","",IFERROR(INDEX(tblCategories[Tax Tag],MATCH($K13,tblCategories[Category],0)),"")) | P13: =IF($C13="","",IF($G13=PersonA,1,IF($G13=PersonB,0,IFERROR(INDEX(tblCategories[Joint Split A],MATCH($K13,tblCategories[Category],0)),DefaultSplitA)))) | Q13: =IF($C13="","",ROUND($J13*N($P13),2)) | R13: =IF($C13="","",ROUND($J13-N($Q13),2)) | U13: sample-data | V13: SAMPLE | W13: 856EE728 | X13: =IF($C13="","",IFERROR(IF(_xlfn.ISFORMULA($K13),"Rule","Manual"),"")) | Y13: =IF($C13="","",IF(ReportView=PersonA,N($Q13),IF(ReportView=PersonB,N($R13),$J13)))
B14: =IF($C14="","","T"&TEXT(ROW()-ROW(tblTxn[[#Headers],[Txn ID]]),"000000")) | C14: 46087 | D14: =IF($C14="","",TEXT($C14,"yyyy-mm")) | E14: Amex Cobalt (Joint) | F14: =IF($C14="","",IFERROR(INDEX(tblAccounts[Owner],MATCH($E14,tblAccounts[Account],0)),"Joint")) | G14: =IF($C14="","",IF(HouseholdMode="Couple",IFERROR(IF(INDEX(tblCategories[Default Owner],MATCH($K14,tblCategories[Category],0))="",$F14,INDEX(tblCategories[Default Owner],MATCH($K14,tblCategories[Category],0))),$F14),$F14)) | H14: IDP PURCHASE - 5260 SWISS CHALET #1631 ON | I14: =IF($H14="","",$H14) | J14: -56.99 | K14: =IF($H14="","",IFERROR(INDEX(tblRules[Category],SUMPRODUCT(MIN((1-((tblRules[Enabled]<>"No")*(tblRules[Pattern]<>"")*(tblRules[Category]<>"")*((tblRules[Flow]="Any")+(tblRules[Flow]="")+((tblRules[Flow]="Money out")*($J14<0))+((tblRules[Flow]="Money in")*($J14>0)))*(((tblRules[Look In]="Account")*ISNUMBER(SEARCH(tblRules[Pattern],$E14)))+((tblRules[Look In]<>"Account")*(((tblRules[Test]="Word")*ISNUMBER(SEARCH(" "&tblRules[Pattern]&" "," "&$H14&" ")))+((tblRules[Test]<>"Word")*ISNUMBER(SEARCH(tblRules[Pattern],$H14))))))>0))*1E+9+ROW(tblRules[Pattern])))-ROW(tblRules[[#Headers],[Pattern]])),"Uncategorized")) | L14: =IF($C14="","",IFERROR(INDEX(tblCategories[Group],MATCH($K14,tblCategories[Category],0)),"Other")) | M14: =IF($C14="","",IFERROR(INDEX(tblCategories[Type],MATCH($K14,tblCategories[Category],0)),IF($J14>0,"Income","Expense"))) | N14: =IF($C14="","",IFERROR(INDEX(tblCategories[Essential],MATCH($K14,tblCategories[Category],0)),"No")) | O14: =IF($C14="","",IFERROR(INDEX(tblCategories[Tax Tag],MATCH($K14,tblCategories[Category],0)),"")) | P14: =IF($C14="","",IF($G14=PersonA,1,IF($G14=PersonB,0,IFERROR(INDEX(tblCategories[Joint Split A],MATCH($K14,tblCategories[Category],0)),DefaultSplitA)))) | Q14: =IF($C14="","",ROUND($J14*N($P14),2)) | R14: =IF($C14="","",ROUND($J14-N($Q14),2)) | U14: sample-data | V14: SAMPLE | W14: 573803B2 | X14: =IF($C14="","",IFERROR(IF(_xlfn.ISFORMULA($K14),"Rule","Manual"),"")) | Y14: =IF($C14="","",IF(ReportView=PersonA,N($Q14),IF(ReportView=PersonB,N($R14),$J14)))
B15: =IF($C15="","","T"&TEXT(ROW()-ROW(tblTxn[[#Headers],[Txn ID]]),"000000")) | C15: 46087 | D15: =IF($C15="","",TEXT($C15,"yyyy-mm")) | E15: BMO Joint Chequing | F15: =IF($C15="","",IFERROR(INDEX(tblAccounts[Owner],MATCH($E15,tblAccounts[Account],0)),"Joint")) | G15: =IF($C15="","",IF(HouseholdMode="Couple",IFERROR(IF(INDEX(tblCategories[Default Owner],MATCH($K15,tblCategories[Category],0))="",$F15,INDEX(tblCategories[Default Owner],MATCH($K15,tblCategories[Category],0))),$F15),$F15)) | H15: SUN LIFE ASSURANCE MISC PAYMENT | I15: =IF($H15="","",$H15) | J15: -74.5 | K15: =IF($H15="","",IFERROR(INDEX(tblRules[Category],SUMPRODUCT(MIN((1-((tblRules[Enabled]<>"No")*(tblRules[Pattern]<>"")*(tblRules[Category]<>"")*((tblRules[Flow]="Any")+(tblRules[Flow]="")+((tblRules[Flow]="Money out")*($J15<0))+((tblRules[Flow]="Money in")*($J15>0)))*(((tblRules[Look In]="Account")*ISNUMBER(SEARCH(tblRules[Pattern],$E15)))+((tblRules[Look In]<>"Account")*(((tblRules[Test]="Word")*ISNUMBER(SEARCH(" "&tblRules[Pattern]&" "," "&$H15&" ")))+((tblRules[Test]<>"Word")*ISNUMBER(SEARCH(tblRules[Pattern],$H15))))))>0))*1E+9+ROW(tblRules[Pattern])))-ROW(tblRules[[#Headers],[Pattern]])),"Uncategorized")) | L15: =IF($C15="","",IFERROR(INDEX(tblCategories[Group],MATCH($K15,tblCategories[Category],0)),"Other")) | M15: =IF($C15="","",IFERROR(INDEX(tblCategories[Type],MATCH($K15,tblCategories[Category],0)),IF($J15>0,"Income","Expense"))) | N15: =IF($C15="","",IFERROR(INDEX(tblCategories[Essential],MATCH($K15,tblCategories[Category],0)),"No")) | O15: =IF($C15="","",IFERROR(INDEX(tblCategories[Tax Tag],MATCH($K15,tblCategories[Category],0)),"")) | P15: =IF($C15="","",IF($G15=PersonA,1,IF($G15=PersonB,0,IFERROR(INDEX(tblCategories[Joint Split A],MATCH($K15,tblCategories[Category],0)),DefaultSplitA)))) | Q15: =IF($C15="","",ROUND($J15*N($P15),2)) | R15: =IF($C15="","",ROUND($J15-N($Q15),2)) | U15: sample-data | V15: SAMPLE | W15: 7B77744A | X15: =IF($C15="","",IFERROR(IF(_xlfn.ISFORMULA($K15),"Rule","Manual"),"")) | Y15: =IF($C15="","",IF(ReportView=PersonA,N($Q15),IF(ReportView=PersonB,N($R15),$J15)))
B16: =IF($C16="","","T"&TEXT(ROW()-ROW(tblTxn[[#Headers],[Txn ID]]),"000000")) | C16: 46088 | D16: =IF($C16="","",TEXT($C16,"yyyy-mm")) | E16: Amex Cobalt (Joint) | F16: =IF($C16="","",IFERROR(INDEX(tblAccounts[Owner],MATCH($E16,tblAccounts[Account],0)),"Joint")) | G16: =IF($C16="","",IF(HouseholdMode="Couple",IFERROR(IF(INDEX(tblCategories[Default Owner],MATCH($K16,tblCategories[Category],0))="",$F16,INDEX(tblCategories[Default Owner],MATCH($K16,tblCategories[Category],0))),$F16),$F16)) | H16: IDP PURCHASE - 5650 TIM HORTONS #1246 TORONTO ON | I16: =IF($H16="","",$H16) | J16: -4.17 | K16: =IF($H16="","",IFERROR(INDEX(tblRules[Category],SUMPRODUCT(MIN((1-((tblRules[Enabled]<>"No")*(tblRules[Pattern]<>"")*(tblRules[Category]<>"")*((tblRules[Flow]="Any")+(tblRules[Flow]="")+((tblRules[Flow]="Money out")*($J16<0))+((tblRules[Flow]="Money in")*($J16>0)))*(((tblRules[Look In]="Account")*ISNUMBER(SEARCH(tblRules[Pattern],$E16)))+((tblRules[Look In]<>"Account")*(((tblRules[Test]="Word")*ISNUMBER(SEARCH(" "&tblRules[Pattern]&" "," "&$H16&" ")))+((tblRules[Test]<>"Word")*ISNUMBER(SEARCH(tblRules[Pattern],$H16))))))>0))*1E+9+ROW(tblRules[Pattern])))-ROW(tblRules[[#Headers],[Pattern]])),"Uncategorized")) | L16: =IF($C16="","",IFERROR(INDEX(tblCategories[Group],MATCH($K16,tblCategories[Category],0)),"Other")) | M16: =IF($C16="","",IFERROR(INDEX(tblCategories[Type],MATCH($K16,tblCategories[Category],0)),IF($J16>0,"Income","Expense"))) | N16: =IF($C16="","",IFERROR(INDEX(tblCategories[Essential],MATCH($K16,tblCategories[Category],0)),"No")) | O16: =IF($C16="","",IFERROR(INDEX(tblCategories[Tax Tag],MATCH($K16,tblCategories[Category],0)),"")) | P16: =IF($C16="","",IF($G16=PersonA,1,IF($G16=PersonB,0,IFERROR(INDEX(tblCategories[Joint Split A],MATCH($K16,tblCategories[Category],0)),DefaultSplitA)))) | Q16: =IF($C16="","",ROUND($J16*N($P16),2)) | R16: =IF($C16="","",ROUND($J16-N($Q16),2)) | U16: sample-data | V16: SAMPLE | W16: 003ECA6D | X16: =IF($C16="","",IFERROR(IF(_xlfn.ISFORMULA($K16),"Rule","Manual"),"")) | Y16: =IF($C16="","",IF(ReportView=PersonA,N($Q16),IF(ReportView=PersonB,N($R16),$J16)))
B17: =IF($C17="","","T"&TEXT(ROW()-ROW(tblTxn[[#Headers],[Txn ID]]),"000000")) | C17: 46089 | D17: =IF($C17="","",TEXT($C17,"yyyy-mm")) | E17: BMO Joint Chequing | F17: =IF($C17="","",IFERROR(INDEX(tblAccounts[Owner],MATCH($E17,tblAccounts[Account],0)),"Joint")) | G17: =IF($C17="","",IF(HouseholdMode="Couple",IFERROR(IF(INDEX(tblCategories[Default Owner],MATCH($K17,tblCategories[Category],0))="",$F17,INDEX(tblCategories[Default Owner],MATCH($K17,tblCategories[Category],0))),$F17),$F17)) | H17: TORONTO HYDRO BILL PAYMENT | I17: =IF($H17="","",$H17) | J17: -97.76 | K17: =IF($H17="","",IFERROR(INDEX(tblRules[Category],SUMPRODUCT(MIN((1-((tblRules[Enabled]<>"No")*(tblRules[Pattern]<>"")*(tblRules[Category]<>"")*((tblRules[Flow]="Any")+(tblRules[Flow]="")+((tblRules[Flow]="Money out")*($J17<0))+((tblRules[Flow]="Money in")*($J17>0)))*(((tblRules[Look In]="Account")*ISNUMBER(SEARCH(tblRules[Pattern],$E17)))+((tblRules[Look In]<>"Account")*(((tblRules[Test]="Word")*ISNUMBER(SEARCH(" "&tblRules[Pattern]&" "," "&$H17&" ")))+((tblRules[Test]<>"Word")*ISNUMBER(SEARCH(tblRules[Pattern],$H17))))))>0))*1E+9+ROW(tblRules[Pattern])))-ROW(tblRules[[#Headers],[Pattern]])),"Uncategorized")) | L17: =IF($C17="","",IFERROR(INDEX(tblCategories[Group],MATCH($K17,tblCategories[Category],0)),"Other")) | M17: =IF($C17="","",IFERROR(INDEX(tblCategories[Type],MATCH($K17,tblCategories[Category],0)),IF($J17>0,"Income","Expense"))) | N17: =IF($C17="","",IFERROR(INDEX(tblCategories[Essential],MATCH($K17,tblCategories[Category],0)),"No")) | O17: =IF($C17="","",IFERROR(INDEX(tblCategories[Tax Tag],MATCH($K17,tblCategories[Category],0)),"")) | P17: =IF($C17="","",IF($G17=PersonA,1,IF($G17=PersonB,0,IFERROR(INDEX(tblCategories[Joint Split A],MATCH($K17,tblCategories[Category],0)),DefaultSplitA)))) | Q17: =IF($C17="","",ROUND($J17*N($P17),2)) | R17: =IF($C17="","",ROUND($J17-N($Q17),2)) | U17: sample-data | V17: SAMPLE | W17: 5C2C6966 | X17: =IF($C17="","",IFERROR(IF(_xlfn.ISFORMULA($K17),"Rule","Manual"),"")) | Y17: =IF($C17="","",IF(ReportView=PersonA,N($Q17),IF(ReportView=PersonB,N($R17),$J17)))
B18: =IF($C18="","","T"&TEXT(ROW()-ROW(tblTxn[[#Headers],[Txn ID]]),"000000")) | C18: 46090 | D18: =IF($C18="","",TEXT($C18,"yyyy-mm")) | E18: Amex Cobalt (Joint) | F18: =IF($C18="","",IFERROR(INDEX(tblAccounts[Owner],MATCH($E18,tblAccounts[Account],0)),"Joint")) | G18: =IF($C18="","",IF(HouseholdMode="Couple",IFERROR(IF(INDEX(tblCategories[Default Owner],MATCH($K18,tblCategories[Category],0))="",$F18,INDEX(tblCategories[Default Owner],MATCH($K18,tblCategories[Category],0))),$F18),$F18)) | H18: IDP PURCHASE - 5119 WINNERS #3424 ON | I18: =IF($H18="","",$H18) | J18: -48.55 | K18: =IF($H18="","",IFERROR(INDEX(tblRules[Category],SUMPRODUCT(MIN((1-((tblRules[Enabled]<>"No")*(tblRules[Pattern]<>"")*(tblRules[Category]<>"")*((tblRules[Flow]="Any")+(tblRules[Flow]="")+((tblRules[Flow]="Money out")*($J18<0))+((tblRules[Flow]="Money in")*($J18>0)))*(((tblRules[Look In]="Account")*ISNUMBER(SEARCH(tblRules[Pattern],$E18)))+((tblRules[Look In]<>"Account")*(((tblRules[Test]="Word")*ISNUMBER(SEARCH(" "&tblRules[Pattern]&" "," "&$H18&" ")))+((tblRules[Test]<>"Word")*ISNUMBER(SEARCH(tblRules[Pattern],$H18))))))>0))*1E+9+ROW(tblRules[Pattern])))-ROW(tblRules[[#Headers],[Pattern]])),"Uncategorized")) | L18: =IF($C18="","",IFERROR(INDEX(tblCategories[Group],MATCH($K18,tblCategories[Category],0)),"Other")) | M18: =IF($C18="","",IFERROR(INDEX(tblCategories[Type],MATCH($K18,tblCategories[Category],0)),IF($J18>0,"Income","Expense"))) | N18: =IF($C18="","",IFERROR(INDEX(tblCategories[Essential],MATCH($K18,tblCategories[Category],0)),"No")) | O18: =IF($C18="","",IFERROR(INDEX(tblCategories[Tax Tag],MATCH($K18,tblCategories[Category],0)),"")) | P18: =IF($C18="","",IF($G18=PersonA,1,IF($G18=PersonB,0,IFERROR(INDEX(tblCategories[Joint Split A],MATCH($K18,tblCategories[Category],0)),DefaultSplitA)))) | Q18: =IF($C18="","",ROUND($J18*N($P18),2)) | R18: =IF($C18="","",ROUND($J18-N($Q18),2)) | U18: sample-data | V18: SAMPLE | W18: 44D69BE1 | X18: =IF($C18="","",IFERROR(IF(_xlfn.ISFORMULA($K18),"Rule","Manual"),"")) | Y18: =IF($C18="","",IF(ReportView=PersonA,N($Q18),IF(ReportView=PersonB,N($R18),$J18)))
... B330: =IF($C330="","","T"&TEXT(ROW()-ROW(tblTxn[[#Headers],[Txn ID]]),"000000")) | C330: 46265 | D330: =IF($C330="","",TEXT($C330,"yyyy-mm")) | E330: RBC Chequing (Alex) | F330: =IF($C330="","",IFERROR(INDEX(tblAccounts[Owner],MATCH($E330,tblAccounts[Account],0)),"Joint")) | G330: =IF($C330="","",IF(HouseholdMode="Couple",IFERROR(IF(INDEX(tblCategories[Default Owner],MATCH($K330,tblCategories[Category],0))="",$F330,INDEX(tblCategories[Default Owner],MATCH($K330,tblCategories[Category],0))),$F330),$F330)) | H330: IDP PURCHASE - 6285 TIM HORTONS #3283 TORONTO ON | I330: =IF($H330="","",$H330) | J330: -10.53 | K330: =IF($H330="","",IFERROR(INDEX(tblRules[Category],SUMPRODUCT(MIN((1-((tblRules[Enabled]<>"No")*(tblRules[Pattern]<>"")*(tblRules[Category]<>"")*((tblRules[Flow]="Any")+(tblRules[Flow]="")+((tblRules[Flow]="Money out")*($J330<0))+((tblRules[Flow]="Money in")*($J330>0)))*(((tblRules[Look In]="Account")*ISNUMBER(SEARCH(tblRules[Pattern],$E330)))+((tblRules[Look In]<>"Account")*(((tblRules[Test]="Word")*ISNUMBER(SEARCH(" "&tblRules[Pattern]&" "," "&$H330&" ")))+((tblRules[Test]<>"Word")*ISNUMBER(SEARCH(tblRules[Pattern],$H330))))))>0))*1E+9+ROW(tblRules[Pattern])))-ROW(tblRules[[#Headers],[Pattern]])),"Uncategorized")) | L330: =IF($C330="","",IFERROR(INDEX(tblCategories[Group],MATCH($K330,tblCategories[Category],0)),"Other")) | M330: =IF($C330="","",IFERROR(INDEX(tblCategories[Type],MATCH($K330,tblCategories[Category],0)),IF($J330>0,"Income","Expense"))) | N330: =IF($C330="","",IFERROR(INDEX(tblCategories[Essential],MATCH($K330,tblCategories[Category],0)),"No")) | O330: =IF($C330="","",IFERROR(INDEX(tblCategories[Tax Tag],MATCH($K330,tblCategories[Category],0)),"")) | P330: =IF($C330="","",IF($G330=PersonA,1,IF($G330=PersonB,0,IFERROR(INDEX(tblCategories[Joint Split A],MATCH($K330,tblCategories[Category],0)),DefaultSplitA)))) | Q330: =IF($C330="","",ROUND($J330*N($P330),2)) | R330: =IF($C330="","",ROUND($J330-N($Q330),2)) | U330: sample-data | V330: SAMPLE | W330: D9DD2819 | X330: =IF($C330="","",IFERROR(IF(_xlfn.ISFORMULA($K330),"Rule","Manual"),"")) | Y330: =IF($C330="","",IF(ReportView=PersonA,N($Q330),IF(ReportView=PersonB,N($R330),$J330)))
B331: =IF($C331="","","T"&TEXT(ROW()-ROW(tblTxn[[#Headers],[Txn ID]]),"000000")) | D331: =IF($C331="","",TEXT($C331,"yyyy-mm")) | F331: =IF($C331="","",IFERROR(INDEX(tblAccounts[Owner],MATCH($E331,tblAccounts[Account],0)),"Joint")) | G331: =IF($C331="","",IF(HouseholdMode="Couple",IFERROR(IF(INDEX(tblCategories[Default Owner],MATCH($K331,tblCategories[Category],0))="",$F331,INDEX(tblCategories[Default Owner],MATCH($K331,tblCategories[Category],0))),$F331),$F331)) | I331: =IF($H331="","",$H331) | K331: =IF($H331="","",IFERROR(INDEX(tblRules[Category],SUMPRODUCT(MIN((1-((tblRules[Enabled]<>"No")*(tblRules[Pattern]<>"")*(tblRules[Category]<>"")*((tblRules[Flow]="Any")+(tblRules[Flow]="")+((tblRules[Flow]="Money out")*($J331<0))+((tblRules[Flow]="Money in")*($J331>0)))*(((tblRules[Look In]="Account")*ISNUMBER(SEARCH(tblRules[Pattern],$E331)))+((tblRules[Look In]<>"Account")*(((tblRules[Test]="Word")*ISNUMBER(SEARCH(" "&tblRules[Pattern]&" "," "&$H331&" ")))+((tblRules[Test]<>"Word")*ISNUMBER(SEARCH(tblRules[Pattern],$H331))))))>0))*1E+9+ROW(tblRules[Pattern])))-ROW(tblRules[[#Headers],[Pattern]])),"Uncategorized")) | L331: =IF($C331="","",IFERROR(INDEX(tblCategories[Group],MATCH($K331,tblCategories[Category],0)),"Other")) | M331: =IF($C331="","",IFERROR(INDEX(tblCategories[Type],MATCH($K331,tblCategories[Category],0)),IF($J331>0,"Income","Expense"))) | N331: =IF($C331="","",IFERROR(INDEX(tblCategories[Essential],MATCH($K331,tblCategories[Category],0)),"No")) | O331: =IF($C331="","",IFERROR(INDEX(tblCategories[Tax Tag],MATCH($K331,tblCategories[Category],0)),"")) | P331: =IF($C331="","",IF($G331=PersonA,1,IF($G331=PersonB,0,IFERROR(INDEX(tblCategories[Joint Split A],MATCH($K331,tblCategories[Category],0)),DefaultSplitA)))) | Q331: =IF($C331="","",ROUND($J331*N($P331),2)) | R331: =IF($C331="","",ROUND($J331-N($Q331),2)) | X331: =IF($C331="","",IFERROR(IF(_xlfn.ISFORMULA($K331),"Rule","Manual"),"")) | Y331: =IF($C331="","",IF(ReportView=PersonA,N($Q331),IF(ReportView=PersonB,N($R331),$J331)))
B332: =IF($C332="","","T"&TEXT(ROW()-ROW(tblTxn[[#Headers],[Txn ID]]),"000000")) | D332: =IF($C332="","",TEXT($C332,"yyyy-mm")) | F332: =IF($C332="","",IFERROR(INDEX(tblAccounts[Owner],MATCH($E332,tblAccounts[Account],0)),"Joint")) | G332: =IF($C332="","",IF(HouseholdMode="Couple",IFERROR(IF(INDEX(tblCategories[Default Owner],MATCH($K332,tblCategories[Category],0))="",$F332,INDEX(tblCategories[Default Owner],MATCH($K332,tblCategories[Category],0))),$F332),$F332)) | I332: =IF($H332="","",$H332) | K332: =IF($H332="","",IFERROR(INDEX(tblRules[Category],SUMPRODUCT(MIN((1-((tblRules[Enabled]<>"No")*(tblRules[Pattern]<>"")*(tblRules[Category]<>"")*((tblRules[Flow]="Any")+(tblRules[Flow]="")+((tblRules[Flow]="Money out")*($J332<0))+((tblRules[Flow]="Money in")*($J332>0)))*(((tblRules[Look In]="Account")*ISNUMBER(SEARCH(tblRules[Pattern],$E332)))+((tblRules[Look In]<>"Account")*(((tblRules[Test]="Word")*ISNUMBER(SEARCH(" "&tblRules[Pattern]&" "," "&$H332&" ")))+((tblRules[Test]<>"Word")*ISNUMBER(SEARCH(tblRules[Pattern],$H332))))))>0))*1E+9+ROW(tblRules[Pattern])))-ROW(tblRules[[#Headers],[Pattern]])),"Uncategorized")) | L332: =IF($C332="","",IFERROR(INDEX(tblCategories[Group],MATCH($K332,tblCategories[Category],0)),"Other")) | M332: =IF($C332="","",IFERROR(INDEX(tblCategories[Type],MATCH($K332,tblCategories[Category],0)),IF($J332>0,"Income","Expense"))) | N332: =IF($C332="","",IFERROR(INDEX(tblCategories[Essential],MATCH($K332,tblCategories[Category],0)),"No")) | O332: =IF($C332="","",IFERROR(INDEX(tblCategories[Tax Tag],MATCH($K332,tblCategories[Category],0)),"")) | P332: =IF($C332="","",IF($G332=PersonA,1,IF($G332=PersonB,0,IFERROR(INDEX(tblCategories[Joint Split A],MATCH($K332,tblCategories[Category],0)),DefaultSplitA)))) | Q332: =IF($C332="","",ROUND($J332*N($P332),2)) | R332: =IF($C332="","",ROUND($J332-N($Q332),2)) | X332: =IF($C332="","",IFERROR(IF(_xlfn.ISFORMULA($K332),"Rule","Manual"),"")) | Y332: =IF($C332="","",IF(ReportView=PersonA,N($Q332),IF(ReportView=PersonB,N($R332),$J332)))
B333: =IF($C333="","","T"&TEXT(ROW()-ROW(tblTxn[[#Headers],[Txn ID]]),"000000")) | D333: =IF($C333="","",TEXT($C333,"yyyy-mm")) | F333: =IF($C333="","",IFERROR(INDEX(tblAccounts[Owner],MATCH($E333,tblAccounts[Account],0)),"Joint")) | G333: =IF($C333="","",IF(HouseholdMode="Couple",IFERROR(IF(INDEX(tblCategories[Default Owner],MATCH($K333,tblCategories[Category],0))="",$F333,INDEX(tblCategories[Default Owner],MATCH($K333,tblCategories[Category],0))),$F333),$F333)) | I333: =IF($H333="","",$H333) | K333: =IF($H333="","",IFERROR(INDEX(tblRules[Category],SUMPRODUCT(MIN((1-((tblRules[Enabled]<>"No")*(tblRules[Pattern]<>"")*(tblRules[Category]<>"")*((tblRules[Flow]="Any")+(tblRules[Flow]="")+((tblRules[Flow]="Money out")*($J333<0))+((tblRules[Flow]="Money in")*($J333>0)))*(((tblRules[Look In]="Account")*ISNUMBER(SEARCH(tblRules[Pattern],$E333)))+((tblRules[Look In]<>"Account")*(((tblRules[Test]="Word")*ISNUMBER(SEARCH(" "&tblRules[Pattern]&" "," "&$H333&" ")))+((tblRules[Test]<>"Word")*ISNUMBER(SEARCH(tblRules[Pattern],$H333))))))>0))*1E+9+ROW(tblRules[Pattern])))-ROW(tblRules[[#Headers],[Pattern]])),"Uncategorized")) | L333: =IF($C333="","",IFERROR(INDEX(tblCategories[Group],MATCH($K333,tblCategories[Category],0)),"Other")) | M333: =IF($C333="","",IFERROR(INDEX(tblCategories[Type],MATCH($K333,tblCategories[Category],0)),IF($J333>0,"Income","Expense"))) | N333: =IF($C333="","",IFERROR(INDEX(tblCategories[Essential],MATCH($K333,tblCategories[Category],0)),"No")) | O333: =IF($C333="","",IFERROR(INDEX(tblCategories[Tax Tag],MATCH($K333,tblCategories[Category],0)),"")) | P333: =IF($C333="","",IF($G333=PersonA,1,IF($G333=PersonB,0,IFERROR(INDEX(tblCategories[Joint Split A],MATCH($K333,tblCategories[Category],0)),DefaultSplitA)))) | Q333: =IF($C333="","",ROUND($J333*N($P333),2)) | R333: =IF($C333="","",ROUND($J333-N($Q333),2)) | X333: =IF($C333="","",IFERROR(IF(_xlfn.ISFORMULA($K333),"Rule","Manual"),"")) | Y333: =IF($C333="","",IF(ReportView=PersonA,N($Q333),IF(ReportView=PersonB,N($R333),$J333)))
B334: =IF($C334="","","T"&TEXT(ROW()-ROW(tblTxn[[#Headers],[Txn ID]]),"000000")) | D334: =IF($C334="","",TEXT($C334,"yyyy-mm")) | F334: =IF($C334="","",IFERROR(INDEX(tblAccounts[Owner],MATCH($E334,tblAccounts[Account],0)),"Joint")) | G334: =IF($C334="","",IF(HouseholdMode="Couple",IFERROR(IF(INDEX(tblCategories[Default Owner],MATCH($K334,tblCategories[Category],0))="",$F334,INDEX(tblCategories[Default Owner],MATCH($K334,tblCategories[Category],0))),$F334),$F334)) | I334: =IF($H334="","",$H334) | K334: =IF($H334="","",IFERROR(INDEX(tblRules[Category],SUMPRODUCT(MIN((1-((tblRules[Enabled]<>"No")*(tblRules[Pattern]<>"")*(tblRules[Category]<>"")*((tblRules[Flow]="Any")+(tblRules[Flow]="")+((tblRules[Flow]="Money out")*($J334<0))+((tblRules[Flow]="Money in")*($J334>0)))*(((tblRules[Look In]="Account")*ISNUMBER(SEARCH(tblRules[Pattern],$E334)))+((tblRules[Look In]<>"Account")*(((tblRules[Test]="Word")*ISNUMBER(SEARCH(" "&tblRules[Pattern]&" "," "&$H334&" ")))+((tblRules[Test]<>"Word")*ISNUMBER(SEARCH(tblRules[Pattern],$H334))))))>0))*1E+9+ROW(tblRules[Pattern])))-ROW(tblRules[[#Headers],[Pattern]])),"Uncategorized")) | L334: =IF($C334="","",IFERROR(INDEX(tblCategories[Group],MATCH($K334,tblCategories[Category],0)),"Other")) | M334: =IF($C334="","",IFERROR(INDEX(tblCategories[Type],MATCH($K334,tblCategories[Category],0)),IF($J334>0,"Income","Expense"))) | N334: =IF($C334="","",IFERROR(INDEX(tblCategories[Essential],MATCH($K334,tblCategories[Category],0)),"No")) | O334: =IF($C334="","",IFERROR(INDEX(tblCategories[Tax Tag],MATCH($K334,tblCategories[Category],0)),"")) | P334: =IF($C334="","",IF($G334=PersonA,1,IF($G334=PersonB,0,IFERROR(INDEX(tblCategories[Joint Split A],MATCH($K334,tblCategories[Category],0)),DefaultSplitA)))) | Q334: =IF($C334="","",ROUND($J334*N($P334),2)) | R334: =IF($C334="","",ROUND($J334-N($Q334),2)) | X334: =IF($C334="","",IFERROR(IF(_xlfn.ISFORMULA($K334),"Rule","Manual"),"")) | Y334: =IF($C334="","",IF(ReportView=PersonA,N($Q334),IF(ReportView=PersonB,N($R334),$J334)))
B335: =IF($C335="","","T"&TEXT(ROW()-ROW(tblTxn[[#Headers],[Txn ID]]),"000000")) | D335: =IF($C335="","",TEXT($C335,"yyyy-mm")) | F335: =IF($C335="","",IFERROR(INDEX(tblAccounts[Owner],MATCH($E335,tblAccounts[Account],0)),"Joint")) | G335: =IF($C335="","",IF(HouseholdMode="Couple",IFERROR(IF(INDEX(tblCategories[Default Owner],MATCH($K335,tblCategories[Category],0))="",$F335,INDEX(tblCategories[Default Owner],MATCH($K335,tblCategories[Category],0))),$F335),$F335)) | I335: =IF($H335="","",$H335) | K335: =IF($H335="","",IFERROR(INDEX(tblRules[Category],SUMPRODUCT(MIN((1-((tblRules[Enabled]<>"No")*(tblRules[Pattern]<>"")*(tblRules[Category]<>"")*((tblRules[Flow]="Any")+(tblRules[Flow]="")+((tblRules[Flow]="Money out")*($J335<0))+((tblRules[Flow]="Money in")*($J335>0)))*(((tblRules[Look In]="Account")*ISNUMBER(SEARCH(tblRules[Pattern],$E335)))+((tblRules[Look In]<>"Account")*(((tblRules[Test]="Word")*ISNUMBER(SEARCH(" "&tblRules[Pattern]&" "," "&$H335&" ")))+((tblRules[Test]<>"Word")*ISNUMBER(SEARCH(tblRules[Pattern],$H335))))))>0))*1E+9+ROW(tblRules[Pattern])))-ROW(tblRules[[#Headers],[Pattern]])),"Uncategorized")) | L335: =IF($C335="","",IFERROR(INDEX(tblCategories[Group],MATCH($K335,tblCategories[Category],0)),"Other")) | M335: =IF($C335="","",IFERROR(INDEX(tblCategories[Type],MATCH($K335,tblCategories[Category],0)),IF($J335>0,"Income","Expense"))) | N335: =IF($C335="","",IFERROR(INDEX(tblCategories[Essential],MATCH($K335,tblCategories[Category],0)),"No")) | O335: =IF($C335="","",IFERROR(INDEX(tblCategories[Tax Tag],MATCH($K335,tblCategories[Category],0)),"")) | P335: =IF($C335="","",IF($G335=PersonA,1,IF($G335=PersonB,0,IFERROR(INDEX(tblCategories[Joint Split A],MATCH($K335,tblCategories[Category],0)),DefaultSplitA)))) | Q335: =IF($C335="","",ROUND($J335*N($P335),2)) | R335: =IF($C335="","",ROUND($J335-N($Q335),2)) | X335: =IF($C335="","",IFERROR(IF(_xlfn.ISFORMULA($K335),"Rule","Manual"),"")) | Y335: =IF($C335="","",IF(ReportView=PersonA,N($Q335),IF(ReportView=PersonB,N($R335),$J335)))
B336: =IF($C336="","","T"&TEXT(ROW()-ROW(tblTxn[[#Headers],[Txn ID]]),"000000")) | D336: =IF($C336="","",TEXT($C336,"yyyy-mm")) | F336: =IF($C336="","",IFERROR(INDEX(tblAccounts[Owner],MATCH($E336,tblAccounts[Account],0)),"Joint")) | G336: =IF($C336="","",IF(HouseholdMode="Couple",IFERROR(IF(INDEX(tblCategories[Default Owner],MATCH($K336,tblCategories[Category],0))="",$F336,INDEX(tblCategories[Default Owner],MATCH($K336,tblCategories[Category],0))),$F336),$F336)) | I336: =IF($H336="","",$H336) | K336: =IF($H336="","",IFERROR(INDEX(tblRules[Category],SUMPRODUCT(MIN((1-((tblRules[Enabled]<>"No")*(tblRules[Pattern]<>"")*(tblRules[Category]<>"")*((tblRules[Flow]="Any")+(tblRules[Flow]="")+((tblRules[Flow]="Money out")*($J336<0))+((tblRules[Flow]="Money in")*($J336>0)))*(((tblRules[Look In]="Account")*ISNUMBER(SEARCH(tblRules[Pattern],$E336)))+((tblRules[Look In]<>"Account")*(((tblRules[Test]="Word")*ISNUMBER(SEARCH(" "&tblRules[Pattern]&" "," "&$H336&" ")))+((tblRules[Test]<>"Word")*ISNUMBER(SEARCH(tblRules[Pattern],$H336))))))>0))*1E+9+ROW(tblRules[Pattern])))-ROW(tblRules[[#Headers],[Pattern]])),"Uncategorized")) | L336: =IF($C336="","",IFERROR(INDEX(tblCategories[Group],MATCH($K336,tblCategories[Category],0)),"Other")) | M336: =IF($C336="","",IFERROR(INDEX(tblCategories[Type],MATCH($K336,tblCategories[Category],0)),IF($J336>0,"Income","Expense"))) | N336: =IF($C336="","",IFERROR(INDEX(tblCategories[Essential],MATCH($K336,tblCategories[Category],0)),"No")) | O336: =IF($C336="","",IFERROR(INDEX(tblCategories[Tax Tag],MATCH($K336,tblCategories[Category],0)),"")) | P336: =IF($C336="","",IF($G336=PersonA,1,IF($G336=PersonB,0,IFERROR(INDEX(tblCategories[Joint Split A],MATCH($K336,tblCategories[Category],0)),DefaultSplitA)))) | Q336: =IF($C336="","",ROUND($J336*N($P336),2)) | R336: =IF($C336="","",ROUND($J336-N($Q336),2)) | X336: =IF($C336="","",IFERROR(IF(_xlfn.ISFORMULA($K336),"Rule","Manual"),"")) | Y336: =IF($C336="","",IF(ReportView=PersonA,N($Q336),IF(ReportView=PersonB,N($R336),$J336)))
B337: =IF($C337="","","T"&TEXT(ROW()-ROW(tblTxn[[#Headers],[Txn ID]]),"000000")) | D337: =IF($C337="","",TEXT($C337,"yyyy-mm")) | F337: =IF($C337="","",IFERROR(INDEX(tblAccounts[Owner],MATCH($E337,tblAccounts[Account],0)),"Joint")) | G337: =IF($C337="","",IF(HouseholdMode="Couple",IFERROR(IF(INDEX(tblCategories[Default Owner],MATCH($K337,tblCategories[Category],0))="",$F337,INDEX(tblCategories[Default Owner],MATCH($K337,tblCategories[Category],0))),$F337),$F337)) | I337: =IF($H337="","",$H337) | K337: =IF($H337="","",IFERROR(INDEX(tblRules[Category],SUMPRODUCT(MIN((1-((tblRules[Enabled]<>"No")*(tblRules[Pattern]<>"")*(tblRules[Category]<>"")*((tblRules[Flow]="Any")+(tblRules[Flow]="")+((tblRules[Flow]="Money out")*($J337<0))+((tblRules[Flow]="Money in")*($J337>0)))*(((tblRules[Look In]="Account")*ISNUMBER(SEARCH(tblRules[Pattern],$E337)))+((tblRules[Look In]<>"Account")*(((tblRules[Test]="Word")*ISNUMBER(SEARCH(" "&tblRules[Pattern]&" "," "&$H337&" ")))+((tblRules[Test]<>"Word")*ISNUMBER(SEARCH(tblRules[Pattern],$H337))))))>0))*1E+9+ROW(tblRules[Pattern])))-ROW(tblRules[[#Headers],[Pattern]])),"Uncategorized")) | L337: =IF($C337="","",IFERROR(INDEX(tblCategories[Group],MATCH($K337,tblCategories[Category],0)),"Other")) | M337: =IF($C337="","",IFERROR(INDEX(tblCategories[Type],MATCH($K337,tblCategories[Category],0)),IF($J337>0,"Income","Expense"))) | N337: =IF($C337="","",IFERROR(INDEX(tblCategories[Essential],MATCH($K337,tblCategories[Category],0)),"No")) | O337: =IF($C337="","",IFERROR(INDEX(tblCategories[Tax Tag],MATCH($K337,tblCategories[Category],0)),"")) | P337: =IF($C337="","",IF($G337=PersonA,1,IF($G337=PersonB,0,IFERROR(INDEX(tblCategories[Joint Split A],MATCH($K337,tblCategories[Category],0)),DefaultSplitA)))) | Q337: =IF($C337="","",ROUND($J337*N($P337),2)) | R337: =IF($C337="","",ROUND($J337-N($Q337),2)) | X337: =IF($C337="","",IFERROR(IF(_xlfn.ISFORMULA($K337),"Rule","Manual"),"")) | Y337: =IF($C337="","",IF(ReportView=PersonA,N($Q337),IF(ReportView=PersonB,N($R337),$J337)))
B338: =IF($C338="","","T"&TEXT(ROW()-ROW(tblTxn[[#Headers],[Txn ID]]),"000000")) | D338: =IF($C338="","",TEXT($C338,"yyyy-mm")) | F338: =IF($C338="","",IFERROR(INDEX(tblAccounts[Owner],MATCH($E338,tblAccounts[Account],0)),"Joint")) | G338: =IF($C338="","",IF(HouseholdMode="Couple",IFERROR(IF(INDEX(tblCategories[Default Owner],MATCH($K338,tblCategories[Category],0))="",$F338,INDEX(tblCategories[Default Owner],MATCH($K338,tblCategories[Category],0))),$F338),$F338)) | I338: =IF($H338="","",$H338) | K338: =IF($H338="","",IFERROR(INDEX(tblRules[Category],SUMPRODUCT(MIN((1-((tblRules[Enabled]<>"No")*(tblRules[Pattern]<>"")*(tblRules[Category]<>"")*((tblRules[Flow]="Any")+(tblRules[Flow]="")+((tblRules[Flow]="Money out")*($J338<0))+((tblRules[Flow]="Money in")*($J338>0)))*(((tblRules[Look In]="Account")*ISNUMBER(SEARCH(tblRules[Pattern],$E338)))+((tblRules[Look In]<>"Account")*(((tblRules[Test]="Word")*ISNUMBER(SEARCH(" "&tblRules[Pattern]&" "," "&$H338&" ")))+((tblRules[Test]<>"Word")*ISNUMBER(SEARCH(tblRules[Pattern],$H338))))))>0))*1E+9+ROW(tblRules[Pattern])))-ROW(tblRules[[#Headers],[Pattern]])),"Uncategorized")) | L338: =IF($C338="","",IFERROR(INDEX(tblCategories[Group],MATCH($K338,tblCategories[Category],0)),"Other")) | M338: =IF($C338="","",IFERROR(INDEX(tblCategories[Type],MATCH($K338,tblCategories[Category],0)),IF($J338>0,"Income","Expense"))) | N338: =IF($C338="","",IFERROR(INDEX(tblCategories[Essential],MATCH($K338,tblCategories[Category],0)),"No")) | O338: =IF($C338="","",IFERROR(INDEX(tblCategories[Tax Tag],MATCH($K338,tblCategories[Category],0)),"")) | P338: =IF($C338="","",IF($G338=PersonA,1,IF($G338=PersonB,0,IFERROR(INDEX(tblCategories[Joint Split A],MATCH($K338,tblCategories[Category],0)),DefaultSplitA)))) | Q338: =IF($C338="","",ROUND($J338*N($P338),2)) | R338: =IF($C338="","",ROUND($J338-N($Q338),2)) | X338: =IF($C338="","",IFERROR(IF(_xlfn.ISFORMULA($K338),"Rule","Manual"),"")) | Y338: =IF($C338="","",IF(ReportView=PersonA,N($Q338),IF(ReportView=PersonB,N($R338),$J338)))
B339: =IF($C339="","","T"&TEXT(ROW()-ROW(tblTxn[[#Headers],[Txn ID]]),"000000")) | D339: =IF($C339="","",TEXT($C339,"yyyy-mm")) | F339: =IF($C339="","",IFERROR(INDEX(tblAccounts[Owner],MATCH($E339,tblAccounts[Account],0)),"Joint")) | G339: =IF($C339="","",IF(HouseholdMode="Couple",IFERROR(IF(INDEX(tblCategories[Default Owner],MATCH($K339,tblCategories[Category],0))="",$F339,INDEX(tblCategories[Default Owner],MATCH($K339,tblCategories[Category],0))),$F339),$F339)) | I339: =IF($H339="","",$H339) | K339: =IF($H339="","",IFERROR(INDEX(tblRules[Category],SUMPRODUCT(MIN((1-((tblRules[Enabled]<>"No")*(tblRules[Pattern]<>"")*(tblRules[Category]<>"")*((tblRules[Flow]="Any")+(tblRules[Flow]="")+((tblRules[Flow]="Money out")*($J339<0))+((tblRules[Flow]="Money in")*($J339>0)))*(((tblRules[Look In]="Account")*ISNUMBER(SEARCH(tblRules[Pattern],$E339)))+((tblRules[Look In]<>"Account")*(((tblRules[Test]="Word")*ISNUMBER(SEARCH(" "&tblRules[Pattern]&" "," "&$H339&" ")))+((tblRules[Test]<>"Word")*ISNUMBER(SEARCH(tblRules[Pattern],$H339))))))>0))*1E+9+ROW(tblRules[Pattern])))-ROW(tblRules[[#Headers],[Pattern]])),"Uncategorized")) | L339: =IF($C339="","",IFERROR(INDEX(tblCategories[Group],MATCH($K339,tblCategories[Category],0)),"Other")) | M339: =IF($C339="","",IFERROR(INDEX(tblCategories[Type],MATCH($K339,tblCategories[Category],0)),IF($J339>0,"Income","Expense"))) | N339: =IF($C339="","",IFERROR(INDEX(tblCategories[Essential],MATCH($K339,tblCategories[Category],0)),"No")) | O339: =IF($C339="","",IFERROR(INDEX(tblCategories[Tax Tag],MATCH($K339,tblCategories[Category],0)),"")) | P339: =IF($C339="","",IF($G339=PersonA,1,IF($G339=PersonB,0,IFERROR(INDEX(tblCategories[Joint Split A],MATCH($K339,tblCategories[Category],0)),DefaultSplitA)))) | Q339: =IF($C339="","",ROUND($J339*N($P339),2)) | R339: =IF($C339="","",ROUND($J339-N($Q339),2)) | X339: =IF($C339="","",IFERROR(IF(_xlfn.ISFORMULA($K339),"Rule","Manual"),"")) | Y339: =IF($C339="","",IF(ReportView=PersonA,N($Q339),IF(ReportView=PersonB,N($R339),$J339)))
B340: =IF($C340="","","T"&TEXT(ROW()-ROW(tblTxn[[#Headers],[Txn ID]]),"000000")) | D340: =IF($C340="","",TEXT($C340,"yyyy-mm")) | F340: =IF($C340="","",IFERROR(INDEX(tblAccounts[Owner],MATCH($E340,tblAccounts[Account],0)),"Joint")) | G340: =IF($C340="","",IF(HouseholdMode="Couple",IFERROR(IF(INDEX(tblCategories[Default Owner],MATCH($K340,tblCategories[Category],0))="",$F340,INDEX(tblCategories[Default Owner],MATCH($K340,tblCategories[Category],0))),$F340),$F340)) | I340: =IF($H340="","",$H340) | K340: =IF($H340="","",IFERROR(INDEX(tblRules[Category],SUMPRODUCT(MIN((1-((tblRules[Enabled]<>"No")*(tblRules[Pattern]<>"")*(tblRules[Category]<>"")*((tblRules[Flow]="Any")+(tblRules[Flow]="")+((tblRules[Flow]="Money out")*($J340<0))+((tblRules[Flow]="Money in")*($J340>0)))*(((tblRules[Look In]="Account")*ISNUMBER(SEARCH(tblRules[Pattern],$E340)))+((tblRules[Look In]<>"Account")*(((tblRules[Test]="Word")*ISNUMBER(SEARCH(" "&tblRules[Pattern]&" "," "&$H340&" ")))+((tblRules[Test]<>"Word")*ISNUMBER(SEARCH(tblRules[Pattern],$H340))))))>0))*1E+9+ROW(tblRules[Pattern])))-ROW(tblRules[[#Headers],[Pattern]])),"Uncategorized")) | L340: =IF($C340="","",IFERROR(INDEX(tblCategories[Group],MATCH($K340,tblCategories[Category],0)),"Other")) | M340: =IF($C340="","",IFERROR(INDEX(tblCategories[Type],MATCH($K340,tblCategories[Category],0)),IF($J340>0,"Income","Expense"))) | N340: =IF($C340="","",IFERROR(INDEX(tblCategories[Essential],MATCH($K340,tblCategories[Category],0)),"No")) | O340: =IF($C340="","",IFERROR(INDEX(tblCategories[Tax Tag],MATCH($K340,tblCategories[Category],0)),"")) | P340: =IF($C340="","",IF($G340=PersonA,1,IF($G340=PersonB,0,IFERROR(INDEX(tblCategories[Joint Split A],MATCH($K340,tblCategories[Category],0)),DefaultSplitA)))) | Q340: =IF($C340="","",ROUND($J340*N($P340),2)) | R340: =IF($C340="","",ROUND($J340-N($Q340),2)) | X340: =IF($C340="","",IFERROR(IF(_xlfn.ISFORMULA($K340),"Rule","Manual"),"")) | Y340: =IF($C340="","",IF(ReportView=PersonA,N($Q340),IF(ReportView=PersonB,N($R340),$J340)))
B341: =IF($C341="","","T"&TEXT(ROW()-ROW(tblTxn[[#Headers],[Txn ID]]),"000000")) | D341: =IF($C341="","",TEXT($C341,"yyyy-mm")) | F341: =IF($C341="","",IFERROR(INDEX(tblAccounts[Owner],MATCH($E341,tblAccounts[Account],0)),"Joint")) | G341: =IF($C341="","",IF(HouseholdMode="Couple",IFERROR(IF(INDEX(tblCategories[Default Owner],MATCH($K341,tblCategories[Category],0))="",$F341,INDEX(tblCategories[Default Owner],MATCH($K341,tblCategories[Category],0))),$F341),$F341)) | I341: =IF($H341="","",$H341) | K341: =IF($H341="","",IFERROR(INDEX(tblRules[Category],SUMPRODUCT(MIN((1-((tblRules[Enabled]<>"No")*(tblRules[Pattern]<>"")*(tblRules[Category]<>"")*((tblRules[Flow]="Any")+(tblRules[Flow]="")+((tblRules[Flow]="Money out")*($J341<0))+((tblRules[Flow]="Money in")*($J341>0)))*(((tblRules[Look In]="Account")*ISNUMBER(SEARCH(tblRules[Pattern],$E341)))+((tblRules[Look In]<>"Account")*(((tblRules[Test]="Word")*ISNUMBER(SEARCH(" "&tblRules[Pattern]&" "," "&$H341&" ")))+((tblRules[Test]<>"Word")*ISNUMBER(SEARCH(tblRules[Pattern],$H341))))))>0))*1E+9+ROW(tblRules[Pattern])))-ROW(tblRules[[#Headers],[Pattern]])),"Uncategorized")) | L341: =IF($C341="","",IFERROR(INDEX(tblCategories[Group],MATCH($K341,tblCategories[Category],0)),"Other")) | M341: =IF($C341="","",IFERROR(INDEX(tblCategories[Type],MATCH($K341,tblCategories[Category],0)),IF($J341>0,"Income","Expense"))) | N341: =IF($C341="","",IFERROR(INDEX(tblCategories[Essential],MATCH($K341,tblCategories[Category],0)),"No")) | O341: =IF($C341="","",IFERROR(INDEX(tblCategories[Tax Tag],MATCH($K341,tblCategories[Category],0)),"")) | P341: =IF($C341="","",IF($G341=PersonA,1,IF($G341=PersonB,0,IFERROR(INDEX(tblCategories[Joint Split A],MATCH($K341,tblCategories[Category],0)),DefaultSplitA)))) | Q341: =IF($C341="","",ROUND($J341*N($P341),2)) | R341: =IF($C341="","",ROUND($J341-N($Q341),2)) | X341: =IF($C341="","",IFERROR(IF(_xlfn.ISFORMULA($K341),"Rule","Manual"),"")) | Y341: =IF($C341="","",IF(ReportView=PersonA,N($Q341),IF(ReportView=PersonB,N($R341),$J341)))
B342: =IF($C342="","","T"&TEXT(ROW()-ROW(tblTxn[[#Headers],[Txn ID]]),"000000")) | D342: =IF($C342="","",TEXT($C342,"yyyy-mm")) | F342: =IF($C342="","",IFERROR(INDEX(tblAccounts[Owner],MATCH($E342,tblAccounts[Account],0)),"Joint")) | G342: =IF($C342="","",IF(HouseholdMode="Couple",IFERROR(IF(INDEX(tblCategories[Default Owner],MATCH($K342,tblCategories[Category],0))="",$F342,INDEX(tblCategories[Default Owner],MATCH($K342,tblCategories[Category],0))),$F342),$F342)) | I342: =IF($H342="","",$H342) | K342: =IF($H342="","",IFERROR(INDEX(tblRules[Category],SUMPRODUCT(MIN((1-((tblRules[Enabled]<>"No")*(tblRules[Pattern]<>"")*(tblRules[Category]<>"")*((tblRules[Flow]="Any")+(tblRules[Flow]="")+((tblRules[Flow]="Money out")*($J342<0))+((tblRules[Flow]="Money in")*($J342>0)))*(((tblRules[Look In]="Account")*ISNUMBER(SEARCH(tblRules[Pattern],$E342)))+((tblRules[Look In]<>"Account")*(((tblRules[Test]="Word")*ISNUMBER(SEARCH(" "&tblRules[Pattern]&" "," "&$H342&" ")))+((tblRules[Test]<>"Word")*ISNUMBER(SEARCH(tblRules[Pattern],$H342))))))>0))*1E+9+ROW(tblRules[Pattern])))-ROW(tblRules[[#Headers],[Pattern]])),"Uncategorized")) | L342: =IF($C342="","",IFERROR(INDEX(tblCategories[Group],MATCH($K342,tblCategories[Category],0)),"Other")) | M342: =IF($C342="","",IFERROR(INDEX(tblCategories[Type],MATCH($K342,tblCategories[Category],0)),IF($J342>0,"Income","Expense"))) | N342: =IF($C342="","",IFERROR(INDEX(tblCategories[Essential],MATCH($K342,tblCategories[Category],0)),"No")) | O342: =IF($C342="","",IFERROR(INDEX(tblCategories[Tax Tag],MATCH($K342,tblCategories[Category],0)),"")) | P342: =IF($C342="","",IF($G342=PersonA,1,IF($G342=PersonB,0,IFERROR(INDEX(tblCategories[Joint Split A],MATCH($K342,tblCategories[Category],0)),DefaultSplitA)))) | Q342: =IF($C342="","",ROUND($J342*N($P342),2)) | R342: =IF($C342="","",ROUND($J342-N($Q342),2)) | X342: =IF($C342="","",IFERROR(IF(_xlfn.ISFORMULA($K342),"Rule","Manual"),"")) | Y342: =IF($C342="","",IF(ReportView=PersonA,N($Q342),IF(ReportView=PersonB,N($R342),$J342)))
... B530: =IF($C530="","","T"&TEXT(ROW()-ROW(tblTxn[[#Headers],[Txn ID]]),"000000")) | D530: =IF($C530="","",TEXT($C530,"yyyy-mm")) | F530: =IF($C530="","",IFERROR(INDEX(tblAccounts[Owner],MATCH($E530,tblAccounts[Account],0)),"Joint")) | G530: =IF($C530="","",IF(HouseholdMode="Couple",IFERROR(IF(INDEX(tblCategories[Default Owner],MATCH($K530,tblCategories[Category],0))="",$F530,INDEX(tblCategories[Default Owner],MATCH($K530,tblCategories[Category],0))),$F530),$F530)) | I530: =IF($H530="","",$H530) | K530: =IF($H530="","",IFERROR(INDEX(tblRules[Category],SUMPRODUCT(MIN((1-((tblRules[Enabled]<>"No")*(tblRules[Pattern]<>"")*(tblRules[Category]<>"")*((tblRules[Flow]="Any")+(tblRules[Flow]="")+((tblRules[Flow]="Money out")*($J530<0))+((tblRules[Flow]="Money in")*($J530>0)))*(((tblRules[Look In]="Account")*ISNUMBER(SEARCH(tblRules[Pattern],$E530)))+((tblRules[Look In]<>"Account")*(((tblRules[Test]="Word")*ISNUMBER(SEARCH(" "&tblRules[Pattern]&" "," "&$H530&" ")))+((tblRules[Test]<>"Word")*ISNUMBER(SEARCH(tblRules[Pattern],$H530))))))>0))*1E+9+ROW(tblRules[Pattern])))-ROW(tblRules[[#Headers],[Pattern]])),"Uncategorized")) | L530: =IF($C530="","",IFERROR(INDEX(tblCategories[Group],MATCH($K530,tblCategories[Category],0)),"Other")) | M530: =IF($C530="","",IFERROR(INDEX(tblCategories[Type],MATCH($K530,tblCategories[Category],0)),IF($J530>0,"Income","Expense"))) | N530: =IF($C530="","",IFERROR(INDEX(tblCategories[Essential],MATCH($K530,tblCategories[Category],0)),"No")) | O530: =IF($C530="","",IFERROR(INDEX(tblCategories[Tax Tag],MATCH($K530,tblCategories[Category],0)),"")) | P530: =IF($C530="","",IF($G530=PersonA,1,IF($G530=PersonB,0,IFERROR(INDEX(tblCategories[Joint Split A],MATCH($K530,tblCategories[Category],0)),DefaultSplitA)))) | Q530: =IF($C530="","",ROUND($J530*N($P530),2)) | R530: =IF($C530="","",ROUND($J530-N($Q530),2)) | X530: =IF($C530="","",IFERROR(IF(_xlfn.ISFORMULA($K530),"Rule","Manual"),"")) | Y530: =IF($C530="","",IF(ReportView=PersonA,N($Q530),IF(ReportView=PersonB,N($R530),$J530)))

Sheet Accounts
B1: Accounts
B2: One row per bank or card account. The Owner is who "Paid By" names when a transaction uses that account. Bank Format and File Name Contains are only used by the macro-enabled edition.
B4: Account | C4: Institution | D4: Type | E4: Owner | F4: Bank Format | G4: File Name Contains | H4: Include in Household | I4: Notes
B5: RBC Chequing (Alex) | C5: RBC Royal Bank | D5: Chequing | E5: Alex | F5: RBC Chequing/Savings/Card | G5: rbc-chequing-alex | H5: Yes | I5: Sample account
B6: Tangerine Chequing (Sam) | C6: Tangerine | D6: Chequing | E6: Sam | F6: Tangerine | G6: tangerine-chequing-sam | H6: Yes | I6: Sample account
B7: BMO Joint Chequing | C7: BMO | D7: Chequing | E7: Joint | F7: BMO | G7: bmo-joint-chequing | H7: Yes | I7: Sample account
B8: Amex Cobalt (Joint) | C8: American Express | D8: Credit Card | E8: Joint | F8: Amex Canada | G8: amex-cobalt-joint | H8: Yes | I8: Sample account

Sheet Categories
B1: Categories
B2: Add your own rows freely. Type drives the reports: Income and Expense count in cash flow, Saving is money you kept, Transfer is ignored. "Default Owner" decides whose expense it is when the rules categorise a row, and "Joint Split A" overrides the household split for one category.
B4: Category | C4: Group | D4: Type | E4: Essential | F4: Tax Tag | G4: Monthly Budget | H4: Default Owner | I4: Joint Split A | J4: Notes
B5: Employment Income | C5: Income | D5: Income | E5: Yes | I5: =DefaultSplitA | J5: Net pay after source deductions
B6: Bonus & Commission | C6: Income | D6: Income | E6: No | I6: =DefaultSplitA
B7: Self-Employment Income | C7: Income | D7: Income | E7: No | F7: Business income | I7: =DefaultSplitA | J7: T2125
B8: EI Benefits | C8: Income | D8: Income | E8: Yes | I8: =DefaultSplitA
B9: CPP / OAS | C9: Income | D9: Income | E9: Yes | I9: =DefaultSplitA
B10: Canada Child Benefit | C10: Income | D10: Income | E10: Yes | H10: Joint | I10: =DefaultSplitA | J10: Tax free
B11: GST/HST Credit | C11: Income | D11: Income | E11: No | I11: =DefaultSplitA | J11: Tax free
B12: Canada Carbon Rebate | C12: Income | D12: Income | E12: No | I12: =DefaultSplitA | J12: Where it still applies
B13: Tax Refund (CRA) | C13: Income | D13: Income | E13: No | I13: =DefaultSplitA
B14: Investment Income | C14: Income | D14: Income | E14: No | F14: Investment income | I14: =DefaultSplitA | J14: T5 / T3
B15: Rental Income | C15: Income | D15: Income | E15: No | F15: Rental income | I15: =DefaultSplitA | J15: T776
B16: Interest Earned | C16: Income | D16: Income | E16: No | F16: Investment income | I16: =DefaultSplitA
B17: Gifts Received | C17: Income | D17: Income | E17: No | I17: =DefaultSplitA
B18: Other Income | C18: Income | D18: Income | E18: No | I18: =DefaultSplitA
B19: Rent | C19: Housing | D19: Expense | E19: Yes | H19: Joint | I19: =DefaultSplitA
B20: Mortgage Payment | C20: Housing | D20: Expense | E20: Yes | H20: Joint | I20: =DefaultSplitA | J20: Principal plus interest
B21: Property Tax | C21: Housing | D21: Expense | E21: Yes | H21: Joint | I21: =DefaultSplitA
B22: Condo / Strata Fees | C22: Housing | D22: Expense | E22: Yes | H22: Joint | I22: =DefaultSplitA
B23: Home Insurance | C23: Housing | D23: Expense | E23: Yes | H23: Joint | I23: =DefaultSplitA
B24: Home Maintenance | C24: Housing | D24: Expense | E24: Yes | H24: Joint | I24: =DefaultSplitA
B25: Home Improvement | C25: Housing | D25: Expense | E25: No | H25: Joint | I25: =DefaultSplitA
B26: Furniture & Housewares | C26: Housing | D26: Expense | E26: No | H26: Joint | I26: =DefaultSplitA
B27: Electricity / Hydro | C27: Utilities | D27: Expense | E27: Yes | H27: Joint | I27: =DefaultSplitA
B28: Natural Gas / Heating | C28: Utilities | D28: Expense | E28: Yes | H28: Joint | I28: =DefaultSplitA
B29: Water & Sewer | C29: Utilities | D29: Expense | E29: Yes | H29: Joint | I29: =DefaultSplitA
B30: Internet | C30: Utilities | D30: Expense | E30: Yes | H30: Joint | I30: =DefaultSplitA
B31: Mobile Phone | C31: Utilities | D31: Expense | E31: Yes | I31: =DefaultSplitA
B32: Groceries | C32: Food | D32: Expense | E32: Yes | H32: Joint | I32: =DefaultSplitA
B33: Restaurants & Takeout | C33: Food | D33: Expense | E33: No | H33: Joint | I33: =DefaultSplitA
B34: Coffee & Snacks | C34: Food | D34: Expense | E34: No | I34: =DefaultSplitA
B35: Alcohol | C35: Food | D35: Expense | E35: No | I35: =DefaultSplitA | J35: LCBO, SAQ, BC Liquor, ANBL
B36: Cannabis | C36: Food | D36: Expense | E36: No | I36: =DefaultSplitA
B37: Fuel | C37: Transportation | D37: Expense | E37: Yes | H37: Joint | I37: =DefaultSplitA
B38: Auto Insurance | C38: Transportation | D38: Expense | E38: Yes | H38: Joint | I38: =DefaultSplitA
B39: Auto Maintenance | C39: Transportation | D39: Expense | E39: Yes | H39: Joint | I39: =DefaultSplitA
B40: Vehicle Payment | C40: Transportation | D40: Expense | E40: Yes | H40: Joint | I40: =DefaultSplitA | J40: Loan or lease
B41: Vehicle Registration | C41: Transportation | D41: Expense | E41: Yes | H41: Joint | I41: =DefaultSplitA
B42: Public Transit | C42: Transportation | D42: Expense | E42: Yes | I42: =DefaultSplitA | J42: Presto, Compass, OPUS
B43: Taxi & Rideshare | C43: Transportation | D43: Expense | E43: No | I43: =DefaultSplitA
B44: Parking & Tolls | C44: Transportation | D44: Expense | E44: No | H44: Joint | I44: =DefaultSplitA | J44: 407 ETR, city parking
B45: Health Insurance | C45: Health | D45: Expense | E45: Yes | F45: Medical | I45: =DefaultSplitA
B46: Dental | C46: Health | D46: Expense | E46: Yes | F46: Medical | I46: =DefaultSplitA | J46: Line 33099
B47: Prescriptions & Pharmacy | C47: Health | D47: Expense | E47: Yes | F47: Medical | I47: =DefaultSplitA | J47: Line 33099
B48: Vision | C48: Health | D48: Expense | E48: Yes | F48: Medical | I48: =DefaultSplitA | J48: Line 33099
B49: Therapy & Counselling | C49: Health | D49: Expense | E49: Yes | F49: Medical | I49: =DefaultSplitA | J49: Line 33099
B50: Other Medical | C50: Health | D50: Expense | E50: Yes | F50: Medical | I50: =DefaultSplitA | J50: Line 33099
B51: Fitness & Sports | C51: Health | D51: Expense | E51: No | I51: =DefaultSplitA
B52: Childcare & Daycare | C52: Family | D52: Expense | E52: Yes | F52: Childcare | H52: Joint | I52: =DefaultSplitA | J52: Line 21400
B53: Children's Activities | C53: Family | D53: Expense | E53: No | H53: Joint | I53: =DefaultSplitA
B54: Children's Clothing | C54: Family | D54: Expense | E54: Yes | H54: Joint | I54: =DefaultSplitA
B55: Baby Supplies | C55: Family | D55: Expense | E55: Yes | H55: Joint | I55: =DefaultSplitA
B56: Child / Spousal Support | C56: Family | D56: Expense | E56: Yes | F56: Support payments | I56: =DefaultSplitA | J56: Line 22000
B57: Pet Care | C57: Family | D57: Expense | E57: No | H57: Joint | I57: =DefaultSplitA
B58: Elder Care | C58: Family | D58: Expense | E58: Yes | F58: Medical | I58: =DefaultSplitA
B59: Tuition | C59: Education | D59: Expense | E59: No | F59: Tuition | I59: =DefaultSplitA | J59: T2202
B60: Student Loan Payment | C60: Education | D60: Expense | E60: Yes | F60: Student loan interest | I60: =DefaultSplitA | J60: OSAP / CSLP
B61: Books & Supplies | C61: Education | D61: Expense | E61: No | I61: =DefaultSplitA
B62: Courses & Training | C62: Education | D62: Expense | E62: No | I62: =DefaultSplitA
B63: Professional Dues | C63: Education | D63: Expense | E63: Yes | F63: Union or professional dues | I63: =DefaultSplitA | J63: Line 21200
B64: Clothing & Shoes | C64: Personal | D64: Expense | E64: No | I64: =DefaultSplitA
B65: Personal Care | C65: Personal | D65: Expense | E65: No | I65: =DefaultSplitA | J65: Haircuts, cosmetics
B66: Subscriptions | C66: Personal | D66: Expense | E66: No | I66: =DefaultSplitA | J66: Streaming, apps, news
B67: Entertainment | C67: Personal | D67: Expense | E67: No | H67: Joint | I67: =DefaultSplitA
B68: Hobbies | C68: Personal | D68: Expense | E68: No | I68: =DefaultSplitA
B69: Gifts & Celebrations | C69: Personal | D69: Expense | E69: No | I69: =DefaultSplitA
B70: Donations | C70: Personal | D70: Expense | E70: No | F70: Donations | I70: =DefaultSplitA | J70: Line 34900
B71: Electronics | C71: Personal | D71: Expense | E71: No | I71: =DefaultSplitA
B72: Flights | C72: Travel | D72: Expense | E72: No | H72: Joint | I72: =DefaultSplitA
B73: Accommodation | C73: Travel | D73: Expense | E73: No | H73: Joint | I73: =DefaultSplitA
B74: Travel Other | C74: Travel | D74: Expense | E74: No | H74: Joint | I74: =DefaultSplitA
B75: Bank Fees | C75: Financial | D75: Expense | E75: Yes | I75: =DefaultSplitA
B76: Interest & Card Charges | C76: Financial | D76: Expense | E76: Yes | I76: =DefaultSplitA
B77: Foreign Exchange Fees | C77: Financial | D77: Expense | E77: No | I77: =DefaultSplitA
B78: Life & Disability Insurance | C78: Financial | D78: Expense | E78: Yes | I78: =DefaultSplitA
B79: Investment Fees | C79: Financial | D79: Expense | E79: No | F79: Investment expenses | I79: =DefaultSplitA
B80: Tax Payment to CRA | C80: Financial | D80: Expense | E80: Yes | F80: Taxes paid | I80: =DefaultSplitA
B81: Legal & Accounting | C81: Financial | D81: Expense | E81: No | I81: =DefaultSplitA
B82: Debt Payment | C82: Financial | D82: Expense | E82: Yes | I82: =DefaultSplitA | J82: Loan or line of credit
B83: RRSP Contribution | C83: Saving | D83: Saving | E83: Yes | F83: RRSP | I83: =DefaultSplitA | J83: Keep every receipt
B84: TFSA Contribution | C84: Saving | D84: Saving | E84: Yes | I84: =DefaultSplitA
B85: FHSA Contribution | C85: Saving | D85: Saving | E85: No | F85: FHSA | I85: =DefaultSplitA | J85: First Home Savings Account
B86: RESP Contribution | C86: Saving | D86: Saving | E86: No | H86: Joint | I86: =DefaultSplitA | J86: Attracts the CESG
B87: Non-Registered Investing | C87: Saving | D87: Saving | E87: No | I87: =DefaultSplitA
B88: Emergency Savings | C88: Saving | D88: Saving | E88: Yes | H88: Joint | I88: =DefaultSplitA
B89: Internal Transfer | C89: Transfers | D89: Transfer | E89: No | I89: =DefaultSplitA | J89: Between your own accounts
B90: Credit Card Payment | C90: Transfers | D90: Transfer | E90: No | I90: =DefaultSplitA | J90: Not an expense on its own
B91: Interac e-Transfer Sent | C91: Other | D91: Expense | E91: No | I91: =DefaultSplitA | J91: Re-categorise when you can
B92: Interac e-Transfer Received | C92: Income | D92: Income | E92: No | I92: =DefaultSplitA
B93: Cash Withdrawal | C93: Other | D93: Expense | E93: No | I93: =DefaultSplitA | J93: Where the cash went is unknown
B94: Business Expense | C94: Other | D94: Expense | E94: No | F94: Business expense | I94: =DefaultSplitA | J94: T2125
B95: Miscellaneous | C95: Other | D95: Expense | E95: No | I95: =DefaultSplitA
B96: Uncategorized | C96: Other | D96: Expense | E96: No | I96: =DefaultSplitA | J96: Anything the rules could not place

Sheet Rules
B1: Rules
B2: Rules run in Priority order, lowest first, and the first match wins. Add a row to teach a new one - the Category column on the Transactions sheet picks it up at once. This edition applies Contains and Word tests and the Flow; the pattern is looked for in the Description (or the Account).
B4: Priority | C4: Enabled | D4: Look In | E4: Test | F4: Pattern | G4: Min Amount | H4: Max Amount | I4: Flow | J4: Category | K4: Set Owner | L4: Hits | M4: Notes
B5: 9 | C5: Yes | D5: Description | E5: Contains | F5: RRSP | I5: Money out | J5: RRSP Contribution | L5: 0 | M5: Built in
B6: 9 | C6: Yes | D6: Description | E6: Contains | F6: TFSA | I6: Money out | J6: TFSA Contribution | L6: 0 | M6: Built in
B7: 9 | C7: Yes | D7: Description | E7: Contains | F7: FHSA | I7: Money out | J7: FHSA Contribution | L7: 0 | M7: Built in
B8: 9 | C8: Yes | D8: Description | E8: Contains | F8: RESP | I8: Money out | J8: RESP Contribution | L8: 0 | M8: Built in
B9: 10 | C9: Yes | D9: Description | E9: Contains | F9: PAYMENT - THANK YOU | I9: Money in | J9: Credit Card Payment | L9: 0 | M9: Built in
B10: 10 | C10: Yes | D10: Description | E10: Contains | F10: PAIEMENT | I10: Money in | J10: Credit Card Payment | L10: 0 | M10: Built in
B11: 11 | C11: Yes | D11: Description | E11: Contains | F11: CREDIT CARD/LOC PAY | I11: Any | J11: Credit Card Payment | L11: 0 | M11: Built in
B12: 12 | C12: Yes | D12: Description | E12: Contains | F12: TRANSFER TO | I12: Money out | J12: Internal Transfer | L12: 0 | M12: Built in
B13: 12 | C13: Yes | D13: Description | E13: Contains | F13: TRANSFER FROM | I13: Money in | J13: Internal Transfer | L13: 0 | M13: Built in
B14: 13 | C14: Yes | D14: Description | E14: Contains | F14: E-TRANSFER SENT | I14: Money out | J14: Interac e-Transfer Sent | L14: 0 | M14: Built in
B15: 13 | C15: Yes | D15: Description | E15: Contains | F15: INTERAC E-TRANSFER SENT | I15: Money out | J15: Interac e-Transfer Sent | L15: 0 | M15: Built in
B16: 13 | C16: Yes | D16: Description | E16: Contains | F16: E-TRANSFER RECEIVED | I16: Money in | J16: Interac e-Transfer Received | L16: 0 | M16: Built in
... B198: 84 | C198: Yes | D198: Description | E198: Contains | F198: STUDENT LOAN | I198: Money out | J198: Student Loan Payment | L198: 0 | M198: Built in

Sheet Budget
B1: Budget
B2: Set a monthly budget per category on the Categories sheet; this page compares it with what actually happened in the report month chosen on the Dashboard. Income and spending are both shown as positive numbers, and a negative Difference always means the month went the wrong way.
B3: Month shown | C3: =ReportMonth
B5: Category | C5: Group | D5: Type | E5: Budget | F5: Actual | G5: Difference | H5: % used | I5: 12-month average | J5: Notes
B6: =IFERROR(INDEX(tblCategories[Category],1),"") | C6: =IF($B6="","",IFERROR(INDEX(tblCategories[Group],MATCH($B6,tblCategories[Category],0)),"")) | D6: =IF($B6="","",IFERROR(INDEX(tblCategories[Type],MATCH($B6,tblCategories[Category],0)),"")) | E6: =IF($B6="","",IFERROR(INDEX(tblCategories[Monthly Budget],MATCH($B6,tblCategories[Category],0)),0)) | F6: =IF($B6="","",SUMIFS(tblTxn[View Amount],tblTxn[Month],ReportMonth,tblTxn[Category],$B6)*$K6) | G6: =IF(N(E6)=0,"",IF($D6="Income",F6-E6,E6-F6)) | H6: =IF(N(E6)=0,"",F6/E6) | I6: =IF($B6="","",SUMIFS(tblTxn[View Amount],tblTxn[Category],$B6,tblTxn[Month],">="&TEXT(EDATE(DATE(VALUE(LEFT(ReportMonth,4)),VALUE(RIGHT(ReportMonth,2)),1),-11),"yyyy-mm"),tblTxn[Month],"<="&ReportMonth)*$K6/12) | K6: =IF($D6="Income",1,-1)
B7: =IFERROR(INDEX(tblCategories[Category],2),"") | C7: =IF($B7="","",IFERROR(INDEX(tblCategories[Group],MATCH($B7,tblCategories[Category],0)),"")) | D7: =IF($B7="","",IFERROR(INDEX(tblCategories[Type],MATCH($B7,tblCategories[Category],0)),"")) | E7: =IF($B7="","",IFERROR(INDEX(tblCategories[Monthly Budget],MATCH($B7,tblCategories[Category],0)),0)) | F7: =IF($B7="","",SUMIFS(tblTxn[View Amount],tblTxn[Month],ReportMonth,tblTxn[Category],$B7)*$K7) | G7: =IF(N(E7)=0,"",IF($D7="Income",F7-E7,E7-F7)) | H7: =IF(N(E7)=0,"",F7/E7) | I7: =IF($B7="","",SUMIFS(tblTxn[View Amount],tblTxn[Category],$B7,tblTxn[Month],">="&TEXT(EDATE(DATE(VALUE(LEFT(ReportMonth,4)),VALUE(RIGHT(ReportMonth,2)),1),-11),"yyyy-mm"),tblTxn[Month],"<="&ReportMonth)*$K7/12) | K7: =IF($D7="Income",1,-1)
B8: =IFERROR(INDEX(tblCategories[Category],3),"") | C8: =IF($B8="","",IFERROR(INDEX(tblCategories[Group],MATCH($B8,tblCategories[Category],0)),"")) | D8: =IF($B8="","",IFERROR(INDEX(tblCategories[Type],MATCH($B8,tblCategories[Category],0)),"")) | E8: =IF($B8="","",IFERROR(INDEX(tblCategories[Monthly Budget],MATCH($B8,tblCategories[Category],0)),0)) | F8: =IF($B8="","",SUMIFS(tblTxn[View Amount],tblTxn[Month],ReportMonth,tblTxn[Category],$B8)*$K8) | G8: =IF(N(E8)=0,"",IF($D8="Income",F8-E8,E8-F8)) | H8: =IF(N(E8)=0,"",F8/E8) | I8: =IF($B8="","",SUMIFS(tblTxn[View Amount],tblTxn[Category],$B8,tblTxn[Month],">="&TEXT(EDATE(DATE(VALUE(LEFT(ReportMonth,4)),VALUE(RIGHT(ReportMonth,2)),1),-11),"yyyy-mm"),tblTxn[Month],"<="&ReportMonth)*$K8/12) | K8: =IF($D8="Income",1,-1)
B9: =IFERROR(INDEX(tblCategories[Category],4),"") | C9: =IF($B9="","",IFERROR(INDEX(tblCategories[Group],MATCH($B9,tblCategories[Category],0)),"")) | D9: =IF($B9="","",IFERROR(INDEX(tblCategories[Type],MATCH($B9,tblCategories[Category],0)),"")) | E9: =IF($B9="","",IFERROR(INDEX(tblCategories[Monthly Budget],MATCH($B9,tblCategories[Category],0)),0)) | F9: =IF($B9="","",SUMIFS(tblTxn[View Amount],tblTxn[Month],ReportMonth,tblTxn[Category],$B9)*$K9) | G9: =IF(N(E9)=0,"",IF($D9="Income",F9-E9,E9-F9)) | H9: =IF(N(E9)=0,"",F9/E9) | I9: =IF($B9="","",SUMIFS(tblTxn[View Amount],tblTxn[Category],$B9,tblTxn[Month],">="&TEXT(EDATE(DATE(VALUE(LEFT(ReportMonth,4)),VALUE(RIGHT(ReportMonth,2)),1),-11),"yyyy-mm"),tblTxn[Month],"<="&ReportMonth)*$K9/12) | K9: =IF($D9="Income",1,-1)
B10: =IFERROR(INDEX(tblCategories[Category],5),"") | C10: =IF($B10="","",IFERROR(INDEX(tblCategories[Group],MATCH($B10,tblCategories[Category],0)),"")) | D10: =IF($B10="","",IFERROR(INDEX(tblCategories[Type],MATCH($B10,tblCategories[Category],0)),"")) | E10: =IF($B10="","",IFERROR(INDEX(tblCategories[Monthly Budget],MATCH($B10,tblCategories[Category],0)),0)) | F10: =IF($B10="","",SUMIFS(tblTxn[View Amount],tblTxn[Month],ReportMonth,tblTxn[Category],$B10)*$K10) | G10: =IF(N(E10)=0,"",IF($D10="Income",F10-E10,E10-F10)) | H10: =IF(N(E10)=0,"",F10/E10) | I10: =IF($B10="","",SUMIFS(tblTxn[View Amount],tblTxn[Category],$B10,tblTxn[Month],">="&TEXT(EDATE(DATE(VALUE(LEFT(ReportMonth,4)),VALUE(RIGHT(ReportMonth,2)),1),-11),"yyyy-mm"),tblTxn[Month],"<="&ReportMonth)*$K10/12) | K10: =IF($D10="Income",1,-1)
B11: =IFERROR(INDEX(tblCategories[Category],6),"") | C11: =IF($B11="","",IFERROR(INDEX(tblCategories[Group],MATCH($B11,tblCategories[Category],0)),"")) | D11: =IF($B11="","",IFERROR(INDEX(tblCategories[Type],MATCH($B11,tblCategories[Category],0)),"")) | E11: =IF($B11="","",IFERROR(INDEX(tblCategories[Monthly Budget],MATCH($B11,tblCategories[Category],0)),0)) | F11: =IF($B11="","",SUMIFS(tblTxn[View Amount],tblTxn[Month],ReportMonth,tblTxn[Category],$B11)*$K11) | G11: =IF(N(E11)=0,"",IF($D11="Income",F11-E11,E11-F11)) | H11: =IF(N(E11)=0,"",F11/E11) | I11: =IF($B11="","",SUMIFS(tblTxn[View Amount],tblTxn[Category],$B11,tblTxn[Month],">="&TEXT(EDATE(DATE(VALUE(LEFT(ReportMonth,4)),VALUE(RIGHT(ReportMonth,2)),1),-11),"yyyy-mm"),tblTxn[Month],"<="&ReportMonth)*$K11/12) | K11: =IF($D11="Income",1,-1)
B12: =IFERROR(INDEX(tblCategories[Category],7),"") | C12: =IF($B12="","",IFERROR(INDEX(tblCategories[Group],MATCH($B12,tblCategories[Category],0)),"")) | D12: =IF($B12="","",IFERROR(INDEX(tblCategories[Type],MATCH($B12,tblCategories[Category],0)),"")) | E12: =IF($B12="","",IFERROR(INDEX(tblCategories[Monthly Budget],MATCH($B12,tblCategories[Category],0)),0)) | F12: =IF($B12="","",SUMIFS(tblTxn[View Amount],tblTxn[Month],ReportMonth,tblTxn[Category],$B12)*$K12) | G12: =IF(N(E12)=0,"",IF($D12="Income",F12-E12,E12-F12)) | H12: =IF(N(E12)=0,"",F12/E12) | I12: =IF($B12="","",SUMIFS(tblTxn[View Amount],tblTxn[Category],$B12,tblTxn[Month],">="&TEXT(EDATE(DATE(VALUE(LEFT(ReportMonth,4)),VALUE(RIGHT(ReportMonth,2)),1),-11),"yyyy-mm"),tblTxn[Month],"<="&ReportMonth)*$K12/12) | K12: =IF($D12="Income",1,-1)
B13: =IFERROR(INDEX(tblCategories[Category],8),"") | C13: =IF($B13="","",IFERROR(INDEX(tblCategories[Group],MATCH($B13,tblCategories[Category],0)),"")) | D13: =IF($B13="","",IFERROR(INDEX(tblCategories[Type],MATCH($B13,tblCategories[Category],0)),"")) | E13: =IF($B13="","",IFERROR(INDEX(tblCategories[Monthly Budget],MATCH($B13,tblCategories[Category],0)),0)) | F13: =IF($B13="","",SUMIFS(tblTxn[View Amount],tblTxn[Month],ReportMonth,tblTxn[Category],$B13)*$K13) | G13: =IF(N(E13)=0,"",IF($D13="Income",F13-E13,E13-F13)) | H13: =IF(N(E13)=0,"",F13/E13) | I13: =IF($B13="","",SUMIFS(tblTxn[View Amount],tblTxn[Category],$B13,tblTxn[Month],">="&TEXT(EDATE(DATE(VALUE(LEFT(ReportMonth,4)),VALUE(RIGHT(ReportMonth,2)),1),-11),"yyyy-mm"),tblTxn[Month],"<="&ReportMonth)*$K13/12) | K13: =IF($D13="Income",1,-1)
B14: =IFERROR(INDEX(tblCategories[Category],9),"") | C14: =IF($B14="","",IFERROR(INDEX(tblCategories[Group],MATCH($B14,tblCategories[Category],0)),"")) | D14: =IF($B14="","",IFERROR(INDEX(tblCategories[Type],MATCH($B14,tblCategories[Category],0)),"")) | E14: =IF($B14="","",IFERROR(INDEX(tblCategories[Monthly Budget],MATCH($B14,tblCategories[Category],0)),0)) | F14: =IF($B14="","",SUMIFS(tblTxn[View Amount],tblTxn[Month],ReportMonth,tblTxn[Category],$B14)*$K14) | G14: =IF(N(E14)=0,"",IF($D14="Income",F14-E14,E14-F14)) | H14: =IF(N(E14)=0,"",F14/E14) | I14: =IF($B14="","",SUMIFS(tblTxn[View Amount],tblTxn[Category],$B14,tblTxn[Month],">="&TEXT(EDATE(DATE(VALUE(LEFT(ReportMonth,4)),VALUE(RIGHT(ReportMonth,2)),1),-11),"yyyy-mm"),tblTxn[Month],"<="&ReportMonth)*$K14/12) | K14: =IF($D14="Income",1,-1)
B15: =IFERROR(INDEX(tblCategories[Category],10),"") | C15: =IF($B15="","",IFERROR(INDEX(tblCategories[Group],MATCH($B15,tblCategories[Category],0)),"")) | D15: =IF($B15="","",IFERROR(INDEX(tblCategories[Type],MATCH($B15,tblCategories[Category],0)),"")) | E15: =IF($B15="","",IFERROR(INDEX(tblCategories[Monthly Budget],MATCH($B15,tblCategories[Category],0)),0)) | F15: =IF($B15="","",SUMIFS(tblTxn[View Amount],tblTxn[Month],ReportMonth,tblTxn[Category],$B15)*$K15) | G15: =IF(N(E15)=0,"",IF($D15="Income",F15-E15,E15-F15)) | H15: =IF(N(E15)=0,"",F15/E15) | I15: =IF($B15="","",SUMIFS(tblTxn[View Amount],tblTxn[Category],$B15,tblTxn[Month],">="&TEXT(EDATE(DATE(VALUE(LEFT(ReportMonth,4)),VALUE(RIGHT(ReportMonth,2)),1),-11),"yyyy-mm"),tblTxn[Month],"<="&ReportMonth)*$K15/12) | K15: =IF($D15="Income",1,-1)
B16: =IFERROR(INDEX(tblCategories[Category],11),"") | C16: =IF($B16="","",IFERROR(INDEX(tblCategories[Group],MATCH($B16,tblCategories[Category],0)),"")) | D16: =IF($B16="","",IFERROR(INDEX(tblCategories[Type],MATCH($B16,tblCategories[Category],0)),"")) | E16: =IF($B16="","",IFERROR(INDEX(tblCategories[Monthly Budget],MATCH($B16,tblCategories[Category],0)),0)) | F16: =IF($B16="","",SUMIFS(tblTxn[View Amount],tblTxn[Month],ReportMonth,tblTxn[Category],$B16)*$K16) | G16: =IF(N(E16)=0,"",IF($D16="Income",F16-E16,E16-F16)) | H16: =IF(N(E16)=0,"",F16/E16) | I16: =IF($B16="","",SUMIFS(tblTxn[View Amount],tblTxn[Category],$B16,tblTxn[Month],">="&TEXT(EDATE(DATE(VALUE(LEFT(ReportMonth,4)),VALUE(RIGHT(ReportMonth,2)),1),-11),"yyyy-mm"),tblTxn[Month],"<="&ReportMonth)*$K16/12) | K16: =IF($D16="Income",1,-1)
B17: =IFERROR(INDEX(tblCategories[Category],12),"") | C17: =IF($B17="","",IFERROR(INDEX(tblCategories[Group],MATCH($B17,tblCategories[Category],0)),"")) | D17: =IF($B17="","",IFERROR(INDEX(tblCategories[Type],MATCH($B17,tblCategories[Category],0)),"")) | E17: =IF($B17="","",IFERROR(INDEX(tblCategories[Monthly Budget],MATCH($B17,tblCategories[Category],0)),0)) | F17: =IF($B17="","",SUMIFS(tblTxn[View Amount],tblTxn[Month],ReportMonth,tblTxn[Category],$B17)*$K17) | G17: =IF(N(E17)=0,"",IF($D17="Income",F17-E17,E17-F17)) | H17: =IF(N(E17)=0,"",F17/E17) | I17: =IF($B17="","",SUMIFS(tblTxn[View Amount],tblTxn[Category],$B17,tblTxn[Month],">="&TEXT(EDATE(DATE(VALUE(LEFT(ReportMonth,4)),VALUE(RIGHT(ReportMonth,2)),1),-11),"yyyy-mm"),tblTxn[Month],"<="&ReportMonth)*$K17/12) | K17: =IF($D17="Income",1,-1)
B18: =IFERROR(INDEX(tblCategories[Category],13),"") | C18: =IF($B18="","",IFERROR(INDEX(tblCategories[Group],MATCH($B18,tblCategories[Category],0)),"")) | D18: =IF($B18="","",IFERROR(INDEX(tblCategories[Type],MATCH($B18,tblCategories[Category],0)),"")) | E18: =IF($B18="","",IFERROR(INDEX(tblCategories[Monthly Budget],MATCH($B18,tblCategories[Category],0)),0)) | F18: =IF($B18="","",SUMIFS(tblTxn[View Amount],tblTxn[Month],ReportMonth,tblTxn[Category],$B18)*$K18) | G18: =IF(N(E18)=0,"",IF($D18="Income",F18-E18,E18-F18)) | H18: =IF(N(E18)=0,"",F18/E18) | I18: =IF($B18="","",SUMIFS(tblTxn[View Amount],tblTxn[Category],$B18,tblTxn[Month],">="&TEXT(EDATE(DATE(VALUE(LEFT(ReportMonth,4)),VALUE(RIGHT(ReportMonth,2)),1),-11),"yyyy-mm"),tblTxn[Month],"<="&ReportMonth)*$K18/12) | K18: =IF($D18="Income",1,-1)
B19: =IFERROR(INDEX(tblCategories[Category],14),"") | C19: =IF($B19="","",IFERROR(INDEX(tblCategories[Group],MATCH($B19,tblCategories[Category],0)),"")) | D19: =IF($B19="","",IFERROR(INDEX(tblCategories[Type],MATCH($B19,tblCategories[Category],0)),"")) | E19: =IF($B19="","",IFERROR(INDEX(tblCategories[Monthly Budget],MATCH($B19,tblCategories[Category],0)),0)) | F19: =IF($B19="","",SUMIFS(tblTxn[View Amount],tblTxn[Month],ReportMonth,tblTxn[Category],$B19)*$K19) | G19: =IF(N(E19)=0,"",IF($D19="Income",F19-E19,E19-F19)) | H19: =IF(N(E19)=0,"",F19/E19) | I19: =IF($B19="","",SUMIFS(tblTxn[View Amount],tblTxn[Category],$B19,tblTxn[Month],">="&TEXT(EDATE(DATE(VALUE(LEFT(ReportMonth,4)),VALUE(RIGHT(ReportMonth,2)),1),-11),"yyyy-mm"),tblTxn[Month],"<="&ReportMonth)*$K19/12) | K19: =IF($D19="Income",1,-1)
B20: =IFERROR(INDEX(tblCategories[Category],15),"") | C20: =IF($B20="","",IFERROR(INDEX(tblCategories[Group],MATCH($B20,tblCategories[Category],0)),"")) | D20: =IF($B20="","",IFERROR(INDEX(tblCategories[Type],MATCH($B20,tblCategories[Category],0)),"")) | E20: =IF($B20="","",IFERROR(INDEX(tblCategories[Monthly Budget],MATCH($B20,tblCategories[Category],0)),0)) | F20: =IF($B20="","",SUMIFS(tblTxn[View Amount],tblTxn[Month],ReportMonth,tblTxn[Category],$B20)*$K20) | G20: =IF(N(E20)=0,"",IF($D20="Income",F20-E20,E20-F20)) | H20: =IF(N(E20)=0,"",F20/E20) | I20: =IF($B20="","",SUMIFS(tblTxn[View Amount],tblTxn[Category],$B20,tblTxn[Month],">="&TEXT(EDATE(DATE(VALUE(LEFT(ReportMonth,4)),VALUE(RIGHT(ReportMonth,2)),1),-11),"yyyy-mm"),tblTxn[Month],"<="&ReportMonth)*$K20/12) | K20: =IF($D20="Income",1,-1)
B21: =IFERROR(INDEX(tblCategories[Category],16),"") | C21: =IF($B21="","",IFERROR(INDEX(tblCategories[Group],MATCH($B21,tblCategories[Category],0)),"")) | D21: =IF($B21="","",IFERROR(INDEX(tblCategories[Type],MATCH($B21,tblCategories[Category],0)),"")) | E21: =IF($B21="","",IFERROR(INDEX(tblCategories[Monthly Budget],MATCH($B21,tblCategories[Category],0)),0)) | F21: =IF($B21="","",SUMIFS(tblTxn[View Amount],tblTxn[Month],ReportMonth,tblTxn[Category],$B21)*$K21) | G21: =IF(N(E21)=0,"",IF($D21="Income",F21-E21,E21-F21)) | H21: =IF(N(E21)=0,"",F21/E21) | I21: =IF($B21="","",SUMIFS(tblTxn[View Amount],tblTxn[Category],$B21,tblTxn[Month],">="&TEXT(EDATE(DATE(VALUE(LEFT(ReportMonth,4)),VALUE(RIGHT(ReportMonth,2)),1),-11),"yyyy-mm"),tblTxn[Month],"<="&ReportMonth)*$K21/12) | K21: =IF($D21="Income",1,-1)
B22: =IFERROR(INDEX(tblCategories[Category],17),"") | C22: =IF($B22="","",IFERROR(INDEX(tblCategories[Group],MATCH($B22,tblCategories[Category],0)),"")) | D22: =IF($B22="","",IFERROR(INDEX(tblCategories[Type],MATCH($B22,tblCategories[Category],0)),"")) | E22: =IF($B22="","",IFERROR(INDEX(tblCategories[Monthly Budget],MATCH($B22,tblCategories[Category],0)),0)) | F22: =IF($B22="","",SUMIFS(tblTxn[View Amount],tblTxn[Month],ReportMonth,tblTxn[Category],$B22)*$K22) | G22: =IF(N(E22)=0,"",IF($D22="Income",F22-E22,E22-F22)) | H22: =IF(N(E22)=0,"",F22/E22) | I22: =IF($B22="","",SUMIFS(tblTxn[View Amount],tblTxn[Category],$B22,tblTxn[Month],">="&TEXT(EDATE(DATE(VALUE(LEFT(ReportMonth,4)),VALUE(RIGHT(ReportMonth,2)),1),-11),"yyyy-mm"),tblTxn[Month],"<="&ReportMonth)*$K22/12) | K22: =IF($D22="Income",1,-1)
B23: =IFERROR(INDEX(tblCategories[Category],18),"") | C23: =IF($B23="","",IFERROR(INDEX(tblCategories[Group],MATCH($B23,tblCategories[Category],0)),"")) | D23: =IF($B23="","",IFERROR(INDEX(tblCategories[Type],MATCH($B23,tblCategories[Category],0)),"")) | E23: =IF($B23="","",IFERROR(INDEX(tblCategories[Monthly Budget],MATCH($B23,tblCategories[Category],0)),0)) | F23: =IF($B23="","",SUMIFS(tblTxn[View Amount],tblTxn[Month],ReportMonth,tblTxn[Category],$B23)*$K23) | G23: =IF(N(E23)=0,"",IF($D23="Income",F23-E23,E23-F23)) | H23: =IF(N(E23)=0,"",F23/E23) | I23: =IF($B23="","",SUMIFS(tblTxn[View Amount],tblTxn[Category],$B23,tblTxn[Month],">="&TEXT(EDATE(DATE(VALUE(LEFT(ReportMonth,4)),VALUE(RIGHT(ReportMonth,2)),1),-11),"yyyy-mm"),tblTxn[Month],"<="&ReportMonth)*$K23/12) | K23: =IF($D23="Income",1,-1)
B24: =IFERROR(INDEX(tblCategories[Category],19),"") | C24: =IF($B24="","",IFERROR(INDEX(tblCategories[Group],MATCH($B24,tblCategories[Category],0)),"")) | D24: =IF($B24="","",IFERROR(INDEX(tblCategories[Type],MATCH($B24,tblCategories[Category],0)),"")) | E24: =IF($B24="","",IFERROR(INDEX(tblCategories[Monthly Budget],MATCH($B24,tblCategories[Category],0)),0)) | F24: =IF($B24="","",SUMIFS(tblTxn[View Amount],tblTxn[Month],ReportMonth,tblTxn[Category],$B24)*$K24) | G24: =IF(N(E24)=0,"",IF($D24="Income",F24-E24,E24-F24)) | H24: =IF(N(E24)=0,"",F24/E24) | I24: =IF($B24="","",SUMIFS(tblTxn[View Amount],tblTxn[Category],$B24,tblTxn[Month],">="&TEXT(EDATE(DATE(VALUE(LEFT(ReportMonth,4)),VALUE(RIGHT(ReportMonth,2)),1),-11),"yyyy-mm"),tblTxn[Month],"<="&ReportMonth)*$K24/12) | K24: =IF($D24="Income",1,-1)
B25: =IFERROR(INDEX(tblCategories[Category],20),"") | C25: =IF($B25="","",IFERROR(INDEX(tblCategories[Group],MATCH($B25,tblCategories[Category],0)),"")) | D25: =IF($B25="","",IFERROR(INDEX(tblCategories[Type],MATCH($B25,tblCategories[Category],0)),"")) | E25: =IF($B25="","",IFERROR(INDEX(tblCategories[Monthly Budget],MATCH($B25,tblCategories[Category],0)),0)) | F25: =IF($B25="","",SUMIFS(tblTxn[View Amount],tblTxn[Month],ReportMonth,tblTxn[Category],$B25)*$K25) | G25: =IF(N(E25)=0,"",IF($D25="Income",F25-E25,E25-F25)) | H25: =IF(N(E25)=0,"",F25/E25) | I25: =IF($B25="","",SUMIFS(tblTxn[View Amount],tblTxn[Category],$B25,tblTxn[Month],">="&TEXT(EDATE(DATE(VALUE(LEFT(ReportMonth,4)),VALUE(RIGHT(ReportMonth,2)),1),-11),"yyyy-mm"),tblTxn[Month],"<="&ReportMonth)*$K25/12) | K25: =IF($D25="Income",1,-1)
B26: =IFERROR(INDEX(tblCategories[Category],21),"") | C26: =IF($B26="","",IFERROR(INDEX(tblCategories[Group],MATCH($B26,tblCategories[Category],0)),"")) | D26: =IF($B26="","",IFERROR(INDEX(tblCategories[Type],MATCH($B26,tblCategories[Category],0)),"")) | E26: =IF($B26="","",IFERROR(INDEX(tblCategories[Monthly Budget],MATCH($B26,tblCategories[Category],0)),0)) | F26: =IF($B26="","",SUMIFS(tblTxn[View Amount],tblTxn[Month],ReportMonth,tblTxn[Category],$B26)*$K26) | G26: =IF(N(E26)=0,"",IF($D26="Income",F26-E26,E26-F26)) | H26: =IF(N(E26)=0,"",F26/E26) | I26: =IF($B26="","",SUMIFS(tblTxn[View Amount],tblTxn[Category],$B26,tblTxn[Month],">="&TEXT(EDATE(DATE(VALUE(LEFT(ReportMonth,4)),VALUE(RIGHT(ReportMonth,2)),1),-11),"yyyy-mm"),tblTxn[Month],"<="&ReportMonth)*$K26/12) | K26: =IF($D26="Income",1,-1)
B27: =IFERROR(INDEX(tblCategories[Category],22),"") | C27: =IF($B27="","",IFERROR(INDEX(tblCategories[Group],MATCH($B27,tblCategories[Category],0)),"")) | D27: =IF($B27="","",IFERROR(INDEX(tblCategories[Type],MATCH($B27,tblCategories[Category],0)),"")) | E27: =IF($B27="","",IFERROR(INDEX(tblCategories[Monthly Budget],MATCH($B27,tblCategories[Category],0)),0)) | F27: =IF($B27="","",SUMIFS(tblTxn[View Amount],tblTxn[Month],ReportMonth,tblTxn[Category],$B27)*$K27) | G27: =IF(N(E27)=0,"",IF($D27="Income",F27-E27,E27-F27)) | H27: =IF(N(E27)=0,"",F27/E27) | I27: =IF($B27="","",SUMIFS(tblTxn[View Amount],tblTxn[Category],$B27,tblTxn[Month],">="&TEXT(EDATE(DATE(VALUE(LEFT(ReportMonth,4)),VALUE(RIGHT(ReportMonth,2)),1),-11),"yyyy-mm"),tblTxn[Month],"<="&ReportMonth)*$K27/12) | K27: =IF($D27="Income",1,-1)
B28: =IFERROR(INDEX(tblCategories[Category],23),"") | C28: =IF($B28="","",IFERROR(INDEX(tblCategories[Group],MATCH($B28,tblCategories[Category],0)),"")) | D28: =IF($B28="","",IFERROR(INDEX(tblCategories[Type],MATCH($B28,tblCategories[Category],0)),"")) | E28: =IF($B28="","",IFERROR(INDEX(tblCategories[Monthly Budget],MATCH($B28,tblCategories[Category],0)),0)) | F28: =IF($B28="","",SUMIFS(tblTxn[View Amount],tblTxn[Month],ReportMonth,tblTxn[Category],$B28)*$K28) | G28: =IF(N(E28)=0,"",IF($D28="Income",F28-E28,E28-F28)) | H28: =IF(N(E28)=0,"",F28/E28) | I28: =IF($B28="","",SUMIFS(tblTxn[View Amount],tblTxn[Category],$B28,tblTxn[Month],">="&TEXT(EDATE(DATE(VALUE(LEFT(ReportMonth,4)),VALUE(RIGHT(ReportMonth,2)),1),-11),"yyyy-mm"),tblTxn[Month],"<="&ReportMonth)*$K28/12) | K28: =IF($D28="Income",1,-1)
B29: =IFERROR(INDEX(tblCategories[Category],24),"") | C29: =IF($B29="","",IFERROR(INDEX(tblCategories[Group],MATCH($B29,tblCategories[Category],0)),"")) | D29: =IF($B29="","",IFERROR(INDEX(tblCategories[Type],MATCH($B29,tblCategories[Category],0)),"")) | E29: =IF($B29="","",IFERROR(INDEX(tblCategories[Monthly Budget],MATCH($B29,tblCategories[Category],0)),0)) | F29: =IF($B29="","",SUMIFS(tblTxn[View Amount],tblTxn[Month],ReportMonth,tblTxn[Category],$B29)*$K29) | G29: =IF(N(E29)=0,"",IF($D29="Income",F29-E29,E29-F29)) | H29: =IF(N(E29)=0,"",F29/E29) | I29: =IF($B29="","",SUMIFS(tblTxn[View Amount],tblTxn[Category],$B29,tblTxn[Month],">="&TEXT(EDATE(DATE(VALUE(LEFT(ReportMonth,4)),VALUE(RIGHT(ReportMonth,2)),1),-11),"yyyy-mm"),tblTxn[Month],"<="&ReportMonth)*$K29/12) | K29: =IF($D29="Income",1,-1)
B30: =IFERROR(INDEX(tblCategories[Category],25),"") | C30: =IF($B30="","",IFERROR(INDEX(tblCategories[Group],MATCH($B30,tblCategories[Category],0)),"")) | D30: =IF($B30="","",IFERROR(INDEX(tblCategories[Type],MATCH($B30,tblCategories[Category],0)),"")) | E30: =IF($B30="","",IFERROR(INDEX(tblCategories[Monthly Budget],MATCH($B30,tblCategories[Category],0)),0)) | F30: =IF($B30="","",SUMIFS(tblTxn[View Amount],tblTxn[Month],ReportMonth,tblTxn[Category],$B30)*$K30) | G30: =IF(N(E30)=0,"",IF($D30="Income",F30-E30,E30-F30)) | H30: =IF(N(E30)=0,"",F30/E30) | I30: =IF($B30="","",SUMIFS(tblTxn[View Amount],tblTxn[Category],$B30,tblTxn[Month],">="&TEXT(EDATE(DATE(VALUE(LEFT(ReportMonth,4)),VALUE(RIGHT(ReportMonth,2)),1),-11),"yyyy-mm"),tblTxn[Month],"<="&ReportMonth)*$K30/12) | K30: =IF($D30="Income",1,-1)
B31: =IFERROR(INDEX(tblCategories[Category],26),"") | C31: =IF($B31="","",IFERROR(INDEX(tblCategories[Group],MATCH($B31,tblCategories[Category],0)),"")) | D31: =IF($B31="","",IFERROR(INDEX(tblCategories[Type],MATCH($B31,tblCategories[Category],0)),"")) | E31: =IF($B31="","",IFERROR(INDEX(tblCategories[Monthly Budget],MATCH($B31,tblCategories[Category],0)),0)) | F31: =IF($B31="","",SUMIFS(tblTxn[View Amount],tblTxn[Month],ReportMonth,tblTxn[Category],$B31)*$K31) | G31: =IF(N(E31)=0,"",IF($D31="Income",F31-E31,E31-F31)) | H31: =IF(N(E31)=0,"",F31/E31) | I31: =IF($B31="","",SUMIFS(tblTxn[View Amount],tblTxn[Category],$B31,tblTxn[Month],">="&TEXT(EDATE(DATE(VALUE(LEFT(ReportMonth,4)),VALUE(RIGHT(ReportMonth,2)),1),-11),"yyyy-mm"),tblTxn[Month],"<="&ReportMonth)*$K31/12) | K31: =IF($D31="Income",1,-1)
B32: =IFERROR(INDEX(tblCategories[Category],27),"") | C32: =IF($B32="","",IFERROR(INDEX(tblCategories[Group],MATCH($B32,tblCategories[Category],0)),"")) | D32: =IF($B32="","",IFERROR(INDEX(tblCategories[Type],MATCH($B32,tblCategories[Category],0)),"")) | E32: =IF($B32="","",IFERROR(INDEX(tblCategories[Monthly Budget],MATCH($B32,tblCategories[Category],0)),0)) | F32: =IF($B32="","",SUMIFS(tblTxn[View Amount],tblTxn[Month],ReportMonth,tblTxn[Category],$B32)*$K32) | G32: =IF(N(E32)=0,"",IF($D32="Income",F32-E32,E32-F32)) | H32: =IF(N(E32)=0,"",F32/E32) | I32: =IF($B32="","",SUMIFS(tblTxn[View Amount],tblTxn[Category],$B32,tblTxn[Month],">="&TEXT(EDATE(DATE(VALUE(LEFT(ReportMonth,4)),VALUE(RIGHT(ReportMonth,2)),1),-11),"yyyy-mm"),tblTxn[Month],"<="&ReportMonth)*$K32/12) | K32: =IF($D32="Income",1,-1)
B33: =IFERROR(INDEX(tblCategories[Category],28),"") | C33: =IF($B33="","",IFERROR(INDEX(tblCategories[Group],MATCH($B33,tblCategories[Category],0)),"")) | D33: =IF($B33="","",IFERROR(INDEX(tblCategories[Type],MATCH($B33,tblCategories[Category],0)),"")) | E33: =IF($B33="","",IFERROR(INDEX(tblCategories[Monthly Budget],MATCH($B33,tblCategories[Category],0)),0)) | F33: =IF($B33="","",SUMIFS(tblTxn[View Amount],tblTxn[Month],ReportMonth,tblTxn[Category],$B33)*$K33) | G33: =IF(N(E33)=0,"",IF($D33="Income",F33-E33,E33-F33)) | H33: =IF(N(E33)=0,"",F33/E33) | I33: =IF($B33="","",SUMIFS(tblTxn[View Amount],tblTxn[Category],$B33,tblTxn[Month],">="&TEXT(EDATE(DATE(VALUE(LEFT(ReportMonth,4)),VALUE(RIGHT(ReportMonth,2)),1),-11),"yyyy-mm"),tblTxn[Month],"<="&ReportMonth)*$K33/12) | K33: =IF($D33="Income",1,-1)
B34: =IFERROR(INDEX(tblCategories[Category],29),"") | C34: =IF($B34="","",IFERROR(INDEX(tblCategories[Group],MATCH($B34,tblCategories[Category],0)),"")) | D34: =IF($B34="","",IFERROR(INDEX(tblCategories[Type],MATCH($B34,tblCategories[Category],0)),"")) | E34: =IF($B34="","",IFERROR(INDEX(tblCategories[Monthly Budget],MATCH($B34,tblCategories[Category],0)),0)) | F34: =IF($B34="","",SUMIFS(tblTxn[View Amount],tblTxn[Month],ReportMonth,tblTxn[Category],$B34)*$K34) | G34: =IF(N(E34)=0,"",IF($D34="Income",F34-E34,E34-F34)) | H34: =IF(N(E34)=0,"",F34/E34) | I34: =IF($B34="","",SUMIFS(tblTxn[View Amount],tblTxn[Category],$B34,tblTxn[Month],">="&TEXT(EDATE(DATE(VALUE(LEFT(ReportMonth,4)),VALUE(RIGHT(ReportMonth,2)),1),-11),"yyyy-mm"),tblTxn[Month],"<="&ReportMonth)*$K34/12) | K34: =IF($D34="Income",1,-1)
B35: =IFERROR(INDEX(tblCategories[Category],30),"") | C35: =IF($B35="","",IFERROR(INDEX(tblCategories[Group],MATCH($B35,tblCategories[Category],0)),"")) | D35: =IF($B35="","",IFERROR(INDEX(tblCategories[Type],MATCH($B35,tblCategories[Category],0)),"")) | E35: =IF($B35="","",IFERROR(INDEX(tblCategories[Monthly Budget],MATCH($B35,tblCategories[Category],0)),0)) | F35: =IF($B35="","",SUMIFS(tblTxn[View Amount],tblTxn[Month],ReportMonth,tblTxn[Category],$B35)*$K35) | G35: =IF(N(E35)=0,"",IF($D35="Income",F35-E35,E35-F35)) | H35: =IF(N(E35)=0,"",F35/E35) | I35: =IF($B35="","",SUMIFS(tblTxn[View Amount],tblTxn[Category],$B35,tblTxn[Month],">="&TEXT(EDATE(DATE(VALUE(LEFT(ReportMonth,4)),VALUE(RIGHT(ReportMonth,2)),1),-11),"yyyy-mm"),tblTxn[Month],"<="&ReportMonth)*$K35/12) | K35: =IF($D35="Income",1,-1)
B36: =IFERROR(INDEX(tblCategories[Category],31),"") | C36: =IF($B36="","",IFERROR(INDEX(tblCategories[Group],MATCH($B36,tblCategories[Category],0)),"")) | D36: =IF($B36="","",IFERROR(INDEX(tblCategories[Type],MATCH($B36,tblCategories[Category],0)),"")) | E36: =IF($B36="","",IFERROR(INDEX(tblCategories[Monthly Budget],MATCH($B36,tblCategories[Category],0)),0)) | F36: =IF($B36="","",SUMIFS(tblTxn[View Amount],tblTxn[Month],ReportMonth,tblTxn[Category],$B36)*$K36) | G36: =IF(N(E36)=0,"",IF($D36="Income",F36-E36,E36-F36)) | H36: =IF(N(E36)=0,"",F36/E36) | I36: =IF($B36="","",SUMIFS(tblTxn[View Amount],tblTxn[Category],$B36,tblTxn[Month],">="&TEXT(EDATE(DATE(VALUE(LEFT(ReportMonth,4)),VALUE(RIGHT(ReportMonth,2)),1),-11),"yyyy-mm"),tblTxn[Month],"<="&ReportMonth)*$K36/12) | K36: =IF($D36="Income",1,-1)
B37: =IFERROR(INDEX(tblCategories[Category],32),"") | C37: =IF($B37="","",IFERROR(INDEX(tblCategories[Group],MATCH($B37,tblCategories[Category],0)),"")) | D37: =IF($B37="","",IFERROR(INDEX(tblCategories[Type],MATCH($B37,tblCategories[Category],0)),"")) | E37: =IF($B37="","",IFERROR(INDEX(tblCategories[Monthly Budget],MATCH($B37,tblCategories[Category],0)),0)) | F37: =IF($B37="","",SUMIFS(tblTxn[View Amount],tblTxn[Month],ReportMonth,tblTxn[Category],$B37)*$K37) | G37: =IF(N(E37)=0,"",IF($D37="Income",F37-E37,E37-F37)) | H37: =IF(N(E37)=0,"",F37/E37) | I37: =IF($B37="","",SUMIFS(tblTxn[View Amount],tblTxn[Category],$B37,tblTxn[Month],">="&TEXT(EDATE(DATE(VALUE(LEFT(ReportMonth,4)),VALUE(RIGHT(ReportMonth,2)),1),-11),"yyyy-mm"),tblTxn[Month],"<="&ReportMonth)*$K37/12) | K37: =IF($D37="Income",1,-1)
B38: =IFERROR(INDEX(tblCategories[Category],33),"") | C38: =IF($B38="","",IFERROR(INDEX(tblCategories[Group],MATCH($B38,tblCategories[Category],0)),"")) | D38: =IF($B38="","",IFERROR(INDEX(tblCategories[Type],MATCH($B38,tblCategories[Category],0)),"")) | E38: =IF($B38="","",IFERROR(INDEX(tblCategories[Monthly Budget],MATCH($B38,tblCategories[Category],0)),0)) | F38: =IF($B38="","",SUMIFS(tblTxn[View Amount],tblTxn[Month],ReportMonth,tblTxn[Category],$B38)*$K38) | G38: =IF(N(E38)=0,"",IF($D38="Income",F38-E38,E38-F38)) | H38: =IF(N(E38)=0,"",F38/E38) | I38: =IF($B38="","",SUMIFS(tblTxn[View Amount],tblTxn[Category],$B38,tblTxn[Month],">="&TEXT(EDATE(DATE(VALUE(LEFT(ReportMonth,4)),VALUE(RIGHT(ReportMonth,2)),1),-11),"yyyy-mm"),tblTxn[Month],"<="&ReportMonth)*$K38/12) | K38: =IF($D38="Income",1,-1)
B39: =IFERROR(INDEX(tblCategories[Category],34),"") | C39: =IF($B39="","",IFERROR(INDEX(tblCategories[Group],MATCH($B39,tblCategories[Category],0)),"")) | D39: =IF($B39="","",IFERROR(INDEX(tblCategories[Type],MATCH($B39,tblCategories[Category],0)),"")) | E39: =IF($B39="","",IFERROR(INDEX(tblCategories[Monthly Budget],MATCH($B39,tblCategories[Category],0)),0)) | F39: =IF($B39="","",SUMIFS(tblTxn[View Amount],tblTxn[Month],ReportMonth,tblTxn[Category],$B39)*$K39) | G39: =IF(N(E39)=0,"",IF($D39="Income",F39-E39,E39-F39)) | H39: =IF(N(E39)=0,"",F39/E39) | I39: =IF($B39="","",SUMIFS(tblTxn[View Amount],tblTxn[Category],$B39,tblTxn[Month],">="&TEXT(EDATE(DATE(VALUE(LEFT(ReportMonth,4)),VALUE(RIGHT(ReportMonth,2)),1),-11),"yyyy-mm"),tblTxn[Month],"<="&ReportMonth)*$K39/12) | K39: =IF($D39="Income",1,-1)
B40: =IFERROR(INDEX(tblCategories[Category],35),"") | C40: =IF($B40="","",IFERROR(INDEX(tblCategories[Group],MATCH($B40,tblCategories[Category],0)),"")) | D40: =IF($B40="","",IFERROR(INDEX(tblCategories[Type],MATCH($B40,tblCategories[Category],0)),"")) | E40: =IF($B40="","",IFERROR(INDEX(tblCategories[Monthly Budget],MATCH($B40,tblCategories[Category],0)),0)) | F40: =IF($B40="","",SUMIFS(tblTxn[View Amount],tblTxn[Month],ReportMonth,tblTxn[Category],$B40)*$K40) | G40: =IF(N(E40)=0,"",IF($D40="Income",F40-E40,E40-F40)) | H40: =IF(N(E40)=0,"",F40/E40) | I40: =IF($B40="","",SUMIFS(tblTxn[View Amount],tblTxn[Category],$B40,tblTxn[Month],">="&TEXT(EDATE(DATE(VALUE(LEFT(ReportMonth,4)),VALUE(RIGHT(ReportMonth,2)),1),-11),"yyyy-mm"),tblTxn[Month],"<="&ReportMonth)*$K40/12) | K40: =IF($D40="Income",1,-1)
B41: =IFERROR(INDEX(tblCategories[Category],36),"") | C41: =IF($B41="","",IFERROR(INDEX(tblCategories[Group],MATCH($B41,tblCategories[Category],0)),"")) | D41: =IF($B41="","",IFERROR(INDEX(tblCategories[Type],MATCH($B41,tblCategories[Category],0)),"")) | E41: =IF($B41="","",IFERROR(INDEX(tblCategories[Monthly Budget],MATCH($B41,tblCategories[Category],0)),0)) | F41: =IF($B41="","",SUMIFS(tblTxn[View Amount],tblTxn[Month],ReportMonth,tblTxn[Category],$B41)*$K41) | G41: =IF(N(E41)=0,"",IF($D41="Income",F41-E41,E41-F41)) | H41: =IF(N(E41)=0,"",F41/E41) | I41: =IF($B41="","",SUMIFS(tblTxn[View Amount],tblTxn[Category],$B41,tblTxn[Month],">="&TEXT(EDATE(DATE(VALUE(LEFT(ReportMonth,4)),VALUE(RIGHT(ReportMonth,2)),1),-11),"yyyy-mm"),tblTxn[Month],"<="&ReportMonth)*$K41/12) | K41: =IF($D41="Income",1,-1)
B42: =IFERROR(INDEX(tblCategories[Category],37),"") | C42: =IF($B42="","",IFERROR(INDEX(tblCategories[Group],MATCH($B42,tblCategories[Category],0)),"")) | D42: =IF($B42="","",IFERROR(INDEX(tblCategories[Type],MATCH($B42,tblCategories[Category],0)),"")) | E42: =IF($B42="","",IFERROR(INDEX(tblCategories[Monthly Budget],MATCH($B42,tblCategories[Category],0)),0)) | F42: =IF($B42="","",SUMIFS(tblTxn[View Amount],tblTxn[Month],ReportMonth,tblTxn[Category],$B42)*$K42) | G42: =IF(N(E42)=0,"",IF($D42="Income",F42-E42,E42-F42)) | H42: =IF(N(E42)=0,"",F42/E42) | I42: =IF($B42="","",SUMIFS(tblTxn[View Amount],tblTxn[Category],$B42,tblTxn[Month],">="&TEXT(EDATE(DATE(VALUE(LEFT(ReportMonth,4)),VALUE(RIGHT(ReportMonth,2)),1),-11),"yyyy-mm"),tblTxn[Month],"<="&ReportMonth)*$K42/12) | K42: =IF($D42="Income",1,-1)
B43: =IFERROR(INDEX(tblCategories[Category],38),"") | C43: =IF($B43="","",IFERROR(INDEX(tblCategories[Group],MATCH($B43,tblCategories[Category],0)),"")) | D43: =IF($B43="","",IFERROR(INDEX(tblCategories[Type],MATCH($B43,tblCategories[Category],0)),"")) | E43: =IF($B43="","",IFERROR(INDEX(tblCategories[Monthly Budget],MATCH($B43,tblCategories[Category],0)),0)) | F43: =IF($B43="","",SUMIFS(tblTxn[View Amount],tblTxn[Month],ReportMonth,tblTxn[Category],$B43)*$K43) | G43: =IF(N(E43)=0,"",IF($D43="Income",F43-E43,E43-F43)) | H43: =IF(N(E43)=0,"",F43/E43) | I43: =IF($B43="","",SUMIFS(tblTxn[View Amount],tblTxn[Category],$B43,tblTxn[Month],">="&TEXT(EDATE(DATE(VALUE(LEFT(ReportMonth,4)),VALUE(RIGHT(ReportMonth,2)),1),-11),"yyyy-mm"),tblTxn[Month],"<="&ReportMonth)*$K43/12) | K43: =IF($D43="Income",1,-1)
B44: =IFERROR(INDEX(tblCategories[Category],39),"") | C44: =IF($B44="","",IFERROR(INDEX(tblCategories[Group],MATCH($B44,tblCategories[Category],0)),"")) | D44: =IF($B44="","",IFERROR(INDEX(tblCategories[Type],MATCH($B44,tblCategories[Category],0)),"")) | E44: =IF($B44="","",IFERROR(INDEX(tblCategories[Monthly Budget],MATCH($B44,tblCategories[Category],0)),0)) | F44: =IF($B44="","",SUMIFS(tblTxn[View Amount],tblTxn[Month],ReportMonth,tblTxn[Category],$B44)*$K44) | G44: =IF(N(E44)=0,"",IF($D44="Income",F44-E44,E44-F44)) | H44: =IF(N(E44)=0,"",F44/E44) | I44: =IF($B44="","",SUMIFS(tblTxn[View Amount],tblTxn[Category],$B44,tblTxn[Month],">="&TEXT(EDATE(DATE(VALUE(LEFT(ReportMonth,4)),VALUE(RIGHT(ReportMonth,2)),1),-11),"yyyy-mm"),tblTxn[Month],"<="&ReportMonth)*$K44/12) | K44: =IF($D44="Income",1,-1)
B45: =IFERROR(INDEX(tblCategories[Category],40),"") | C45: =IF($B45="","",IFERROR(INDEX(tblCategories[Group],MATCH($B45,tblCategories[Category],0)),"")) | D45: =IF($B45="","",IFERROR(INDEX(tblCategories[Type],MATCH($B45,tblCategories[Category],0)),"")) | E45: =IF($B45="","",IFERROR(INDEX(tblCategories[Monthly Budget],MATCH($B45,tblCategories[Category],0)),0)) | F45: =IF($B45="","",SUMIFS(tblTxn[View Amount],tblTxn[Month],ReportMonth,tblTxn[Category],$B45)*$K45) | G45: =IF(N(E45)=0,"",IF($D45="Income",F45-E45,E45-F45)) | H45: =IF(N(E45)=0,"",F45/E45) | I45: =IF($B45="","",SUMIFS(tblTxn[View Amount],tblTxn[Category],$B45,tblTxn[Month],">="&TEXT(EDATE(DATE(VALUE(LEFT(ReportMonth,4)),VALUE(RIGHT(ReportMonth,2)),1),-11),"yyyy-mm"),tblTxn[Month],"<="&ReportMonth)*$K45/12) | K45: =IF($D45="Income",1,-1)
B46: =IFERROR(INDEX(tblCategories[Category],41),"") | C46: =IF($B46="","",IFERROR(INDEX(tblCategories[Group],MATCH($B46,tblCategories[Category],0)),"")) | D46: =IF($B46="","",IFERROR(INDEX(tblCategories[Type],MATCH($B46,tblCategories[Category],0)),"")) | E46: =IF($B46="","",IFERROR(INDEX(tblCategories[Monthly Budget],MATCH($B46,tblCategories[Category],0)),0)) | F46: =IF($B46="","",SUMIFS(tblTxn[View Amount],tblTxn[Month],ReportMonth,tblTxn[Category],$B46)*$K46) | G46: =IF(N(E46)=0,"",IF($D46="Income",F46-E46,E46-F46)) | H46: =IF(N(E46)=0,"",F46/E46) | I46: =IF($B46="","",SUMIFS(tblTxn[View Amount],tblTxn[Category],$B46,tblTxn[Month],">="&TEXT(EDATE(DATE(VALUE(LEFT(ReportMonth,4)),VALUE(RIGHT(ReportMonth,2)),1),-11),"yyyy-mm"),tblTxn[Month],"<="&ReportMonth)*$K46/12) | K46: =IF($D46="Income",1,-1)
B47: =IFERROR(INDEX(tblCategories[Category],42),"") | C47: =IF($B47="","",IFERROR(INDEX(tblCategories[Group],MATCH($B47,tblCategories[Category],0)),"")) | D47: =IF($B47="","",IFERROR(INDEX(tblCategories[Type],MATCH($B47,tblCategories[Category],0)),"")) | E47: =IF($B47="","",IFERROR(INDEX(tblCategories[Monthly Budget],MATCH($B47,tblCategories[Category],0)),0)) | F47: =IF($B47="","",SUMIFS(tblTxn[View Amount],tblTxn[Month],ReportMonth,tblTxn[Category],$B47)*$K47) | G47: =IF(N(E47)=0,"",IF($D47="Income",F47-E47,E47-F47)) | H47: =IF(N(E47)=0,"",F47/E47) | I47: =IF($B47="","",SUMIFS(tblTxn[View Amount],tblTxn[Category],$B47,tblTxn[Month],">="&TEXT(EDATE(DATE(VALUE(LEFT(ReportMonth,4)),VALUE(RIGHT(ReportMonth,2)),1),-11),"yyyy-mm"),tblTxn[Month],"<="&ReportMonth)*$K47/12) | K47: =IF($D47="Income",1,-1)
B48: =IFERROR(INDEX(tblCategories[Category],43),"") | C48: =IF($B48="","",IFERROR(INDEX(tblCategories[Group],MATCH($B48,tblCategories[Category],0)),"")) | D48: =IF($B48="","",IFERROR(INDEX(tblCategories[Type],MATCH($B48,tblCategories[Category],0)),"")) | E48: =IF($B48="","",IFERROR(INDEX(tblCategories[Monthly Budget],MATCH($B48,tblCategories[Category],0)),0)) | F48: =IF($B48="","",SUMIFS(tblTxn[View Amount],tblTxn[Month],ReportMonth,tblTxn[Category],$B48)*$K48) | G48: =IF(N(E48)=0,"",IF($D48="Income",F48-E48,E48-F48)) | H48: =IF(N(E48)=0,"",F48/E48) | I48: =IF($B48="","",SUMIFS(tblTxn[View Amount],tblTxn[Category],$B48,tblTxn[Month],">="&TEXT(EDATE(DATE(VALUE(LEFT(ReportMonth,4)),VALUE(RIGHT(ReportMonth,2)),1),-11),"yyyy-mm"),tblTxn[Month],"<="&ReportMonth)*$K48/12) | K48: =IF($D48="Income",1,-1)
B49: =IFERROR(INDEX(tblCategories[Category],44),"") | C49: =IF($B49="","",IFERROR(INDEX(tblCategories[Group],MATCH($B49,tblCategories[Category],0)),"")) | D49: =IF($B49="","",IFERROR(INDEX(tblCategories[Type],MATCH($B49,tblCategories[Category],0)),"")) | E49: =IF($B49="","",IFERROR(INDEX(tblCategories[Monthly Budget],MATCH($B49,tblCategories[Category],0)),0)) | F49: =IF($B49="","",SUMIFS(tblTxn[View Amount],tblTxn[Month],ReportMonth,tblTxn[Category],$B49)*$K49) | G49: =IF(N(E49)=0,"",IF($D49="Income",F49-E49,E49-F49)) | H49: =IF(N(E49)=0,"",F49/E49) | I49: =IF($B49="","",SUMIFS(tblTxn[View Amount],tblTxn[Category],$B49,tblTxn[Month],">="&TEXT(EDATE(DATE(VALUE(LEFT(ReportMonth,4)),VALUE(RIGHT(ReportMonth,2)),1),-11),"yyyy-mm"),tblTxn[Month],"<="&ReportMonth)*$K49/12) | K49: =IF($D49="Income",1,-1)
B50: =IFERROR(INDEX(tblCategories[Category],45),"") | C50: =IF($B50="","",IFERROR(INDEX(tblCategories[Group],MATCH($B50,tblCategories[Category],0)),"")) | D50: =IF($B50="","",IFERROR(INDEX(tblCategories[Type],MATCH($B50,tblCategories[Category],0)),"")) | E50: =IF($B50="","",IFERROR(INDEX(tblCategories[Monthly Budget],MATCH($B50,tblCategories[Category],0)),0)) | F50: =IF($B50="","",SUMIFS(tblTxn[View Amount],tblTxn[Month],ReportMonth,tblTxn[Category],$B50)*$K50) | G50: =IF(N(E50)=0,"",IF($D50="Income",F50-E50,E50-F50)) | H50: =IF(N(E50)=0,"",F50/E50) | I50: =IF($B50="","",SUMIFS(tblTxn[View Amount],tblTxn[Category],$B50,tblTxn[Month],">="&TEXT(EDATE(DATE(VALUE(LEFT(ReportMonth,4)),VALUE(RIGHT(ReportMonth,2)),1),-11),"yyyy-mm"),tblTxn[Month],"<="&ReportMonth)*$K50/12) | K50: =IF($D50="Income",1,-1)
B51: =IFERROR(INDEX(tblCategories[Category],46),"") | C51: =IF($B51="","",IFERROR(INDEX(tblCategories[Group],MATCH($B51,tblCategories[Category],0)),"")) | D51: =IF($B51="","",IFERROR(INDEX(tblCategories[Type],MATCH($B51,tblCategories[Category],0)),"")) | E51: =IF($B51="","",IFERROR(INDEX(tblCategories[Monthly Budget],MATCH($B51,tblCategories[Category],0)),0)) | F51: =IF($B51="","",SUMIFS(tblTxn[View Amount],tblTxn[Month],ReportMonth,tblTxn[Category],$B51)*$K51) | G51: =IF(N(E51)=0,"",IF($D51="Income",F51-E51,E51-F51)) | H51: =IF(N(E51)=0,"",F51/E51) | I51: =IF($B51="","",SUMIFS(tblTxn[View Amount],tblTxn[Category],$B51,tblTxn[Month],">="&TEXT(EDATE(DATE(VALUE(LEFT(ReportMonth,4)),VALUE(RIGHT(ReportMonth,2)),1),-11),"yyyy-mm"),tblTxn[Month],"<="&ReportMonth)*$K51/12) | K51: =IF($D51="Income",1,-1)
B52: =IFERROR(INDEX(tblCategories[Category],47),"") | C52: =IF($B52="","",IFERROR(INDEX(tblCategories[Group],MATCH($B52,tblCategories[Category],0)),"")) | D52: =IF($B52="","",IFERROR(INDEX(tblCategories[Type],MATCH($B52,tblCategories[Category],0)),"")) | E52: =IF($B52="","",IFERROR(INDEX(tblCategories[Monthly Budget],MATCH($B52,tblCategories[Category],0)),0)) | F52: =IF($B52="","",SUMIFS(tblTxn[View Amount],tblTxn[Month],ReportMonth,tblTxn[Category],$B52)*$K52) | G52: =IF(N(E52)=0,"",IF($D52="Income",F52-E52,E52-F52)) | H52: =IF(N(E52)=0,"",F52/E52) | I52: =IF($B52="","",SUMIFS(tblTxn[View Amount],tblTxn[Category],$B52,tblTxn[Month],">="&TEXT(EDATE(DATE(VALUE(LEFT(ReportMonth,4)),VALUE(RIGHT(ReportMonth,2)),1),-11),"yyyy-mm"),tblTxn[Month],"<="&ReportMonth)*$K52/12) | K52: =IF($D52="Income",1,-1)
B53: =IFERROR(INDEX(tblCategories[Category],48),"") | C53: =IF($B53="","",IFERROR(INDEX(tblCategories[Group],MATCH($B53,tblCategories[Category],0)),"")) | D53: =IF($B53="","",IFERROR(INDEX(tblCategories[Type],MATCH($B53,tblCategories[Category],0)),"")) | E53: =IF($B53="","",IFERROR(INDEX(tblCategories[Monthly Budget],MATCH($B53,tblCategories[Category],0)),0)) | F53: =IF($B53="","",SUMIFS(tblTxn[View Amount],tblTxn[Month],ReportMonth,tblTxn[Category],$B53)*$K53) | G53: =IF(N(E53)=0,"",IF($D53="Income",F53-E53,E53-F53)) | H53: =IF(N(E53)=0,"",F53/E53) | I53: =IF($B53="","",SUMIFS(tblTxn[View Amount],tblTxn[Category],$B53,tblTxn[Month],">="&TEXT(EDATE(DATE(VALUE(LEFT(ReportMonth,4)),VALUE(RIGHT(ReportMonth,2)),1),-11),"yyyy-mm"),tblTxn[Month],"<="&ReportMonth)*$K53/12) | K53: =IF($D53="Income",1,-1)
B54: =IFERROR(INDEX(tblCategories[Category],49),"") | C54: =IF($B54="","",IFERROR(INDEX(tblCategories[Group],MATCH($B54,tblCategories[Category],0)),"")) | D54: =IF($B54="","",IFERROR(INDEX(tblCategories[Type],MATCH($B54,tblCategories[Category],0)),"")) | E54: =IF($B54="","",IFERROR(INDEX(tblCategories[Monthly Budget],MATCH($B54,tblCategories[Category],0)),0)) | F54: =IF($B54="","",SUMIFS(tblTxn[View Amount],tblTxn[Month],ReportMonth,tblTxn[Category],$B54)*$K54) | G54: =IF(N(E54)=0,"",IF($D54="Income",F54-E54,E54-F54)) | H54: =IF(N(E54)=0,"",F54/E54) | I54: =IF($B54="","",SUMIFS(tblTxn[View Amount],tblTxn[Category],$B54,tblTxn[Month],">="&TEXT(EDATE(DATE(VALUE(LEFT(ReportMonth,4)),VALUE(RIGHT(ReportMonth,2)),1),-11),"yyyy-mm"),tblTxn[Month],"<="&ReportMonth)*$K54/12) | K54: =IF($D54="Income",1,-1)
B55: =IFERROR(INDEX(tblCategories[Category],50),"") | C55: =IF($B55="","",IFERROR(INDEX(tblCategories[Group],MATCH($B55,tblCategories[Category],0)),"")) | D55: =IF($B55="","",IFERROR(INDEX(tblCategories[Type],MATCH($B55,tblCategories[Category],0)),"")) | E55: =IF($B55="","",IFERROR(INDEX(tblCategories[Monthly Budget],MATCH($B55,tblCategories[Category],0)),0)) | F55: =IF($B55="","",SUMIFS(tblTxn[View Amount],tblTxn[Month],ReportMonth,tblTxn[Category],$B55)*$K55) | G55: =IF(N(E55)=0,"",IF($D55="Income",F55-E55,E55-F55)) | H55: =IF(N(E55)=0,"",F55/E55) | I55: =IF($B55="","",SUMIFS(tblTxn[View Amount],tblTxn[Category],$B55,tblTxn[Month],">="&TEXT(EDATE(DATE(VALUE(LEFT(ReportMonth,4)),VALUE(RIGHT(ReportMonth,2)),1),-11),"yyyy-mm"),tblTxn[Month],"<="&ReportMonth)*$K55/12) | K55: =IF($D55="Income",1,-1)
B56: =IFERROR(INDEX(tblCategories[Category],51),"") | C56: =IF($B56="","",IFERROR(INDEX(tblCategories[Group],MATCH($B56,tblCategories[Category],0)),"")) | D56: =IF($B56="","",IFERROR(INDEX(tblCategories[Type],MATCH($B56,tblCategories[Category],0)),"")) | E56: =IF($B56="","",IFERROR(INDEX(tblCategories[Monthly Budget],MATCH($B56,tblCategories[Category],0)),0)) | F56: =IF($B56="","",SUMIFS(tblTxn[View Amount],tblTxn[Month],ReportMonth,tblTxn[Category],$B56)*$K56) | G56: =IF(N(E56)=0,"",IF($D56="Income",F56-E56,E56-F56)) | H56: =IF(N(E56)=0,"",F56/E56) | I56: =IF($B56="","",SUMIFS(tblTxn[View Amount],tblTxn[Category],$B56,tblTxn[Month],">="&TEXT(EDATE(DATE(VALUE(LEFT(ReportMonth,4)),VALUE(RIGHT(ReportMonth,2)),1),-11),"yyyy-mm"),tblTxn[Month],"<="&ReportMonth)*$K56/12) | K56: =IF($D56="Income",1,-1)
B57: =IFERROR(INDEX(tblCategories[Category],52),"") | C57: =IF($B57="","",IFERROR(INDEX(tblCategories[Group],MATCH($B57,tblCategories[Category],0)),"")) | D57: =IF($B57="","",IFERROR(INDEX(tblCategories[Type],MATCH($B57,tblCategories[Category],0)),"")) | E57: =IF($B57="","",IFERROR(INDEX(tblCategories[Monthly Budget],MATCH($B57,tblCategories[Category],0)),0)) | F57: =IF($B57="","",SUMIFS(tblTxn[View Amount],tblTxn[Month],ReportMonth,tblTxn[Category],$B57)*$K57) | G57: =IF(N(E57)=0,"",IF($D57="Income",F57-E57,E57-F57)) | H57: =IF(N(E57)=0,"",F57/E57) | I57: =IF($B57="","",SUMIFS(tblTxn[View Amount],tblTxn[Category],$B57,tblTxn[Month],">="&TEXT(EDATE(DATE(VALUE(LEFT(ReportMonth,4)),VALUE(RIGHT(ReportMonth,2)),1),-11),"yyyy-mm"),tblTxn[Month],"<="&ReportMonth)*$K57/12) | K57: =IF($D57="Income",1,-1)
B58: =IFERROR(INDEX(tblCategories[Category],53),"") | C58: =IF($B58="","",IFERROR(INDEX(tblCategories[Group],MATCH($B58,tblCategories[Category],0)),"")) | D58: =IF($B58="","",IFERROR(INDEX(tblCategories[Type],MATCH($B58,tblCategories[Category],0)),"")) | E58: =IF($B58="","",IFERROR(INDEX(tblCategories[Monthly Budget],MATCH($B58,tblCategories[Category],0)),0)) | F58: =IF($B58="","",SUMIFS(tblTxn[View Amount],tblTxn[Month],ReportMonth,tblTxn[Category],$B58)*$K58) | G58: =IF(N(E58)=0,"",IF($D58="Income",F58-E58,E58-F58)) | H58: =IF(N(E58)=0,"",F58/E58) | I58: =IF($B58="","",SUMIFS(tblTxn[View Amount],tblTxn[Category],$B58,tblTxn[Month],">="&TEXT(EDATE(DATE(VALUE(LEFT(ReportMonth,4)),VALUE(RIGHT(ReportMonth,2)),1),-11),"yyyy-mm"),tblTxn[Month],"<="&ReportMonth)*$K58/12) | K58: =IF($D58="Income",1,-1)
B59: =IFERROR(INDEX(tblCategories[Category],54),"") | C59: =IF($B59="","",IFERROR(INDEX(tblCategories[Group],MATCH($B59,tblCategories[Category],0)),"")) | D59: =IF($B59="","",IFERROR(INDEX(tblCategories[Type],MATCH($B59,tblCategories[Category],0)),"")) | E59: =IF($B59="","",IFERROR(INDEX(tblCategories[Monthly Budget],MATCH($B59,tblCategories[Category],0)),0)) | F59: =IF($B59="","",SUMIFS(tblTxn[View Amount],tblTxn[Month],ReportMonth,tblTxn[Category],$B59)*$K59) | G59: =IF(N(E59)=0,"",IF($D59="Income",F59-E59,E59-F59)) | H59: =IF(N(E59)=0,"",F59/E59) | I59: =IF($B59="","",SUMIFS(tblTxn[View Amount],tblTxn[Category],$B59,tblTxn[Month],">="&TEXT(EDATE(DATE(VALUE(LEFT(ReportMonth,4)),VALUE(RIGHT(ReportMonth,2)),1),-11),"yyyy-mm"),tblTxn[Month],"<="&ReportMonth)*$K59/12) | K59: =IF($D59="Income",1,-1)
B60: =IFERROR(INDEX(tblCategories[Category],55),"") | C60: =IF($B60="","",IFERROR(INDEX(tblCategories[Group],MATCH($B60,tblCategories[Category],0)),"")) | D60: =IF($B60="","",IFERROR(INDEX(tblCategories[Type],MATCH($B60,tblCategories[Category],0)),"")) | E60: =IF($B60="","",IFERROR(INDEX(tblCategories[Monthly Budget],MATCH($B60,tblCategories[Category],0)),0)) | F60: =IF($B60="","",SUMIFS(tblTxn[View Amount],tblTxn[Month],ReportMonth,tblTxn[Category],$B60)*$K60) | G60: =IF(N(E60)=0,"",IF($D60="Income",F60-E60,E60-F60)) | H60: =IF(N(E60)=0,"",F60/E60) | I60: =IF($B60="","",SUMIFS(tblTxn[View Amount],tblTxn[Category],$B60,tblTxn[Month],">="&TEXT(EDATE(DATE(VALUE(LEFT(ReportMonth,4)),VALUE(RIGHT(ReportMonth,2)),1),-11),"yyyy-mm"),tblTxn[Month],"<="&ReportMonth)*$K60/12) | K60: =IF($D60="Income",1,-1)
B61: =IFERROR(INDEX(tblCategories[Category],56),"") | C61: =IF($B61="","",IFERROR(INDEX(tblCategories[Group],MATCH($B61,tblCategories[Category],0)),"")) | D61: =IF($B61="","",IFERROR(INDEX(tblCategories[Type],MATCH($B61,tblCategories[Category],0)),"")) | E61: =IF($B61="","",IFERROR(INDEX(tblCategories[Monthly Budget],MATCH($B61,tblCategories[Category],0)),0)) | F61: =IF($B61="","",SUMIFS(tblTxn[View Amount],tblTxn[Month],ReportMonth,tblTxn[Category],$B61)*$K61) | G61: =IF(N(E61)=0,"",IF($D61="Income",F61-E61,E61-F61)) | H61: =IF(N(E61)=0,"",F61/E61) | I61: =IF($B61="","",SUMIFS(tblTxn[View Amount],tblTxn[Category],$B61,tblTxn[Month],">="&TEXT(EDATE(DATE(VALUE(LEFT(ReportMonth,4)),VALUE(RIGHT(ReportMonth,2)),1),-11),"yyyy-mm"),tblTxn[Month],"<="&ReportMonth)*$K61/12) | K61: =IF($D61="Income",1,-1)
B62: =IFERROR(INDEX(tblCategories[Category],57),"") | C62: =IF($B62="","",IFERROR(INDEX(tblCategories[Group],MATCH($B62,tblCategories[Category],0)),"")) | D62: =IF($B62="","",IFERROR(INDEX(tblCategories[Type],MATCH($B62,tblCategories[Category],0)),"")) | E62: =IF($B62="","",IFERROR(INDEX(tblCategories[Monthly Budget],MATCH($B62,tblCategories[Category],0)),0)) | F62: =IF($B62="","",SUMIFS(tblTxn[View Amount],tblTxn[Month],ReportMonth,tblTxn[Category],$B62)*$K62) | G62: =IF(N(E62)=0,"",IF($D62="Income",F62-E62,E62-F62)) | H62: =IF(N(E62)=0,"",F62/E62) | I62: =IF($B62="","",SUMIFS(tblTxn[View Amount],tblTxn[Category],$B62,tblTxn[Month],">="&TEXT(EDATE(DATE(VALUE(LEFT(ReportMonth,4)),VALUE(RIGHT(ReportMonth,2)),1),-11),"yyyy-mm"),tblTxn[Month],"<="&ReportMonth)*$K62/12) | K62: =IF($D62="Income",1,-1)
B63: =IFERROR(INDEX(tblCategories[Category],58),"") | C63: =IF($B63="","",IFERROR(INDEX(tblCategories[Group],MATCH($B63,tblCategories[Category],0)),"")) | D63: =IF($B63="","",IFERROR(INDEX(tblCategories[Type],MATCH($B63,tblCategories[Category],0)),"")) | E63: =IF($B63="","",IFERROR(INDEX(tblCategories[Monthly Budget],MATCH($B63,tblCategories[Category],0)),0)) | F63: =IF($B63="","",SUMIFS(tblTxn[View Amount],tblTxn[Month],ReportMonth,tblTxn[Category],$B63)*$K63) | G63: =IF(N(E63)=0,"",IF($D63="Income",F63-E63,E63-F63)) | H63: =IF(N(E63)=0,"",F63/E63) | I63: =IF($B63="","",SUMIFS(tblTxn[View Amount],tblTxn[Category],$B63,tblTxn[Month],">="&TEXT(EDATE(DATE(VALUE(LEFT(ReportMonth,4)),VALUE(RIGHT(ReportMonth,2)),1),-11),"yyyy-mm"),tblTxn[Month],"<="&ReportMonth)*$K63/12) | K63: =IF($D63="Income",1,-1)
B64: =IFERROR(INDEX(tblCategories[Category],59),"") | C64: =IF($B64="","",IFERROR(INDEX(tblCategories[Group],MATCH($B64,tblCategories[Category],0)),"")) | D64: =IF($B64="","",IFERROR(INDEX(tblCategories[Type],MATCH($B64,tblCategories[Category],0)),"")) | E64: =IF($B64="","",IFERROR(INDEX(tblCategories[Monthly Budget],MATCH($B64,tblCategories[Category],0)),0)) | F64: =IF($B64="","",SUMIFS(tblTxn[View Amount],tblTxn[Month],ReportMonth,tblTxn[Category],$B64)*$K64) | G64: =IF(N(E64)=0,"",IF($D64="Income",F64-E64,E64-F64)) | H64: =IF(N(E64)=0,"",F64/E64) | I64: =IF($B64="","",SUMIFS(tblTxn[View Amount],tblTxn[Category],$B64,tblTxn[Month],">="&TEXT(EDATE(DATE(VALUE(LEFT(ReportMonth,4)),VALUE(RIGHT(ReportMonth,2)),1),-11),"yyyy-mm"),tblTxn[Month],"<="&ReportMonth)*$K64/12) | K64: =IF($D64="Income",1,-1)
B65: =IFERROR(INDEX(tblCategories[Category],60),"") | C65: =IF($B65="","",IFERROR(INDEX(tblCategories[Group],MATCH($B65,tblCategories[Category],0)),"")) | D65: =IF($B65="","",IFERROR(INDEX(tblCategories[Type],MATCH($B65,tblCategories[Category],0)),"")) | E65: =IF($B65="","",IFERROR(INDEX(tblCategories[Monthly Budget],MATCH($B65,tblCategories[Category],0)),0)) | F65: =IF($B65="","",SUMIFS(tblTxn[View Amount],tblTxn[Month],ReportMonth,tblTxn[Category],$B65)*$K65) | G65: =IF(N(E65)=0,"",IF($D65="Income",F65-E65,E65-F65)) | H65: =IF(N(E65)=0,"",F65/E65) | I65: =IF($B65="","",SUMIFS(tblTxn[View Amount],tblTxn[Category],$B65,tblTxn[Month],">="&TEXT(EDATE(DATE(VALUE(LEFT(ReportMonth,4)),VALUE(RIGHT(ReportMonth,2)),1),-11),"yyyy-mm"),tblTxn[Month],"<="&ReportMonth)*$K65/12) | K65: =IF($D65="Income",1,-1)
B66: =IFERROR(INDEX(tblCategories[Category],61),"") | C66: =IF($B66="","",IFERROR(INDEX(tblCategories[Group],MATCH($B66,tblCategories[Category],0)),"")) | D66: =IF($B66="","",IFERROR(INDEX(tblCategories[Type],MATCH($B66,tblCategories[Category],0)),"")) | E66: =IF($B66="","",IFERROR(INDEX(tblCategories[Monthly Budget],MATCH($B66,tblCategories[Category],0)),0)) | F66: =IF($B66="","",SUMIFS(tblTxn[View Amount],tblTxn[Month],ReportMonth,tblTxn[Category],$B66)*$K66) | G66: =IF(N(E66)=0,"",IF($D66="Income",F66-E66,E66-F66)) | H66: =IF(N(E66)=0,"",F66/E66) | I66: =IF($B66="","",SUMIFS(tblTxn[View Amount],tblTxn[Category],$B66,tblTxn[Month],">="&TEXT(EDATE(DATE(VALUE(LEFT(ReportMonth,4)),VALUE(RIGHT(ReportMonth,2)),1),-11),"yyyy-mm"),tblTxn[Month],"<="&ReportMonth)*$K66/12) | K66: =IF($D66="Income",1,-1)
B67: =IFERROR(INDEX(tblCategories[Category],62),"") | C67: =IF($B67="","",IFERROR(INDEX(tblCategories[Group],MATCH($B67,tblCategories[Category],0)),"")) | D67: =IF($B67="","",IFERROR(INDEX(tblCategories[Type],MATCH($B67,tblCategories[Category],0)),"")) | E67: =IF($B67="","",IFERROR(INDEX(tblCategories[Monthly Budget],MATCH($B67,tblCategories[Category],0)),0)) | F67: =IF($B67="","",SUMIFS(tblTxn[View Amount],tblTxn[Month],ReportMonth,tblTxn[Category],$B67)*$K67) | G67: =IF(N(E67)=0,"",IF($D67="Income",F67-E67,E67-F67)) | H67: =IF(N(E67)=0,"",F67/E67) | I67: =IF($B67="","",SUMIFS(tblTxn[View Amount],tblTxn[Category],$B67,tblTxn[Month],">="&TEXT(EDATE(DATE(VALUE(LEFT(ReportMonth,4)),VALUE(RIGHT(ReportMonth,2)),1),-11),"yyyy-mm"),tblTxn[Month],"<="&ReportMonth)*$K67/12) | K67: =IF($D67="Income",1,-1)
B68: =IFERROR(INDEX(tblCategories[Category],63),"") | C68: =IF($B68="","",IFERROR(INDEX(tblCategories[Group],MATCH($B68,tblCategories[Category],0)),"")) | D68: =IF($B68="","",IFERROR(INDEX(tblCategories[Type],MATCH($B68,tblCategories[Category],0)),"")) | E68: =IF($B68="","",IFERROR(INDEX(tblCategories[Monthly Budget],MATCH($B68,tblCategories[Category],0)),0)) | F68: =IF($B68="","",SUMIFS(tblTxn[View Amount],tblTxn[Month],ReportMonth,tblTxn[Category],$B68)*$K68) | G68: =IF(N(E68)=0,"",IF($D68="Income",F68-E68,E68-F68)) | H68: =IF(N(E68)=0,"",F68/E68) | I68: =IF($B68="","",SUMIFS(tblTxn[View Amount],tblTxn[Category],$B68,tblTxn[Month],">="&TEXT(EDATE(DATE(VALUE(LEFT(ReportMonth,4)),VALUE(RIGHT(ReportMonth,2)),1),-11),"yyyy-mm"),tblTxn[Month],"<="&ReportMonth)*$K68/12) | K68: =IF($D68="Income",1,-1)
B69: =IFERROR(INDEX(tblCategories[Category],64),"") | C69: =IF($B69="","",IFERROR(INDEX(tblCategories[Group],MATCH($B69,tblCategories[Category],0)),"")) | D69: =IF($B69="","",IFERROR(INDEX(tblCategories[Type],MATCH($B69,tblCategories[Category],0)),"")) | E69: =IF($B69="","",IFERROR(INDEX(tblCategories[Monthly Budget],MATCH($B69,tblCategories[Category],0)),0)) | F69: =IF($B69="","",SUMIFS(tblTxn[View Amount],tblTxn[Month],ReportMonth,tblTxn[Category],$B69)*$K69) | G69: =IF(N(E69)=0,"",IF($D69="Income",F69-E69,E69-F69)) | H69: =IF(N(E69)=0,"",F69/E69) | I69: =IF($B69="","",SUMIFS(tblTxn[View Amount],tblTxn[Category],$B69,tblTxn[Month],">="&TEXT(EDATE(DATE(VALUE(LEFT(ReportMonth,4)),VALUE(RIGHT(ReportMonth,2)),1),-11),"yyyy-mm"),tblTxn[Month],"<="&ReportMonth)*$K69/12) | K69: =IF($D69="Income",1,-1)
B70: =IFERROR(INDEX(tblCategories[Category],65),"") | C70: =IF($B70="","",IFERROR(INDEX(tblCategories[Group],MATCH($B70,tblCategories[Category],0)),"")) | D70: =IF($B70="","",IFERROR(INDEX(tblCategories[Type],MATCH($B70,tblCategories[Category],0)),"")) | E70: =IF($B70="","",IFERROR(INDEX(tblCategories[Monthly Budget],MATCH($B70,tblCategories[Category],0)),0)) | F70: =IF($B70="","",SUMIFS(tblTxn[View Amount],tblTxn[Month],ReportMonth,tblTxn[Category],$B70)*$K70) | G70: =IF(N(E70)=0,"",IF($D70="Income",F70-E70,E70-F70)) | H70: =IF(N(E70)=0,"",F70/E70) | I70: =IF($B70="","",SUMIFS(tblTxn[View Amount],tblTxn[Category],$B70,tblTxn[Month],">="&TEXT(EDATE(DATE(VALUE(LEFT(ReportMonth,4)),VALUE(RIGHT(ReportMonth,2)),1),-11),"yyyy-mm"),tblTxn[Month],"<="&ReportMonth)*$K70/12) | K70: =IF($D70="Income",1,-1)
B71: =IFERROR(INDEX(tblCategories[Category],66),"") | C71: =IF($B71="","",IFERROR(INDEX(tblCategories[Group],MATCH($B71,tblCategories[Category],0)),"")) | D71: =IF($B71="","",IFERROR(INDEX(tblCategories[Type],MATCH($B71,tblCategories[Category],0)),"")) | E71: =IF($B71="","",IFERROR(INDEX(tblCategories[Monthly Budget],MATCH($B71,tblCategories[Category],0)),0)) | F71: =IF($B71="","",SUMIFS(tblTxn[View Amount],tblTxn[Month],ReportMonth,tblTxn[Category],$B71)*$K71) | G71: =IF(N(E71)=0,"",IF($D71="Income",F71-E71,E71-F71)) | H71: =IF(N(E71)=0,"",F71/E71) | I71: =IF($B71="","",SUMIFS(tblTxn[View Amount],tblTxn[Category],$B71,tblTxn[Month],">="&TEXT(EDATE(DATE(VALUE(LEFT(ReportMonth,4)),VALUE(RIGHT(ReportMonth,2)),1),-11),"yyyy-mm"),tblTxn[Month],"<="&ReportMonth)*$K71/12) | K71: =IF($D71="Income",1,-1)
B72: =IFERROR(INDEX(tblCategories[Category],67),"") | C72: =IF($B72="","",IFERROR(INDEX(tblCategories[Group],MATCH($B72,tblCategories[Category],0)),"")) | D72: =IF($B72="","",IFERROR(INDEX(tblCategories[Type],MATCH($B72,tblCategories[Category],0)),"")) | E72: =IF($B72="","",IFERROR(INDEX(tblCategories[Monthly Budget],MATCH($B72,tblCategories[Category],0)),0)) | F72: =IF($B72="","",SUMIFS(tblTxn[View Amount],tblTxn[Month],ReportMonth,tblTxn[Category],$B72)*$K72) | G72: =IF(N(E72)=0,"",IF($D72="Income",F72-E72,E72-F72)) | H72: =IF(N(E72)=0,"",F72/E72) | I72: =IF($B72="","",SUMIFS(tblTxn[View Amount],tblTxn[Category],$B72,tblTxn[Month],">="&TEXT(EDATE(DATE(VALUE(LEFT(ReportMonth,4)),VALUE(RIGHT(ReportMonth,2)),1),-11),"yyyy-mm"),tblTxn[Month],"<="&ReportMonth)*$K72/12) | K72: =IF($D72="Income",1,-1)
B73: =IFERROR(INDEX(tblCategories[Category],68),"") | C73: =IF($B73="","",IFERROR(INDEX(tblCategories[Group],MATCH($B73,tblCategories[Category],0)),"")) | D73: =IF($B73="","",IFERROR(INDEX(tblCategories[Type],MATCH($B73,tblCategories[Category],0)),"")) | E73: =IF($B73="","",IFERROR(INDEX(tblCategories[Monthly Budget],MATCH($B73,tblCategories[Category],0)),0)) | F73: =IF($B73="","",SUMIFS(tblTxn[View Amount],tblTxn[Month],ReportMonth,tblTxn[Category],$B73)*$K73) | G73: =IF(N(E73)=0,"",IF($D73="Income",F73-E73,E73-F73)) | H73: =IF(N(E73)=0,"",F73/E73) | I73: =IF($B73="","",SUMIFS(tblTxn[View Amount],tblTxn[Category],$B73,tblTxn[Month],">="&TEXT(EDATE(DATE(VALUE(LEFT(ReportMonth,4)),VALUE(RIGHT(ReportMonth,2)),1),-11),"yyyy-mm"),tblTxn[Month],"<="&ReportMonth)*$K73/12) | K73: =IF($D73="Income",1,-1)
B74: =IFERROR(INDEX(tblCategories[Category],69),"") | C74: =IF($B74="","",IFERROR(INDEX(tblCategories[Group],MATCH($B74,tblCategories[Category],0)),"")) | D74: =IF($B74="","",IFERROR(INDEX(tblCategories[Type],MATCH($B74,tblCategories[Category],0)),"")) | E74: =IF($B74="","",IFERROR(INDEX(tblCategories[Monthly Budget],MATCH($B74,tblCategories[Category],0)),0)) | F74: =IF($B74="","",SUMIFS(tblTxn[View Amount],tblTxn[Month],ReportMonth,tblTxn[Category],$B74)*$K74) | G74: =IF(N(E74)=0,"",IF($D74="Income",F74-E74,E74-F74)) | H74: =IF(N(E74)=0,"",F74/E74) | I74: =IF($B74="","",SUMIFS(tblTxn[View Amount],tblTxn[Category],$B74,tblTxn[Month],">="&TEXT(EDATE(DATE(VALUE(LEFT(ReportMonth,4)),VALUE(RIGHT(ReportMonth,2)),1),-11),"yyyy-mm"),tblTxn[Month],"<="&ReportMonth)*$K74/12) | K74: =IF($D74="Income",1,-1)
B75: =IFERROR(INDEX(tblCategories[Category],70),"") | C75: =IF($B75="","",IFERROR(INDEX(tblCategories[Group],MATCH($B75,tblCategories[Category],0)),"")) | D75: =IF($B75="","",IFERROR(INDEX(tblCategories[Type],MATCH($B75,tblCategories[Category],0)),"")) | E75: =IF($B75="","",IFERROR(INDEX(tblCategories[Monthly Budget],MATCH($B75,tblCategories[Category],0)),0)) | F75: =IF($B75="","",SUMIFS(tblTxn[View Amount],tblTxn[Month],ReportMonth,tblTxn[Category],$B75)*$K75) | G75: =IF(N(E75)=0,"",IF($D75="Income",F75-E75,E75-F75)) | H75: =IF(N(E75)=0,"",F75/E75) | I75: =IF($B75="","",SUMIFS(tblTxn[View Amount],tblTxn[Category],$B75,tblTxn[Month],">="&TEXT(EDATE(DATE(VALUE(LEFT(ReportMonth,4)),VALUE(RIGHT(ReportMonth,2)),1),-11),"yyyy-mm"),tblTxn[Month],"<="&ReportMonth)*$K75/12) | K75: =IF($D75="Income",1,-1)
B76: =IFERROR(INDEX(tblCategories[Category],71),"") | C76: =IF($B76="","",IFERROR(INDEX(tblCategories[Group],MATCH($B76,tblCategories[Category],0)),"")) | D76: =IF($B76="","",IFERROR(INDEX(tblCategories[Type],MATCH($B76,tblCategories[Category],0)),"")) | E76: =IF($B76="","",IFERROR(INDEX(tblCategories[Monthly Budget],MATCH($B76,tblCategories[Category],0)),0)) | F76: =IF($B76="","",SUMIFS(tblTxn[View Amount],tblTxn[Month],ReportMonth,tblTxn[Category],$B76)*$K76) | G76: =IF(N(E76)=0,"",IF($D76="Income",F76-E76,E76-F76)) | H76: =IF(N(E76)=0,"",F76/E76) | I76: =IF($B76="","",SUMIFS(tblTxn[View Amount],tblTxn[Category],$B76,tblTxn[Month],">="&TEXT(EDATE(DATE(VALUE(LEFT(ReportMonth,4)),VALUE(RIGHT(ReportMonth,2)),1),-11),"yyyy-mm"),tblTxn[Month],"<="&ReportMonth)*$K76/12) | K76: =IF($D76="Income",1,-1)
B77: =IFERROR(INDEX(tblCategories[Category],72),"") | C77: =IF($B77="","",IFERROR(INDEX(tblCategories[Group],MATCH($B77,tblCategories[Category],0)),"")) | D77: =IF($B77="","",IFERROR(INDEX(tblCategories[Type],MATCH($B77,tblCategories[Category],0)),"")) | E77: =IF($B77="","",IFERROR(INDEX(tblCategories[Monthly Budget],MATCH($B77,tblCategories[Category],0)),0)) | F77: =IF($B77="","",SUMIFS(tblTxn[View Amount],tblTxn[Month],ReportMonth,tblTxn[Category],$B77)*$K77) | G77: =IF(N(E77)=0,"",IF($D77="Income",F77-E77,E77-F77)) | H77: =IF(N(E77)=0,"",F77/E77) | I77: =IF($B77="","",SUMIFS(tblTxn[View Amount],tblTxn[Category],$B77,tblTxn[Month],">="&TEXT(EDATE(DATE(VALUE(LEFT(ReportMonth,4)),VALUE(RIGHT(ReportMonth,2)),1),-11),"yyyy-mm"),tblTxn[Month],"<="&ReportMonth)*$K77/12) | K77: =IF($D77="Income",1,-1)
B78: =IFERROR(INDEX(tblCategories[Category],73),"") | C78: =IF($B78="","",IFERROR(INDEX(tblCategories[Group],MATCH($B78,tblCategories[Category],0)),"")) | D78: =IF($B78="","",IFERROR(INDEX(tblCategories[Type],MATCH($B78,tblCategories[Category],0)),"")) | E78: =IF($B78="","",IFERROR(INDEX(tblCategories[Monthly Budget],MATCH($B78,tblCategories[Category],0)),0)) | F78: =IF($B78="","",SUMIFS(tblTxn[View Amount],tblTxn[Month],ReportMonth,tblTxn[Category],$B78)*$K78) | G78: =IF(N(E78)=0,"",IF($D78="Income",F78-E78,E78-F78)) | H78: =IF(N(E78)=0,"",F78/E78) | I78: =IF($B78="","",SUMIFS(tblTxn[View Amount],tblTxn[Category],$B78,tblTxn[Month],">="&TEXT(EDATE(DATE(VALUE(LEFT(ReportMonth,4)),VALUE(RIGHT(ReportMonth,2)),1),-11),"yyyy-mm"),tblTxn[Month],"<="&ReportMonth)*$K78/12) | K78: =IF($D78="Income",1,-1)
B79: =IFERROR(INDEX(tblCategories[Category],74),"") | C79: =IF($B79="","",IFERROR(INDEX(tblCategories[Group],MATCH($B79,tblCategories[Category],0)),"")) | D79: =IF($B79="","",IFERROR(INDEX(tblCategories[Type],MATCH($B79,tblCategories[Category],0)),"")) | E79: =IF($B79="","",IFERROR(INDEX(tblCategories[Monthly Budget],MATCH($B79,tblCategories[Category],0)),0)) | F79: =IF($B79="","",SUMIFS(tblTxn[View Amount],tblTxn[Month],ReportMonth,tblTxn[Category],$B79)*$K79) | G79: =IF(N(E79)=0,"",IF($D79="Income",F79-E79,E79-F79)) | H79: =IF(N(E79)=0,"",F79/E79) | I79: =IF($B79="","",SUMIFS(tblTxn[View Amount],tblTxn[Category],$B79,tblTxn[Month],">="&TEXT(EDATE(DATE(VALUE(LEFT(ReportMonth,4)),VALUE(RIGHT(ReportMonth,2)),1),-11),"yyyy-mm"),tblTxn[Month],"<="&ReportMonth)*$K79/12) | K79: =IF($D79="Income",1,-1)
B80: =IFERROR(INDEX(tblCategories[Category],75),"") | C80: =IF($B80="","",IFERROR(INDEX(tblCategories[Group],MATCH($B80,tblCategories[Category],0)),"")) | D80: =IF($B80="","",IFERROR(INDEX(tblCategories[Type],MATCH($B80,tblCategories[Category],0)),"")) | E80: =IF($B80="","",IFERROR(INDEX(tblCategories[Monthly Budget],MATCH($B80,tblCategories[Category],0)),0)) | F80: =IF($B80="","",SUMIFS(tblTxn[View Amount],tblTxn[Month],ReportMonth,tblTxn[Category],$B80)*$K80) | G80: =IF(N(E80)=0,"",IF($D80="Income",F80-E80,E80-F80)) | H80: =IF(N(E80)=0,"",F80/E80) | I80: =IF($B80="","",SUMIFS(tblTxn[View Amount],tblTxn[Category],$B80,tblTxn[Month],">="&TEXT(EDATE(DATE(VALUE(LEFT(ReportMonth,4)),VALUE(RIGHT(ReportMonth,2)),1),-11),"yyyy-mm"),tblTxn[Month],"<="&ReportMonth)*$K80/12) | K80: =IF($D80="Income",1,-1)
B81: =IFERROR(INDEX(tblCategories[Category],76),"") | C81: =IF($B81="","",IFERROR(INDEX(tblCategories[Group],MATCH($B81,tblCategories[Category],0)),"")) | D81: =IF($B81="","",IFERROR(INDEX(tblCategories[Type],MATCH($B81,tblCategories[Category],0)),"")) | E81: =IF($B81="","",IFERROR(INDEX(tblCategories[Monthly Budget],MATCH($B81,tblCategories[Category],0)),0)) | F81: =IF($B81="","",SUMIFS(tblTxn[View Amount],tblTxn[Month],ReportMonth,tblTxn[Category],$B81)*$K81) | G81: =IF(N(E81)=0,"",IF($D81="Income",F81-E81,E81-F81)) | H81: =IF(N(E81)=0,"",F81/E81) | I81: =IF($B81="","",SUMIFS(tblTxn[View Amount],tblTxn[Category],$B81,tblTxn[Month],">="&TEXT(EDATE(DATE(VALUE(LEFT(ReportMonth,4)),VALUE(RIGHT(ReportMonth,2)),1),-11),"yyyy-mm"),tblTxn[Month],"<="&ReportMonth)*$K81/12) | K81: =IF($D81="Income",1,-1)
B82: =IFERROR(INDEX(tblCategories[Category],77),"") | C82: =IF($B82="","",IFERROR(INDEX(tblCategories[Group],MATCH($B82,tblCategories[Category],0)),"")) | D82: =IF($B82="","",IFERROR(INDEX(tblCategories[Type],MATCH($B82,tblCategories[Category],0)),"")) | E82: =IF($B82="","",IFERROR(INDEX(tblCategories[Monthly Budget],MATCH($B82,tblCategories[Category],0)),0)) | F82: =IF($B82="","",SUMIFS(tblTxn[View Amount],tblTxn[Month],ReportMonth,tblTxn[Category],$B82)*$K82) | G82: =IF(N(E82)=0,"",IF($D82="Income",F82-E82,E82-F82)) | H82: =IF(N(E82)=0,"",F82/E82) | I82: =IF($B82="","",SUMIFS(tblTxn[View Amount],tblTxn[Category],$B82,tblTxn[Month],">="&TEXT(EDATE(DATE(VALUE(LEFT(ReportMonth,4)),VALUE(RIGHT(ReportMonth,2)),1),-11),"yyyy-mm"),tblTxn[Month],"<="&ReportMonth)*$K82/12) | K82: =IF($D82="Income",1,-1)
B83: =IFERROR(INDEX(tblCategories[Category],78),"") | C83: =IF($B83="","",IFERROR(INDEX(tblCategories[Group],MATCH($B83,tblCategories[Category],0)),"")) | D83: =IF($B83="","",IFERROR(INDEX(tblCategories[Type],MATCH($B83,tblCategories[Category],0)),"")) | E83: =IF($B83="","",IFERROR(INDEX(tblCategories[Monthly Budget],MATCH($B83,tblCategories[Category],0)),0)) | F83: =IF($B83="","",SUMIFS(tblTxn[View Amount],tblTxn[Month],ReportMonth,tblTxn[Category],$B83)*$K83) | G83: =IF(N(E83)=0,"",IF($D83="Income",F83-E83,E83-F83)) | H83: =IF(N(E83)=0,"",F83/E83) | I83: =IF($B83="","",SUMIFS(tblTxn[View Amount],tblTxn[Category],$B83,tblTxn[Month],">="&TEXT(EDATE(DATE(VALUE(LEFT(ReportMonth,4)),VALUE(RIGHT(ReportMonth,2)),1),-11),"yyyy-mm"),tblTxn[Month],"<="&ReportMonth)*$K83/12) | K83: =IF($D83="Income",1,-1)
B84: =IFERROR(INDEX(tblCategories[Category],79),"") | C84: =IF($B84="","",IFERROR(INDEX(tblCategories[Group],MATCH($B84,tblCategories[Category],0)),"")) | D84: =IF($B84="","",IFERROR(INDEX(tblCategories[Type],MATCH($B84,tblCategories[Category],0)),"")) | E84: =IF($B84="","",IFERROR(INDEX(tblCategories[Monthly Budget],MATCH($B84,tblCategories[Category],0)),0)) | F84: =IF($B84="","",SUMIFS(tblTxn[View Amount],tblTxn[Month],ReportMonth,tblTxn[Category],$B84)*$K84) | G84: =IF(N(E84)=0,"",IF($D84="Income",F84-E84,E84-F84)) | H84: =IF(N(E84)=0,"",F84/E84) | I84: =IF($B84="","",SUMIFS(tblTxn[View Amount],tblTxn[Category],$B84,tblTxn[Month],">="&TEXT(EDATE(DATE(VALUE(LEFT(ReportMonth,4)),VALUE(RIGHT(ReportMonth,2)),1),-11),"yyyy-mm"),tblTxn[Month],"<="&ReportMonth)*$K84/12) | K84: =IF($D84="Income",1,-1)
B85: =IFERROR(INDEX(tblCategories[Category],80),"") | C85: =IF($B85="","",IFERROR(INDEX(tblCategories[Group],MATCH($B85,tblCategories[Category],0)),"")) | D85: =IF($B85="","",IFERROR(INDEX(tblCategories[Type],MATCH($B85,tblCategories[Category],0)),"")) | E85: =IF($B85="","",IFERROR(INDEX(tblCategories[Monthly Budget],MATCH($B85,tblCategories[Category],0)),0)) | F85: =IF($B85="","",SUMIFS(tblTxn[View Amount],tblTxn[Month],ReportMonth,tblTxn[Category],$B85)*$K85) | G85: =IF(N(E85)=0,"",IF($D85="Income",F85-E85,E85-F85)) | H85: =IF(N(E85)=0,"",F85/E85) | I85: =IF($B85="","",SUMIFS(tblTxn[View Amount],tblTxn[Category],$B85,tblTxn[Month],">="&TEXT(EDATE(DATE(VALUE(LEFT(ReportMonth,4)),VALUE(RIGHT(ReportMonth,2)),1),-11),"yyyy-mm"),tblTxn[Month],"<="&ReportMonth)*$K85/12) | K85: =IF($D85="Income",1,-1)
B86: =IFERROR(INDEX(tblCategories[Category],81),"") | C86: =IF($B86="","",IFERROR(INDEX(tblCategories[Group],MATCH($B86,tblCategories[Category],0)),"")) | D86: =IF($B86="","",IFERROR(INDEX(tblCategories[Type],MATCH($B86,tblCategories[Category],0)),"")) | E86: =IF($B86="","",IFERROR(INDEX(tblCategories[Monthly Budget],MATCH($B86,tblCategories[Category],0)),0)) | F86: =IF($B86="","",SUMIFS(tblTxn[View Amount],tblTxn[Month],ReportMonth,tblTxn[Category],$B86)*$K86) | G86: =IF(N(E86)=0,"",IF($D86="Income",F86-E86,E86-F86)) | H86: =IF(N(E86)=0,"",F86/E86) | I86: =IF($B86="","",SUMIFS(tblTxn[View Amount],tblTxn[Category],$B86,tblTxn[Month],">="&TEXT(EDATE(DATE(VALUE(LEFT(ReportMonth,4)),VALUE(RIGHT(ReportMonth,2)),1),-11),"yyyy-mm"),tblTxn[Month],"<="&ReportMonth)*$K86/12) | K86: =IF($D86="Income",1,-1)
B87: =IFERROR(INDEX(tblCategories[Category],82),"") | C87: =IF($B87="","",IFERROR(INDEX(tblCategories[Group],MATCH($B87,tblCategories[Category],0)),"")) | D87: =IF($B87="","",IFERROR(INDEX(tblCategories[Type],MATCH($B87,tblCategories[Category],0)),"")) | E87: =IF($B87="","",IFERROR(INDEX(tblCategories[Monthly Budget],MATCH($B87,tblCategories[Category],0)),0)) | F87: =IF($B87="","",SUMIFS(tblTxn[View Amount],tblTxn[Month],ReportMonth,tblTxn[Category],$B87)*$K87) | G87: =IF(N(E87)=0,"",IF($D87="Income",F87-E87,E87-F87)) | H87: =IF(N(E87)=0,"",F87/E87) | I87: =IF($B87="","",SUMIFS(tblTxn[View Amount],tblTxn[Category],$B87,tblTxn[Month],">="&TEXT(EDATE(DATE(VALUE(LEFT(ReportMonth,4)),VALUE(RIGHT(ReportMonth,2)),1),-11),"yyyy-mm"),tblTxn[Month],"<="&ReportMonth)*$K87/12) | K87: =IF($D87="Income",1,-1)
B88: =IFERROR(INDEX(tblCategories[Category],83),"") | C88: =IF($B88="","",IFERROR(INDEX(tblCategories[Group],MATCH($B88,tblCategories[Category],0)),"")) | D88: =IF($B88="","",IFERROR(INDEX(tblCategories[Type],MATCH($B88,tblCategories[Category],0)),"")) | E88: =IF($B88="","",IFERROR(INDEX(tblCategories[Monthly Budget],MATCH($B88,tblCategories[Category],0)),0)) | F88: =IF($B88="","",SUMIFS(tblTxn[View Amount],tblTxn[Month],ReportMonth,tblTxn[Category],$B88)*$K88) | G88: =IF(N(E88)=0,"",IF($D88="Income",F88-E88,E88-F88)) | H88: =IF(N(E88)=0,"",F88/E88) | I88: =IF($B88="","",SUMIFS(tblTxn[View Amount],tblTxn[Category],$B88,tblTxn[Month],">="&TEXT(EDATE(DATE(VALUE(LEFT(ReportMonth,4)),VALUE(RIGHT(ReportMonth,2)),1),-11),"yyyy-mm"),tblTxn[Month],"<="&ReportMonth)*$K88/12) | K88: =IF($D88="Income",1,-1)
B89: =IFERROR(INDEX(tblCategories[Category],84),"") | C89: =IF($B89="","",IFERROR(INDEX(tblCategories[Group],MATCH($B89,tblCategories[Category],0)),"")) | D89: =IF($B89="","",IFERROR(INDEX(tblCategories[Type],MATCH($B89,tblCategories[Category],0)),"")) | E89: =IF($B89="","",IFERROR(INDEX(tblCategories[Monthly Budget],MATCH($B89,tblCategories[Category],0)),0)) | F89: =IF($B89="","",SUMIFS(tblTxn[View Amount],tblTxn[Month],ReportMonth,tblTxn[Category],$B89)*$K89) | G89: =IF(N(E89)=0,"",IF($D89="Income",F89-E89,E89-F89)) | H89: =IF(N(E89)=0,"",F89/E89) | I89: =IF($B89="","",SUMIFS(tblTxn[View Amount],tblTxn[Category],$B89,tblTxn[Month],">="&TEXT(EDATE(DATE(VALUE(LEFT(ReportMonth,4)),VALUE(RIGHT(ReportMonth,2)),1),-11),"yyyy-mm"),tblTxn[Month],"<="&ReportMonth)*$K89/12) | K89: =IF($D89="Income",1,-1)
B90: =IFERROR(INDEX(tblCategories[Category],85),"") | C90: =IF($B90="","",IFERROR(INDEX(tblCategories[Group],MATCH($B90,tblCategories[Category],0)),"")) | D90: =IF($B90="","",IFERROR(INDEX(tblCategories[Type],MATCH($B90,tblCategories[Category],0)),"")) | E90: =IF($B90="","",IFERROR(INDEX(tblCategories[Monthly Budget],MATCH($B90,tblCategories[Category],0)),0)) | F90: =IF($B90="","",SUMIFS(tblTxn[View Amount],tblTxn[Month],ReportMonth,tblTxn[Category],$B90)*$K90) | G90: =IF(N(E90)=0,"",IF($D90="Income",F90-E90,E90-F90)) | H90: =IF(N(E90)=0,"",F90/E90) | I90: =IF($B90="","",SUMIFS(tblTxn[View Amount],tblTxn[Category],$B90,tblTxn[Month],">="&TEXT(EDATE(DATE(VALUE(LEFT(ReportMonth,4)),VALUE(RIGHT(ReportMonth,2)),1),-11),"yyyy-mm"),tblTxn[Month],"<="&ReportMonth)*$K90/12) | K90: =IF($D90="Income",1,-1)
B91: =IFERROR(INDEX(tblCategories[Category],86),"") | C91: =IF($B91="","",IFERROR(INDEX(tblCategories[Group],MATCH($B91,tblCategories[Category],0)),"")) | D91: =IF($B91="","",IFERROR(INDEX(tblCategories[Type],MATCH($B91,tblCategories[Category],0)),"")) | E91: =IF($B91="","",IFERROR(INDEX(tblCategories[Monthly Budget],MATCH($B91,tblCategories[Category],0)),0)) | F91: =IF($B91="","",SUMIFS(tblTxn[View Amount],tblTxn[Month],ReportMonth,tblTxn[Category],$B91)*$K91) | G91: =IF(N(E91)=0,"",IF($D91="Income",F91-E91,E91-F91)) | H91: =IF(N(E91)=0,"",F91/E91) | I91: =IF($B91="","",SUMIFS(tblTxn[View Amount],tblTxn[Category],$B91,tblTxn[Month],">="&TEXT(EDATE(DATE(VALUE(LEFT(ReportMonth,4)),VALUE(RIGHT(ReportMonth,2)),1),-11),"yyyy-mm"),tblTxn[Month],"<="&ReportMonth)*$K91/12) | K91: =IF($D91="Income",1,-1)
B92: =IFERROR(INDEX(tblCategories[Category],87),"") | C92: =IF($B92="","",IFERROR(INDEX(tblCategories[Group],MATCH($B92,tblCategories[Category],0)),"")) | D92: =IF($B92="","",IFERROR(INDEX(tblCategories[Type],MATCH($B92,tblCategories[Category],0)),"")) | E92: =IF($B92="","",IFERROR(INDEX(tblCategories[Monthly Budget],MATCH($B92,tblCategories[Category],0)),0)) | F92: =IF($B92="","",SUMIFS(tblTxn[View Amount],tblTxn[Month],ReportMonth,tblTxn[Category],$B92)*$K92) | G92: =IF(N(E92)=0,"",IF($D92="Income",F92-E92,E92-F92)) | H92: =IF(N(E92)=0,"",F92/E92) | I92: =IF($B92="","",SUMIFS(tblTxn[View Amount],tblTxn[Category],$B92,tblTxn[Month],">="&TEXT(EDATE(DATE(VALUE(LEFT(ReportMonth,4)),VALUE(RIGHT(ReportMonth,2)),1),-11),"yyyy-mm"),tblTxn[Month],"<="&ReportMonth)*$K92/12) | K92: =IF($D92="Income",1,-1)
B93: =IFERROR(INDEX(tblCategories[Category],88),"") | C93: =IF($B93="","",IFERROR(INDEX(tblCategories[Group],MATCH($B93,tblCategories[Category],0)),"")) | D93: =IF($B93="","",IFERROR(INDEX(tblCategories[Type],MATCH($B93,tblCategories[Category],0)),"")) | E93: =IF($B93="","",IFERROR(INDEX(tblCategories[Monthly Budget],MATCH($B93,tblCategories[Category],0)),0)) | F93: =IF($B93="","",SUMIFS(tblTxn[View Amount],tblTxn[Month],ReportMonth,tblTxn[Category],$B93)*$K93) | G93: =IF(N(E93)=0,"",IF($D93="Income",F93-E93,E93-F93)) | H93: =IF(N(E93)=0,"",F93/E93) | I93: =IF($B93="","",SUMIFS(tblTxn[View Amount],tblTxn[Category],$B93,tblTxn[Month],">="&TEXT(EDATE(DATE(VALUE(LEFT(ReportMonth,4)),VALUE(RIGHT(ReportMonth,2)),1),-11),"yyyy-mm"),tblTxn[Month],"<="&ReportMonth)*$K93/12) | K93: =IF($D93="Income",1,-1)
B94: =IFERROR(INDEX(tblCategories[Category],89),"") | C94: =IF($B94="","",IFERROR(INDEX(tblCategories[Group],MATCH($B94,tblCategories[Category],0)),"")) | D94: =IF($B94="","",IFERROR(INDEX(tblCategories[Type],MATCH($B94,tblCategories[Category],0)),"")) | E94: =IF($B94="","",IFERROR(INDEX(tblCategories[Monthly Budget],MATCH($B94,tblCategories[Category],0)),0)) | F94: =IF($B94="","",SUMIFS(tblTxn[View Amount],tblTxn[Month],ReportMonth,tblTxn[Category],$B94)*$K94) | G94: =IF(N(E94)=0,"",IF($D94="Income",F94-E94,E94-F94)) | H94: =IF(N(E94)=0,"",F94/E94) | I94: =IF($B94="","",SUMIFS(tblTxn[View Amount],tblTxn[Category],$B94,tblTxn[Month],">="&TEXT(EDATE(DATE(VALUE(LEFT(ReportMonth,4)),VALUE(RIGHT(ReportMonth,2)),1),-11),"yyyy-mm"),tblTxn[Month],"<="&ReportMonth)*$K94/12) | K94: =IF($D94="Income",1,-1)
B95: =IFERROR(INDEX(tblCategories[Category],90),"") | C95: =IF($B95="","",IFERROR(INDEX(tblCategories[Group],MATCH($B95,tblCategories[Category],0)),"")) | D95: =IF($B95="","",IFERROR(INDEX(tblCategories[Type],MATCH($B95,tblCategories[Category],0)),"")) | E95: =IF($B95="","",IFERROR(INDEX(tblCategories[Monthly Budget],MATCH($B95,tblCategories[Category],0)),0)) | F95: =IF($B95="","",SUMIFS(tblTxn[View Amount],tblTxn[Month],ReportMonth,tblTxn[Category],$B95)*$K95) | G95: =IF(N(E95)=0,"",IF($D95="Income",F95-E95,E95-F95)) | H95: =IF(N(E95)=0,"",F95/E95) | I95: =IF($B95="","",SUMIFS(tblTxn[View Amount],tblTxn[Category],$B95,tblTxn[Month],">="&TEXT(EDATE(DATE(VALUE(LEFT(ReportMonth,4)),VALUE(RIGHT(ReportMonth,2)),1),-11),"yyyy-mm"),tblTxn[Month],"<="&ReportMonth)*$K95/12) | K95: =IF($D95="Income",1,-1)
B96: =IFERROR(INDEX(tblCategories[Category],91),"") | C96: =IF($B96="","",IFERROR(INDEX(tblCategories[Group],MATCH($B96,tblCategories[Category],0)),"")) | D96: =IF($B96="","",IFERROR(INDEX(tblCategories[Type],MATCH($B96,tblCategories[Category],0)),"")) | E96: =IF($B96="","",IFERROR(INDEX(tblCategories[Monthly Budget],MATCH($B96,tblCategories[Category],0)),0)) | F96: =IF($B96="","",SUMIFS(tblTxn[View Amount],tblTxn[Month],ReportMonth,tblTxn[Category],$B96)*$K96) | G96: =IF(N(E96)=0,"",IF($D96="Income",F96-E96,E96-F96)) | H96: =IF(N(E96)=0,"",F96/E96) | I96: =IF($B96="","",SUMIFS(tblTxn[View Amount],tblTxn[Category],$B96,tblTxn[Month],">="&TEXT(EDATE(DATE(VALUE(LEFT(ReportMonth,4)),VALUE(RIGHT(ReportMonth,2)),1),-11),"yyyy-mm"),tblTxn[Month],"<="&ReportMonth)*$K96/12) | K96: =IF($D96="Income",1,-1)
B97: =IFERROR(INDEX(tblCategories[Category],92),"") | C97: =IF($B97="","",IFERROR(INDEX(tblCategories[Group],MATCH($B97,tblCategories[Category],0)),"")) | D97: =IF($B97="","",IFERROR(INDEX(tblCategories[Type],MATCH($B97,tblCategories[Category],0)),"")) | E97: =IF($B97="","",IFERROR(INDEX(tblCategories[Monthly Budget],MATCH($B97,tblCategories[Category],0)),0)) | F97: =IF($B97="","",SUMIFS(tblTxn[View Amount],tblTxn[Month],ReportMonth,tblTxn[Category],$B97)*$K97) | G97: =IF(N(E97)=0,"",IF($D97="Income",F97-E97,E97-F97)) | H97: =IF(N(E97)=0,"",F97/E97) | I97: =IF($B97="","",SUMIFS(tblTxn[View Amount],tblTxn[Category],$B97,tblTxn[Month],">="&TEXT(EDATE(DATE(VALUE(LEFT(ReportMonth,4)),VALUE(RIGHT(ReportMonth,2)),1),-11),"yyyy-mm"),tblTxn[Month],"<="&ReportMonth)*$K97/12) | K97: =IF($D97="Income",1,-1)
B98: =IFERROR(INDEX(tblCategories[Category],93),"") | C98: =IF($B98="","",IFERROR(INDEX(tblCategories[Group],MATCH($B98,tblCategories[Category],0)),"")) | D98: =IF($B98="","",IFERROR(INDEX(tblCategories[Type],MATCH($B98,tblCategories[Category],0)),"")) | E98: =IF($B98="","",IFERROR(INDEX(tblCategories[Monthly Budget],MATCH($B98,tblCategories[Category],0)),0)) | F98: =IF($B98="","",SUMIFS(tblTxn[View Amount],tblTxn[Month],ReportMonth,tblTxn[Category],$B98)*$K98) | G98: =IF(N(E98)=0,"",IF($D98="Income",F98-E98,E98-F98)) | H98: =IF(N(E98)=0,"",F98/E98) | I98: =IF($B98="","",SUMIFS(tblTxn[View Amount],tblTxn[Category],$B98,tblTxn[Month],">="&TEXT(EDATE(DATE(VALUE(LEFT(ReportMonth,4)),VALUE(RIGHT(ReportMonth,2)),1),-11),"yyyy-mm"),tblTxn[Month],"<="&ReportMonth)*$K98/12) | K98: =IF($D98="Income",1,-1)
B99: =IFERROR(INDEX(tblCategories[Category],94),"") | C99: =IF($B99="","",IFERROR(INDEX(tblCategories[Group],MATCH($B99,tblCategories[Category],0)),"")) | D99: =IF($B99="","",IFERROR(INDEX(tblCategories[Type],MATCH($B99,tblCategories[Category],0)),"")) | E99: =IF($B99="","",IFERROR(INDEX(tblCategories[Monthly Budget],MATCH($B99,tblCategories[Category],0)),0)) | F99: =IF($B99="","",SUMIFS(tblTxn[View Amount],tblTxn[Month],ReportMonth,tblTxn[Category],$B99)*$K99) | G99: =IF(N(E99)=0,"",IF($D99="Income",F99-E99,E99-F99)) | H99: =IF(N(E99)=0,"",F99/E99) | I99: =IF($B99="","",SUMIFS(tblTxn[View Amount],tblTxn[Category],$B99,tblTxn[Month],">="&TEXT(EDATE(DATE(VALUE(LEFT(ReportMonth,4)),VALUE(RIGHT(ReportMonth,2)),1),-11),"yyyy-mm"),tblTxn[Month],"<="&ReportMonth)*$K99/12) | K99: =IF($D99="Income",1,-1)
B100: =IFERROR(INDEX(tblCategories[Category],95),"") | C100: =IF($B100="","",IFERROR(INDEX(tblCategories[Group],MATCH($B100,tblCategories[Category],0)),"")) | D100: =IF($B100="","",IFERROR(INDEX(tblCategories[Type],MATCH($B100,tblCategories[Category],0)),"")) | E100: =IF($B100="","",IFERROR(INDEX(tblCategories[Monthly Budget],MATCH($B100,tblCategories[Category],0)),0)) | F100: =IF($B100="","",SUMIFS(tblTxn[View Amount],tblTxn[Month],ReportMonth,tblTxn[Category],$B100)*$K100) | G100: =IF(N(E100)=0,"",IF($D100="Income",F100-E100,E100-F100)) | H100: =IF(N(E100)=0,"",F100/E100) | I100: =IF($B100="","",SUMIFS(tblTxn[View Amount],tblTxn[Category],$B100,tblTxn[Month],">="&TEXT(EDATE(DATE(VALUE(LEFT(ReportMonth,4)),VALUE(RIGHT(ReportMonth,2)),1),-11),"yyyy-mm"),tblTxn[Month],"<="&ReportMonth)*$K100/12) | K100: =IF($D100="Income",1,-1)
B101: =IFERROR(INDEX(tblCategories[Category],96),"") | C101: =IF($B101="","",IFERROR(INDEX(tblCategories[Group],MATCH($B101,tblCategories[Category],0)),"")) | D101: =IF($B101="","",IFERROR(INDEX(tblCategories[Type],MATCH($B101,tblCategories[Category],0)),"")) | E101: =IF($B101="","",IFERROR(INDEX(tblCategories[Monthly Budget],MATCH($B101,tblCategories[Category],0)),0)) | F101: =IF($B101="","",SUMIFS(tblTxn[View Amount],tblTxn[Month],ReportMonth,tblTxn[Category],$B101)*$K101) | G101: =IF(N(E101)=0,"",IF($D101="Income",F101-E101,E101-F101)) | H101: =IF(N(E101)=0,"",F101/E101) | I101: =IF($B101="","",SUMIFS(tblTxn[View Amount],tblTxn[Category],$B101,tblTxn[Month],">="&TEXT(EDATE(DATE(VALUE(LEFT(ReportMonth,4)),VALUE(RIGHT(ReportMonth,2)),1),-11),"yyyy-mm"),tblTxn[Month],"<="&ReportMonth)*$K101/12) | K101: =IF($D101="Income",1,-1)
...

Sheet Reports
B1: Reports
B2: Twelve months ending with the report month chosen on the Dashboard, in the same view (household or one person).
B4: Month | C4: =TEXT(EDATE(DATE(VALUE(LEFT(ReportMonth,4)),VALUE(RIGHT(ReportMonth,2)),1),-11),"yyyy-mm") | D4: =TEXT(EDATE(DATE(VALUE(LEFT(ReportMonth,4)),VALUE(RIGHT(ReportMonth,2)),1),-10),"yyyy-mm") | E4: =TEXT(EDATE(DATE(VALUE(LEFT(ReportMonth,4)),VALUE(RIGHT(ReportMonth,2)),1),-9),"yyyy-mm") | F4: =TEXT(EDATE(DATE(VALUE(LEFT(ReportMonth,4)),VALUE(RIGHT(ReportMonth,2)),1),-8),"yyyy-mm") | G4: =TEXT(EDATE(DATE(VALUE(LEFT(ReportMonth,4)),VALUE(RIGHT(ReportMonth,2)),1),-7),"yyyy-mm") | H4: =TEXT(EDATE(DATE(VALUE(LEFT(ReportMonth,4)),VALUE(RIGHT(ReportMonth,2)),1),-6),"yyyy-mm") | I4: =TEXT(EDATE(DATE(VALUE(LEFT(ReportMonth,4)),VALUE(RIGHT(ReportMonth,2)),1),-5),"yyyy-mm") | J4: =TEXT(EDATE(DATE(VALUE(LEFT(ReportMonth,4)),VALUE(RIGHT(ReportMonth,2)),1),-4),"yyyy-mm") | K4: =TEXT(EDATE(DATE(VALUE(LEFT(ReportMonth,4)),VALUE(RIGHT(ReportMonth,2)),1),-3),"yyyy-mm") | L4: =TEXT(EDATE(DATE(VALUE(LEFT(ReportMonth,4)),VALUE(RIGHT(ReportMonth,2)),1),-2),"yyyy-mm") | M4: =TEXT(EDATE(DATE(VALUE(LEFT(ReportMonth,4)),VALUE(RIGHT(ReportMonth,2)),1),-1),"yyyy-mm") | N4: =TEXT(EDATE(DATE(VALUE(LEFT(ReportMonth,4)),VALUE(RIGHT(ReportMonth,2)),1),0),"yyyy-mm") | O4: Total
B5: Money in | C5: =SUMIFS(tblTxn[View Amount],tblTxn[Month],C$4,tblTxn[Type],"Income") | D5: =SUMIFS(tblTxn[View Amount],tblTxn[Month],D$4,tblTxn[Type],"Income") | E5: =SUMIFS(tblTxn[View Amount],tblTxn[Month],E$4,tblTxn[Type],"Income") | F5: =SUMIFS(tblTxn[View Amount],tblTxn[Month],F$4,tblTxn[Type],"Income") | G5: =SUMIFS(tblTxn[View Amount],tblTxn[Month],G$4,tblTxn[Type],"Income") | H5: =SUMIFS(tblTxn[View Amount],tblTxn[Month],H$4,tblTxn[Type],"Income") | I5: =SUMIFS(tblTxn[View Amount],tblTxn[Month],I$4,tblTxn[Type],"Income") | J5: =SUMIFS(tblTxn[View Amount],tblTxn[Month],J$4,tblTxn[Type],"Income") | ... N5: =SUMIFS(tblTxn[View Amount],tblTxn[Month],N$4,tblTxn[Type],"Income") | O5: =SUM(C5:N5)
B6: Money out | C6: =-SUMIFS(tblTxn[View Amount],tblTxn[Month],C$4,tblTxn[Type],"Expense") | D6: =-SUMIFS(tblTxn[View Amount],tblTxn[Month],D$4,tblTxn[Type],"Expense") | E6: =-SUMIFS(tblTxn[View Amount],tblTxn[Month],E$4,tblTxn[Type],"Expense") | F6: =-SUMIFS(tblTxn[View Amount],tblTxn[Month],F$4,tblTxn[Type],"Expense") | G6: =-SUMIFS(tblTxn[View Amount],tblTxn[Month],G$4,tblTxn[Type],"Expense") | H6: =-SUMIFS(tblTxn[View Amount],tblTxn[Month],H$4,tblTxn[Type],"Expense") | I6: =-SUMIFS(tblTxn[View Amount],tblTxn[Month],I$4,tblTxn[Type],"Expense") | J6: =-SUMIFS(tblTxn[View Amount],tblTxn[Month],J$4,tblTxn[Type],"Expense") | ... N6: =-SUMIFS(tblTxn[View Amount],tblTxn[Month],N$4,tblTxn[Type],"Expense") | O6: =SUM(C6:N6)
B7: Saved & invested | C7: =-SUMIFS(tblTxn[View Amount],tblTxn[Month],C$4,tblTxn[Type],"Saving") | D7: =-SUMIFS(tblTxn[View Amount],tblTxn[Month],D$4,tblTxn[Type],"Saving") | E7: =-SUMIFS(tblTxn[View Amount],tblTxn[Month],E$4,tblTxn[Type],"Saving") | F7: =-SUMIFS(tblTxn[View Amount],tblTxn[Month],F$4,tblTxn[Type],"Saving") | G7: =-SUMIFS(tblTxn[View Amount],tblTxn[Month],G$4,tblTxn[Type],"Saving") | H7: =-SUMIFS(tblTxn[View Amount],tblTxn[Month],H$4,tblTxn[Type],"Saving") | I7: =-SUMIFS(tblTxn[View Amount],tblTxn[Month],I$4,tblTxn[Type],"Saving") | J7: =-SUMIFS(tblTxn[View Amount],tblTxn[Month],J$4,tblTxn[Type],"Saving") | ... N7: =-SUMIFS(tblTxn[View Amount],tblTxn[Month],N$4,tblTxn[Type],"Saving") | O7: =SUM(C7:N7)
B8: Net cash flow | C8: =C5-C6-C7 | D8: =D5-D6-D7 | E8: =E5-E6-E7 | F8: =F5-F6-F7 | G8: =G5-G6-G7 | H8: =H5-H6-H7 | I8: =I5-I6-I7 | J8: =J5-J6-J7 | ... N8: =N5-N6-N7 | O8: =SUM(C8:N8)
B9: Savings rate | C9: =IFERROR((C5-C6)/C5,"") | D9: =IFERROR((D5-D6)/D5,"") | E9: =IFERROR((E5-E6)/E5,"") | F9: =IFERROR((F5-F6)/F5,"") | G9: =IFERROR((G5-G6)/G5,"") | H9: =IFERROR((H5-H6)/H5,"") | I9: =IFERROR((I5-I6)/I5,"") | J9: =IFERROR((J5-J6)/J5,"") | ... O9: =IFERROR((O5-O6)/O5,"")
B10: Essential spending | C10: =-SUMIFS(tblTxn[View Amount],tblTxn[Month],C$4,tblTxn[Type],"Expense",tblTxn[Essential],"Yes") | D10: =-SUMIFS(tblTxn[View Amount],tblTxn[Month],D$4,tblTxn[Type],"Expense",tblTxn[Essential],"Yes") | E10: =-SUMIFS(tblTxn[View Amount],tblTxn[Month],E$4,tblTxn[Type],"Expense",tblTxn[Essential],"Yes") | F10: =-SUMIFS(tblTxn[View Amount],tblTxn[Month],F$4,tblTxn[Type],"Expense",tblTxn[Essential],"Yes") | G10: =-SUMIFS(tblTxn[View Amount],tblTxn[Month],G$4,tblTxn[Type],"Expense",tblTxn[Essential],"Yes") | H10: =-SUMIFS(tblTxn[View Amount],tblTxn[Month],H$4,tblTxn[Type],"Expense",tblTxn[Essential],"Yes") | I10: =-SUMIFS(tblTxn[View Amount],tblTxn[Month],I$4,tblTxn[Type],"Expense",tblTxn[Essential],"Yes") | J10: =-SUMIFS(tblTxn[View Amount],tblTxn[Month],J$4,tblTxn[Type],"Expense",tblTxn[Essential],"Yes") | ... N10: =-SUMIFS(tblTxn[View Amount],tblTxn[Month],N$4,tblTxn[Type],"Expense",tblTxn[Essential],"Yes") | O10: =SUM(C10:N10)
B11: Discretionary spending | C11: =C6-C10 | D11: =D6-D10 | E11: =E6-E10 | F11: =F6-F10 | G11: =G6-G10 | H11: =H6-H10 | I11: =I6-I10 | J11: =J6-J10 | ... N11: =N6-N10 | O11: =SUM(C11:N11)
B12: Transactions | C12: =COUNTIFS(tblTxn[Month],C$4) | D12: =COUNTIFS(tblTxn[Month],D$4) | E12: =COUNTIFS(tblTxn[Month],E$4) | F12: =COUNTIFS(tblTxn[Month],F$4) | G12: =COUNTIFS(tblTxn[Month],G$4) | H12: =COUNTIFS(tblTxn[Month],H$4) | I12: =COUNTIFS(tblTxn[Month],I$4) | J12: =COUNTIFS(tblTxn[Month],J$4) | ... N12: =COUNTIFS(tblTxn[Month],N$4) | O12: =SUM(C12:N12)
B14: Spending by group
B15: Housing | C15: =-SUMIFS(tblTxn[View Amount],tblTxn[Month],C$4,tblTxn[Group],$B15) | D15: =-SUMIFS(tblTxn[View Amount],tblTxn[Month],D$4,tblTxn[Group],$B15) | E15: =-SUMIFS(tblTxn[View Amount],tblTxn[Month],E$4,tblTxn[Group],$B15) | F15: =-SUMIFS(tblTxn[View Amount],tblTxn[Month],F$4,tblTxn[Group],$B15) | G15: =-SUMIFS(tblTxn[View Amount],tblTxn[Month],G$4,tblTxn[Group],$B15) | H15: =-SUMIFS(tblTxn[View Amount],tblTxn[Month],H$4,tblTxn[Group],$B15) | I15: =-SUMIFS(tblTxn[View Amount],tblTxn[Month],I$4,tblTxn[Group],$B15) | J15: =-SUMIFS(tblTxn[View Amount],tblTxn[Month],J$4,tblTxn[Group],$B15) | ... N15: =-SUMIFS(tblTxn[View Amount],tblTxn[Month],N$4,tblTxn[Group],$B15) | O15: =SUM(C15:N15)
B16: Utilities | C16: =-SUMIFS(tblTxn[View Amount],tblTxn[Month],C$4,tblTxn[Group],$B16) | D16: =-SUMIFS(tblTxn[View Amount],tblTxn[Month],D$4,tblTxn[Group],$B16) | E16: =-SUMIFS(tblTxn[View Amount],tblTxn[Month],E$4,tblTxn[Group],$B16) | F16: =-SUMIFS(tblTxn[View Amount],tblTxn[Month],F$4,tblTxn[Group],$B16) | G16: =-SUMIFS(tblTxn[View Amount],tblTxn[Month],G$4,tblTxn[Group],$B16) | H16: =-SUMIFS(tblTxn[View Amount],tblTxn[Month],H$4,tblTxn[Group],$B16) | I16: =-SUMIFS(tblTxn[View Amount],tblTxn[Month],I$4,tblTxn[Group],$B16) | J16: =-SUMIFS(tblTxn[View Amount],tblTxn[Month],J$4,tblTxn[Group],$B16) | ... N16: =-SUMIFS(tblTxn[View Amount],tblTxn[Month],N$4,tblTxn[Group],$B16) | O16: =SUM(C16:N16)
B17: Food | C17: =-SUMIFS(tblTxn[View Amount],tblTxn[Month],C$4,tblTxn[Group],$B17) | D17: =-SUMIFS(tblTxn[View Amount],tblTxn[Month],D$4,tblTxn[Group],$B17) | E17: =-SUMIFS(tblTxn[View Amount],tblTxn[Month],E$4,tblTxn[Group],$B17) | F17: =-SUMIFS(tblTxn[View Amount],tblTxn[Month],F$4,tblTxn[Group],$B17) | G17: =-SUMIFS(tblTxn[View Amount],tblTxn[Month],G$4,tblTxn[Group],$B17) | H17: =-SUMIFS(tblTxn[View Amount],tblTxn[Month],H$4,tblTxn[Group],$B17) | I17: =-SUMIFS(tblTxn[View Amount],tblTxn[Month],I$4,tblTxn[Group],$B17) | J17: =-SUMIFS(tblTxn[View Amount],tblTxn[Month],J$4,tblTxn[Group],$B17) | ... N17: =-SUMIFS(tblTxn[View Amount],tblTxn[Month],N$4,tblTxn[Group],$B17) | O17: =SUM(C17:N17)
B18: Transportation | C18: =-SUMIFS(tblTxn[View Amount],tblTxn[Month],C$4,tblTxn[Group],$B18) | D18: =-SUMIFS(tblTxn[View Amount],tblTxn[Month],D$4,tblTxn[Group],$B18) | E18: =-SUMIFS(tblTxn[View Amount],tblTxn[Month],E$4,tblTxn[Group],$B18) | F18: =-SUMIFS(tblTxn[View Amount],tblTxn[Month],F$4,tblTxn[Group],$B18) | G18: =-SUMIFS(tblTxn[View Amount],tblTxn[Month],G$4,tblTxn[Group],$B18) | H18: =-SUMIFS(tblTxn[View Amount],tblTxn[Month],H$4,tblTxn[Group],$B18) | I18: =-SUMIFS(tblTxn[View Amount],tblTxn[Month],I$4,tblTxn[Group],$B18) | J18: =-SUMIFS(tblTxn[View Amount],tblTxn[Month],J$4,tblTxn[Group],$B18) | ... N18: =-SUMIFS(tblTxn[View Amount],tblTxn[Month],N$4,tblTxn[Group],$B18) | O18: =SUM(C18:N18)
B19: Health | C19: =-SUMIFS(tblTxn[View Amount],tblTxn[Month],C$4,tblTxn[Group],$B19) | D19: =-SUMIFS(tblTxn[View Amount],tblTxn[Month],D$4,tblTxn[Group],$B19) | E19: =-SUMIFS(tblTxn[View Amount],tblTxn[Month],E$4,tblTxn[Group],$B19) | F19: =-SUMIFS(tblTxn[View Amount],tblTxn[Month],F$4,tblTxn[Group],$B19) | G19: =-SUMIFS(tblTxn[View Amount],tblTxn[Month],G$4,tblTxn[Group],$B19) | H19: =-SUMIFS(tblTxn[View Amount],tblTxn[Month],H$4,tblTxn[Group],$B19) | I19: =-SUMIFS(tblTxn[View Amount],tblTxn[Month],I$4,tblTxn[Group],$B19) | J19: =-SUMIFS(tblTxn[View Amount],tblTxn[Month],J$4,tblTxn[Group],$B19) | ... N19: =-SUMIFS(tblTxn[View Amount],tblTxn[Month],N$4,tblTxn[Group],$B19) | O19: =SUM(C19:N19)
B20: Family | C20: =-SUMIFS(tblTxn[View Amount],tblTxn[Month],C$4,tblTxn[Group],$B20) | D20: =-SUMIFS(tblTxn[View Amount],tblTxn[Month],D$4,tblTxn[Group],$B20) | E20: =-SUMIFS(tblTxn[View Amount],tblTxn[Month],E$4,tblTxn[Group],$B20) | F20: =-SUMIFS(tblTxn[View Amount],tblTxn[Month],F$4,tblTxn[Group],$B20) | G20: =-SUMIFS(tblTxn[View Amount],tblTxn[Month],G$4,tblTxn[Group],$B20) | H20: =-SUMIFS(tblTxn[View Amount],tblTxn[Month],H$4,tblTxn[Group],$B20) | I20: =-SUMIFS(tblTxn[View Amount],tblTxn[Month],I$4,tblTxn[Group],$B20) | J20: =-SUMIFS(tblTxn[View Amount],tblTxn[Month],J$4,tblTxn[Group],$B20) | ... N20: =-SUMIFS(tblTxn[View Amount],tblTxn[Month],N$4,tblTxn[Group],$B20) | O20: =SUM(C20:N20)
B21: Education | C21: =-SUMIFS(tblTxn[View Amount],tblTxn[Month],C$4,tblTxn[Group],$B21) | D21: =-SUMIFS(tblTxn[View Amount],tblTxn[Month],D$4,tblTxn[Group],$B21) | E21: =-SUMIFS(tblTxn[View Amount],tblTxn[Month],E$4,tblTxn[Group],$B21) | F21: =-SUMIFS(tblTxn[View Amount],tblTxn[Month],F$4,tblTxn[Group],$B21) | G21: =-SUMIFS(tblTxn[View Amount],tblTxn[Month],G$4,tblTxn[Group],$B21) | H21: =-SUMIFS(tblTxn[View Amount],tblTxn[Month],H$4,tblTxn[Group],$B21) | I21: =-SUMIFS(tblTxn[View Amount],tblTxn[Month],I$4,tblTxn[Group],$B21) | J21: =-SUMIFS(tblTxn[View Amount],tblTxn[Month],J$4,tblTxn[Group],$B21) | ... N21: =-SUMIFS(tblTxn[View Amount],tblTxn[Month],N$4,tblTxn[Group],$B21) | O21: =SUM(C21:N21)
B22: Personal | C22: =-SUMIFS(tblTxn[View Amount],tblTxn[Month],C$4,tblTxn[Group],$B22) | D22: =-SUMIFS(tblTxn[View Amount],tblTxn[Month],D$4,tblTxn[Group],$B22) | E22: =-SUMIFS(tblTxn[View Amount],tblTxn[Month],E$4,tblTxn[Group],$B22) | F22: =-SUMIFS(tblTxn[View Amount],tblTxn[Month],F$4,tblTxn[Group],$B22) | G22: =-SUMIFS(tblTxn[View Amount],tblTxn[Month],G$4,tblTxn[Group],$B22) | H22: =-SUMIFS(tblTxn[View Amount],tblTxn[Month],H$4,tblTxn[Group],$B22) | I22: =-SUMIFS(tblTxn[View Amount],tblTxn[Month],I$4,tblTxn[Group],$B22) | J22: =-SUMIFS(tblTxn[View Amount],tblTxn[Month],J$4,tblTxn[Group],$B22) | ... N22: =-SUMIFS(tblTxn[View Amount],tblTxn[Month],N$4,tblTxn[Group],$B22) | O22: =SUM(C22:N22)
B23: Travel | C23: =-SUMIFS(tblTxn[View Amount],tblTxn[Month],C$4,tblTxn[Group],$B23) | D23: =-SUMIFS(tblTxn[View Amount],tblTxn[Month],D$4,tblTxn[Group],$B23) | E23: =-SUMIFS(tblTxn[View Amount],tblTxn[Month],E$4,tblTxn[Group],$B23) | F23: =-SUMIFS(tblTxn[View Amount],tblTxn[Month],F$4,tblTxn[Group],$B23) | G23: =-SUMIFS(tblTxn[View Amount],tblTxn[Month],G$4,tblTxn[Group],$B23) | H23: =-SUMIFS(tblTxn[View Amount],tblTxn[Month],H$4,tblTxn[Group],$B23) | I23: =-SUMIFS(tblTxn[View Amount],tblTxn[Month],I$4,tblTxn[Group],$B23) | J23: =-SUMIFS(tblTxn[View Amount],tblTxn[Month],J$4,tblTxn[Group],$B23) | ... N23: =-SUMIFS(tblTxn[View Amount],tblTxn[Month],N$4,tblTxn[Group],$B23) | O23: =SUM(C23:N23)
B24: Financial | C24: =-SUMIFS(tblTxn[View Amount],tblTxn[Month],C$4,tblTxn[Group],$B24) | D24: =-SUMIFS(tblTxn[View Amount],tblTxn[Month],D$4,tblTxn[Group],$B24) | E24: =-SUMIFS(tblTxn[View Amount],tblTxn[Month],E$4,tblTxn[Group],$B24) | F24: =-SUMIFS(tblTxn[View Amount],tblTxn[Month],F$4,tblTxn[Group],$B24) | G24: =-SUMIFS(tblTxn[View Amount],tblTxn[Month],G$4,tblTxn[Group],$B24) | H24: =-SUMIFS(tblTxn[View Amount],tblTxn[Month],H$4,tblTxn[Group],$B24) | I24: =-SUMIFS(tblTxn[View Amount],tblTxn[Month],I$4,tblTxn[Group],$B24) | J24: =-SUMIFS(tblTxn[View Amount],tblTxn[Month],J$4,tblTxn[Group],$B24) | ... N24: =-SUMIFS(tblTxn[View Amount],tblTxn[Month],N$4,tblTxn[Group],$B24) | O24: =SUM(C24:N24)
B25: Saving | C25: =-SUMIFS(tblTxn[View Amount],tblTxn[Month],C$4,tblTxn[Group],$B25) | D25: =-SUMIFS(tblTxn[View Amount],tblTxn[Month],D$4,tblTxn[Group],$B25) | E25: =-SUMIFS(tblTxn[View Amount],tblTxn[Month],E$4,tblTxn[Group],$B25) | F25: =-SUMIFS(tblTxn[View Amount],tblTxn[Month],F$4,tblTxn[Group],$B25) | G25: =-SUMIFS(tblTxn[View Amount],tblTxn[Month],G$4,tblTxn[Group],$B25) | H25: =-SUMIFS(tblTxn[View Amount],tblTxn[Month],H$4,tblTxn[Group],$B25) | I25: =-SUMIFS(tblTxn[View Amount],tblTxn[Month],I$4,tblTxn[Group],$B25) | J25: =-SUMIFS(tblTxn[View Amount],tblTxn[Month],J$4,tblTxn[Group],$B25) | ... N25: =-SUMIFS(tblTxn[View Amount],tblTxn[Month],N$4,tblTxn[Group],$B25) | O25: =SUM(C25:N25)
B26: Other | C26: =-SUMIFS(tblTxn[View Amount],tblTxn[Month],C$4,tblTxn[Group],$B26) | D26: =-SUMIFS(tblTxn[View Amount],tblTxn[Month],D$4,tblTxn[Group],$B26) | E26: =-SUMIFS(tblTxn[View Amount],tblTxn[Month],E$4,tblTxn[Group],$B26) | F26: =-SUMIFS(tblTxn[View Amount],tblTxn[Month],F$4,tblTxn[Group],$B26) | G26: =-SUMIFS(tblTxn[View Amount],tblTxn[Month],G$4,tblTxn[Group],$B26) | H26: =-SUMIFS(tblTxn[View Amount],tblTxn[Month],H$4,tblTxn[Group],$B26) | I26: =-SUMIFS(tblTxn[View Amount],tblTxn[Month],I$4,tblTxn[Group],$B26) | J26: =-SUMIFS(tblTxn[View Amount],tblTxn[Month],J$4,tblTxn[Group],$B26) | ... N26: =-SUMIFS(tblTxn[View Amount],tblTxn[Month],N$4,tblTxn[Group],$B26) | O26: =SUM(C26:N26)
B28: By category (income positive, spending positive)
B29: =IFERROR(INDEX(tblCategories[Category],1),"") | C29: =IF($B29="","",SUMIFS(tblTxn[View Amount],tblTxn[Month],C$4,tblTxn[Category],$B29)*$P29) | D29: =IF($B29="","",SUMIFS(tblTxn[View Amount],tblTxn[Month],D$4,tblTxn[Category],$B29)*$P29) | E29: =IF($B29="","",SUMIFS(tblTxn[View Amount],tblTxn[Month],E$4,tblTxn[Category],$B29)*$P29) | F29: =IF($B29="","",SUMIFS(tblTxn[View Amount],tblTxn[Month],F$4,tblTxn[Category],$B29)*$P29) | G29: =IF($B29="","",SUMIFS(tblTxn[View Amount],tblTxn[Month],G$4,tblTxn[Category],$B29)*$P29) | H29: =IF($B29="","",SUMIFS(tblTxn[View Amount],tblTxn[Month],H$4,tblTxn[Category],$B29)*$P29) | I29: =IF($B29="","",SUMIFS(tblTxn[View Amount],tblTxn[Month],I$4,tblTxn[Category],$B29)*$P29) | J29: =IF($B29="","",SUMIFS(tblTxn[View Amount],tblTxn[Month],J$4,tblTxn[Category],$B29)*$P29) | ... N29: =IF($B29="","",SUMIFS(tblTxn[View Amount],tblTxn[Month],N$4,tblTxn[Category],$B29)*$P29) | O29: =IF($B29="","",SUM(C29:N29)) | P29: =IF($B29="",0,IFERROR(IF(INDEX(tblCategories[Type],MATCH($B29,tblCategories[Category],0))="Income",1,-1),-1)) | Q29: =IF(AND($B29<>"",$P29<>1,N($N29)>0),$N29+ROW()/1E+7,-1)
B30: =IFERROR(INDEX(tblCategories[Category],2),"") | C30: =IF($B30="","",SUMIFS(tblTxn[View Amount],tblTxn[Month],C$4,tblTxn[Category],$B30)*$P30) | D30: =IF($B30="","",SUMIFS(tblTxn[View Amount],tblTxn[Month],D$4,tblTxn[Category],$B30)*$P30) | E30: =IF($B30="","",SUMIFS(tblTxn[View Amount],tblTxn[Month],E$4,tblTxn[Category],$B30)*$P30) | F30: =IF($B30="","",SUMIFS(tblTxn[View Amount],tblTxn[Month],F$4,tblTxn[Category],$B30)*$P30) | G30: =IF($B30="","",SUMIFS(tblTxn[View Amount],tblTxn[Month],G$4,tblTxn[Category],$B30)*$P30) | H30: =IF($B30="","",SUMIFS(tblTxn[View Amount],tblTxn[Month],H$4,tblTxn[Category],$B30)*$P30) | I30: =IF($B30="","",SUMIFS(tblTxn[View Amount],tblTxn[Month],I$4,tblTxn[Category],$B30)*$P30) | J30: =IF($B30="","",SUMIFS(tblTxn[View Amount],tblTxn[Month],J$4,tblTxn[Category],$B30)*$P30) | ... N30: =IF($B30="","",SUMIFS(tblTxn[View Amount],tblTxn[Month],N$4,tblTxn[Category],$B30)*$P30) | O30: =IF($B30="","",SUM(C30:N30)) | P30: =IF($B30="",0,IFERROR(IF(INDEX(tblCategories[Type],MATCH($B30,tblCategories[Category],0))="Income",1,-1),-1)) | Q30: =IF(AND($B30<>"",$P30<>1,N($N30)>0),$N30+ROW()/1E+7,-1)
B31: =IFERROR(INDEX(tblCategories[Category],3),"") | C31: =IF($B31="","",SUMIFS(tblTxn[View Amount],tblTxn[Month],C$4,tblTxn[Category],$B31)*$P31) | D31: =IF($B31="","",SUMIFS(tblTxn[View Amount],tblTxn[Month],D$4,tblTxn[Category],$B31)*$P31) | E31: =IF($B31="","",SUMIFS(tblTxn[View Amount],tblTxn[Month],E$4,tblTxn[Category],$B31)*$P31) | F31: =IF($B31="","",SUMIFS(tblTxn[View Amount],tblTxn[Month],F$4,tblTxn[Category],$B31)*$P31) | G31: =IF($B31="","",SUMIFS(tblTxn[View Amount],tblTxn[Month],G$4,tblTxn[Category],$B31)*$P31) | H31: =IF($B31="","",SUMIFS(tblTxn[View Amount],tblTxn[Month],H$4,tblTxn[Category],$B31)*$P31) | I31: =IF($B31="","",SUMIFS(tblTxn[View Amount],tblTxn[Month],I$4,tblTxn[Category],$B31)*$P31) | J31: =IF($B31="","",SUMIFS(tblTxn[View Amount],tblTxn[Month],J$4,tblTxn[Category],$B31)*$P31) | ... N31: =IF($B31="","",SUMIFS(tblTxn[View Amount],tblTxn[Month],N$4,tblTxn[Category],$B31)*$P31) | O31: =IF($B31="","",SUM(C31:N31)) | P31: =IF($B31="",0,IFERROR(IF(INDEX(tblCategories[Type],MATCH($B31,tblCategories[Category],0))="Income",1,-1),-1)) | Q31: =IF(AND($B31<>"",$P31<>1,N($N31)>0),$N31+ROW()/1E+7,-1)
B32: =IFERROR(INDEX(tblCategories[Category],4),"") | C32: =IF($B32="","",SUMIFS(tblTxn[View Amount],tblTxn[Month],C$4,tblTxn[Category],$B32)*$P32) | D32: =IF($B32="","",SUMIFS(tblTxn[View Amount],tblTxn[Month],D$4,tblTxn[Category],$B32)*$P32) | E32: =IF($B32="","",SUMIFS(tblTxn[View Amount],tblTxn[Month],E$4,tblTxn[Category],$B32)*$P32) | F32: =IF($B32="","",SUMIFS(tblTxn[View Amount],tblTxn[Month],F$4,tblTxn[Category],$B32)*$P32) | G32: =IF($B32="","",SUMIFS(tblTxn[View Amount],tblTxn[Month],G$4,tblTxn[Category],$B32)*$P32) | H32: =IF($B32="","",SUMIFS(tblTxn[View Amount],tblTxn[Month],H$4,tblTxn[Category],$B32)*$P32) | I32: =IF($B32="","",SUMIFS(tblTxn[View Amount],tblTxn[Month],I$4,tblTxn[Category],$B32)*$P32) | J32: =IF($B32="","",SUMIFS(tblTxn[View Amount],tblTxn[Month],J$4,tblTxn[Category],$B32)*$P32) | ... N32: =IF($B32="","",SUMIFS(tblTxn[View Amount],tblTxn[Month],N$4,tblTxn[Category],$B32)*$P32) | O32: =IF($B32="","",SUM(C32:N32)) | P32: =IF($B32="",0,IFERROR(IF(INDEX(tblCategories[Type],MATCH($B32,tblCategories[Category],0))="Income",1,-1),-1)) | Q32: =IF(AND($B32<>"",$P32<>1,N($N32)>0),$N32+ROW()/1E+7,-1)
B33: =IFERROR(INDEX(tblCategories[Category],5),"") | C33: =IF($B33="","",SUMIFS(tblTxn[View Amount],tblTxn[Month],C$4,tblTxn[Category],$B33)*$P33) | D33: =IF($B33="","",SUMIFS(tblTxn[View Amount],tblTxn[Month],D$4,tblTxn[Category],$B33)*$P33) | E33: =IF($B33="","",SUMIFS(tblTxn[View Amount],tblTxn[Month],E$4,tblTxn[Category],$B33)*$P33) | F33: =IF($B33="","",SUMIFS(tblTxn[View Amount],tblTxn[Month],F$4,tblTxn[Category],$B33)*$P33) | G33: =IF($B33="","",SUMIFS(tblTxn[View Amount],tblTxn[Month],G$4,tblTxn[Category],$B33)*$P33) | H33: =IF($B33="","",SUMIFS(tblTxn[View Amount],tblTxn[Month],H$4,tblTxn[Category],$B33)*$P33) | I33: =IF($B33="","",SUMIFS(tblTxn[View Amount],tblTxn[Month],I$4,tblTxn[Category],$B33)*$P33) | J33: =IF($B33="","",SUMIFS(tblTxn[View Amount],tblTxn[Month],J$4,tblTxn[Category],$B33)*$P33) | ... N33: =IF($B33="","",SUMIFS(tblTxn[View Amount],tblTxn[Month],N$4,tblTxn[Category],$B33)*$P33) | O33: =IF($B33="","",SUM(C33:N33)) | P33: =IF($B33="",0,IFERROR(IF(INDEX(tblCategories[Type],MATCH($B33,tblCategories[Category],0))="Income",1,-1),-1)) | Q33: =IF(AND($B33<>"",$P33<>1,N($N33)>0),$N33+ROW()/1E+7,-1)
B34: =IFERROR(INDEX(tblCategories[Category],6),"") | C34: =IF($B34="","",SUMIFS(tblTxn[View Amount],tblTxn[Month],C$4,tblTxn[Category],$B34)*$P34) | D34: =IF($B34="","",SUMIFS(tblTxn[View Amount],tblTxn[Month],D$4,tblTxn[Category],$B34)*$P34) | E34: =IF($B34="","",SUMIFS(tblTxn[View Amount],tblTxn[Month],E$4,tblTxn[Category],$B34)*$P34) | F34: =IF($B34="","",SUMIFS(tblTxn[View Amount],tblTxn[Month],F$4,tblTxn[Category],$B34)*$P34) | G34: =IF($B34="","",SUMIFS(tblTxn[View Amount],tblTxn[Month],G$4,tblTxn[Category],$B34)*$P34) | H34: =IF($B34="","",SUMIFS(tblTxn[View Amount],tblTxn[Month],H$4,tblTxn[Category],$B34)*$P34) | I34: =IF($B34="","",SUMIFS(tblTxn[View Amount],tblTxn[Month],I$4,tblTxn[Category],$B34)*$P34) | J34: =IF($B34="","",SUMIFS(tblTxn[View Amount],tblTxn[Month],J$4,tblTxn[Category],$B34)*$P34) | ... N34: =IF($B34="","",SUMIFS(tblTxn[View Amount],tblTxn[Month],N$4,tblTxn[Category],$B34)*$P34) | O34: =IF($B34="","",SUM(C34:N34)) | P34: =IF($B34="",0,IFERROR(IF(INDEX(tblCategories[Type],MATCH($B34,tblCategories[Category],0))="Income",1,-1),-1)) | Q34: =IF(AND($B34<>"",$P34<>1,N($N34)>0),$N34+ROW()/1E+7,-1)
B35: =IFERROR(INDEX(tblCategories[Category],7),"") | C35: =IF($B35="","",SUMIFS(tblTxn[View Amount],tblTxn[Month],C$4,tblTxn[Category],$B35)*$P35) | D35: =IF($B35="","",SUMIFS(tblTxn[View Amount],tblTxn[Month],D$4,tblTxn[Category],$B35)*$P35) | E35: =IF($B35="","",SUMIFS(tblTxn[View Amount],tblTxn[Month],E$4,tblTxn[Category],$B35)*$P35) | F35: =IF($B35="","",SUMIFS(tblTxn[View Amount],tblTxn[Month],F$4,tblTxn[Category],$B35)*$P35) | G35: =IF($B35="","",SUMIFS(tblTxn[View Amount],tblTxn[Month],G$4,tblTxn[Category],$B35)*$P35) | H35: =IF($B35="","",SUMIFS(tblTxn[View Amount],tblTxn[Month],H$4,tblTxn[Category],$B35)*$P35) | I35: =IF($B35="","",SUMIFS(tblTxn[View Amount],tblTxn[Month],I$4,tblTxn[Category],$B35)*$P35) | J35: =IF($B35="","",SUMIFS(tblTxn[View Amount],tblTxn[Month],J$4,tblTxn[Category],$B35)*$P35) | ... N35: =IF($B35="","",SUMIFS(tblTxn[View Amount],tblTxn[Month],N$4,tblTxn[Category],$B35)*$P35) | O35: =IF($B35="","",SUM(C35:N35)) | P35: =IF($B35="",0,IFERROR(IF(INDEX(tblCategories[Type],MATCH($B35,tblCategories[Category],0))="Income",1,-1),-1)) | Q35: =IF(AND($B35<>"",$P35<>1,N($N35)>0),$N35+ROW()/1E+7,-1)
B36: =IFERROR(INDEX(tblCategories[Category],8),"") | C36: =IF($B36="","",SUMIFS(tblTxn[View Amount],tblTxn[Month],C$4,tblTxn[Category],$B36)*$P36) | D36: =IF($B36="","",SUMIFS(tblTxn[View Amount],tblTxn[Month],D$4,tblTxn[Category],$B36)*$P36) | E36: =IF($B36="","",SUMIFS(tblTxn[View Amount],tblTxn[Month],E$4,tblTxn[Category],$B36)*$P36) | F36: =IF($B36="","",SUMIFS(tblTxn[View Amount],tblTxn[Month],F$4,tblTxn[Category],$B36)*$P36) | G36: =IF($B36="","",SUMIFS(tblTxn[View Amount],tblTxn[Month],G$4,tblTxn[Category],$B36)*$P36) | H36: =IF($B36="","",SUMIFS(tblTxn[View Amount],tblTxn[Month],H$4,tblTxn[Category],$B36)*$P36) | I36: =IF($B36="","",SUMIFS(tblTxn[View Amount],tblTxn[Month],I$4,tblTxn[Category],$B36)*$P36) | J36: =IF($B36="","",SUMIFS(tblTxn[View Amount],tblTxn[Month],J$4,tblTxn[Category],$B36)*$P36) | ... N36: =IF($B36="","",SUMIFS(tblTxn[View Amount],tblTxn[Month],N$4,tblTxn[Category],$B36)*$P36) | O36: =IF($B36="","",SUM(C36:N36)) | P36: =IF($B36="",0,IFERROR(IF(INDEX(tblCategories[Type],MATCH($B36,tblCategories[Category],0))="Income",1,-1),-1)) | Q36: =IF(AND($B36<>"",$P36<>1,N($N36)>0),$N36+ROW()/1E+7,-1)
B37: =IFERROR(INDEX(tblCategories[Category],9),"") | C37: =IF($B37="","",SUMIFS(tblTxn[View Amount],tblTxn[Month],C$4,tblTxn[Category],$B37)*$P37) | D37: =IF($B37="","",SUMIFS(tblTxn[View Amount],tblTxn[Month],D$4,tblTxn[Category],$B37)*$P37) | E37: =IF($B37="","",SUMIFS(tblTxn[View Amount],tblTxn[Month],E$4,tblTxn[Category],$B37)*$P37) | F37: =IF($B37="","",SUMIFS(tblTxn[View Amount],tblTxn[Month],F$4,tblTxn[Category],$B37)*$P37) | G37: =IF($B37="","",SUMIFS(tblTxn[View Amount],tblTxn[Month],G$4,tblTxn[Category],$B37)*$P37) | H37: =IF($B37="","",SUMIFS(tblTxn[View Amount],tblTxn[Month],H$4,tblTxn[Category],$B37)*$P37) | I37: =IF($B37="","",SUMIFS(tblTxn[View Amount],tblTxn[Month],I$4,tblTxn[Category],$B37)*$P37) | J37: =IF($B37="","",SUMIFS(tblTxn[View Amount],tblTxn[Month],J$4,tblTxn[Category],$B37)*$P37) | ... N37: =IF($B37="","",SUMIFS(tblTxn[View Amount],tblTxn[Month],N$4,tblTxn[Category],$B37)*$P37) | O37: =IF($B37="","",SUM(C37:N37)) | P37: =IF($B37="",0,IFERROR(IF(INDEX(tblCategories[Type],MATCH($B37,tblCategories[Category],0))="Income",1,-1),-1)) | Q37: =IF(AND($B37<>"",$P37<>1,N($N37)>0),$N37+ROW()/1E+7,-1)
B38: =IFERROR(INDEX(tblCategories[Category],10),"") | C38: =IF($B38="","",SUMIFS(tblTxn[View Amount],tblTxn[Month],C$4,tblTxn[Category],$B38)*$P38) | D38: =IF($B38="","",SUMIFS(tblTxn[View Amount],tblTxn[Month],D$4,tblTxn[Category],$B38)*$P38) | E38: =IF($B38="","",SUMIFS(tblTxn[View Amount],tblTxn[Month],E$4,tblTxn[Category],$B38)*$P38) | F38: =IF($B38="","",SUMIFS(tblTxn[View Amount],tblTxn[Month],F$4,tblTxn[Category],$B38)*$P38) | G38: =IF($B38="","",SUMIFS(tblTxn[View Amount],tblTxn[Month],G$4,tblTxn[Category],$B38)*$P38) | H38: =IF($B38="","",SUMIFS(tblTxn[View Amount],tblTxn[Month],H$4,tblTxn[Category],$B38)*$P38) | I38: =IF($B38="","",SUMIFS(tblTxn[View Amount],tblTxn[Month],I$4,tblTxn[Category],$B38)*$P38) | J38: =IF($B38="","",SUMIFS(tblTxn[View Amount],tblTxn[Month],J$4,tblTxn[Category],$B38)*$P38) | ... N38: =IF($B38="","",SUMIFS(tblTxn[View Amount],tblTxn[Month],N$4,tblTxn[Category],$B38)*$P38) | O38: =IF($B38="","",SUM(C38:N38)) | P38: =IF($B38="",0,IFERROR(IF(INDEX(tblCategories[Type],MATCH($B38,tblCategories[Category],0))="Income",1,-1),-1)) | Q38: =IF(AND($B38<>"",$P38<>1,N($N38)>0),$N38+ROW()/1E+7,-1)
B39: =IFERROR(INDEX(tblCategories[Category],11),"") | C39: =IF($B39="","",SUMIFS(tblTxn[View Amount],tblTxn[Month],C$4,tblTxn[Category],$B39)*$P39) | D39: =IF($B39="","",SUMIFS(tblTxn[View Amount],tblTxn[Month],D$4,tblTxn[Category],$B39)*$P39) | E39: =IF($B39="","",SUMIFS(tblTxn[View Amount],tblTxn[Month],E$4,tblTxn[Category],$B39)*$P39) | F39: =IF($B39="","",SUMIFS(tblTxn[View Amount],tblTxn[Month],F$4,tblTxn[Category],$B39)*$P39) | G39: =IF($B39="","",SUMIFS(tblTxn[View Amount],tblTxn[Month],G$4,tblTxn[Category],$B39)*$P39) | H39: =IF($B39="","",SUMIFS(tblTxn[View Amount],tblTxn[Month],H$4,tblTxn[Category],$B39)*$P39) | I39: =IF($B39="","",SUMIFS(tblTxn[View Amount],tblTxn[Month],I$4,tblTxn[Category],$B39)*$P39) | J39: =IF($B39="","",SUMIFS(tblTxn[View Amount],tblTxn[Month],J$4,tblTxn[Category],$B39)*$P39) | ... N39: =IF($B39="","",SUMIFS(tblTxn[View Amount],tblTxn[Month],N$4,tblTxn[Category],$B39)*$P39) | O39: =IF($B39="","",SUM(C39:N39)) | P39: =IF($B39="",0,IFERROR(IF(INDEX(tblCategories[Type],MATCH($B39,tblCategories[Category],0))="Income",1,-1),-1)) | Q39: =IF(AND($B39<>"",$P39<>1,N($N39)>0),$N39+ROW()/1E+7,-1)
B40: =IFERROR(INDEX(tblCategories[Category],12),"") | C40: =IF($B40="","",SUMIFS(tblTxn[View Amount],tblTxn[Month],C$4,tblTxn[Category],$B40)*$P40) | D40: =IF($B40="","",SUMIFS(tblTxn[View Amount],tblTxn[Month],D$4,tblTxn[Category],$B40)*$P40) | E40: =IF($B40="","",SUMIFS(tblTxn[View Amount],tblTxn[Month],E$4,tblTxn[Category],$B40)*$P40) | F40: =IF($B40="","",SUMIFS(tblTxn[View Amount],tblTxn[Month],F$4,tblTxn[Category],$B40)*$P40) | G40: =IF($B40="","",SUMIFS(tblTxn[View Amount],tblTxn[Month],G$4,tblTxn[Category],$B40)*$P40) | H40: =IF($B40="","",SUMIFS(tblTxn[View Amount],tblTxn[Month],H$4,tblTxn[Category],$B40)*$P40) | I40: =IF($B40="","",SUMIFS(tblTxn[View Amount],tblTxn[Month],I$4,tblTxn[Category],$B40)*$P40) | J40: =IF($B40="","",SUMIFS(tblTxn[View Amount],tblTxn[Month],J$4,tblTxn[Category],$B40)*$P40) | ... N40: =IF($B40="","",SUMIFS(tblTxn[View Amount],tblTxn[Month],N$4,tblTxn[Category],$B40)*$P40) | O40: =IF($B40="","",SUM(C40:N40)) | P40: =IF($B40="",0,IFERROR(IF(INDEX(tblCategories[Type],MATCH($B40,tblCategories[Category],0))="Income",1,-1),-1)) | Q40: =IF(AND($B40<>"",$P40<>1,N($N40)>0),$N40+ROW()/1E+7,-1)
B41: =IFERROR(INDEX(tblCategories[Category],13),"") | C41: =IF($B41="","",SUMIFS(tblTxn[View Amount],tblTxn[Month],C$4,tblTxn[Category],$B41)*$P41) | D41: =IF($B41="","",SUMIFS(tblTxn[View Amount],tblTxn[Month],D$4,tblTxn[Category],$B41)*$P41) | E41: =IF($B41="","",SUMIFS(tblTxn[View Amount],tblTxn[Month],E$4,tblTxn[Category],$B41)*$P41) | F41: =IF($B41="","",SUMIFS(tblTxn[View Amount],tblTxn[Month],F$4,tblTxn[Category],$B41)*$P41) | G41: =IF($B41="","",SUMIFS(tblTxn[View Amount],tblTxn[Month],G$4,tblTxn[Category],$B41)*$P41) | H41: =IF($B41="","",SUMIFS(tblTxn[View Amount],tblTxn[Month],H$4,tblTxn[Category],$B41)*$P41) | I41: =IF($B41="","",SUMIFS(tblTxn[View Amount],tblTxn[Month],I$4,tblTxn[Category],$B41)*$P41) | J41: =IF($B41="","",SUMIFS(tblTxn[View Amount],tblTxn[Month],J$4,tblTxn[Category],$B41)*$P41) | ... N41: =IF($B41="","",SUMIFS(tblTxn[View Amount],tblTxn[Month],N$4,tblTxn[Category],$B41)*$P41) | O41: =IF($B41="","",SUM(C41:N41)) | P41: =IF($B41="",0,IFERROR(IF(INDEX(tblCategories[Type],MATCH($B41,tblCategories[Category],0))="Income",1,-1),-1)) | Q41: =IF(AND($B41<>"",$P41<>1,N($N41)>0),$N41+ROW()/1E+7,-1)
B42: =IFERROR(INDEX(tblCategories[Category],14),"") | C42: =IF($B42="","",SUMIFS(tblTxn[View Amount],tblTxn[Month],C$4,tblTxn[Category],$B42)*$P42) | D42: =IF($B42="","",SUMIFS(tblTxn[View Amount],tblTxn[Month],D$4,tblTxn[Category],$B42)*$P42) | E42: =IF($B42="","",SUMIFS(tblTxn[View Amount],tblTxn[Month],E$4,tblTxn[Category],$B42)*$P42) | F42: =IF($B42="","",SUMIFS(tblTxn[View Amount],tblTxn[Month],F$4,tblTxn[Category],$B42)*$P42) | G42: =IF($B42="","",SUMIFS(tblTxn[View Amount],tblTxn[Month],G$4,tblTxn[Category],$B42)*$P42) | H42: =IF($B42="","",SUMIFS(tblTxn[View Amount],tblTxn[Month],H$4,tblTxn[Category],$B42)*$P42) | I42: =IF($B42="","",SUMIFS(tblTxn[View Amount],tblTxn[Month],I$4,tblTxn[Category],$B42)*$P42) | J42: =IF($B42="","",SUMIFS(tblTxn[View Amount],tblTxn[Month],J$4,tblTxn[Category],$B42)*$P42) | ... N42: =IF($B42="","",SUMIFS(tblTxn[View Amount],tblTxn[Month],N$4,tblTxn[Category],$B42)*$P42) | O42: =IF($B42="","",SUM(C42:N42)) | P42: =IF($B42="",0,IFERROR(IF(INDEX(tblCategories[Type],MATCH($B42,tblCategories[Category],0))="Income",1,-1),-1)) | Q42: =IF(AND($B42<>"",$P42<>1,N($N42)>0),$N42+ROW()/1E+7,-1)
B43: =IFERROR(INDEX(tblCategories[Category],15),"") | C43: =IF($B43="","",SUMIFS(tblTxn[View Amount],tblTxn[Month],C$4,tblTxn[Category],$B43)*$P43) | D43: =IF($B43="","",SUMIFS(tblTxn[View Amount],tblTxn[Month],D$4,tblTxn[Category],$B43)*$P43) | E43: =IF($B43="","",SUMIFS(tblTxn[View Amount],tblTxn[Month],E$4,tblTxn[Category],$B43)*$P43) | F43: =IF($B43="","",SUMIFS(tblTxn[View Amount],tblTxn[Month],F$4,tblTxn[Category],$B43)*$P43) | G43: =IF($B43="","",SUMIFS(tblTxn[View Amount],tblTxn[Month],G$4,tblTxn[Category],$B43)*$P43) | H43: =IF($B43="","",SUMIFS(tblTxn[View Amount],tblTxn[Month],H$4,tblTxn[Category],$B43)*$P43) | I43: =IF($B43="","",SUMIFS(tblTxn[View Amount],tblTxn[Month],I$4,tblTxn[Category],$B43)*$P43) | J43: =IF($B43="","",SUMIFS(tblTxn[View Amount],tblTxn[Month],J$4,tblTxn[Category],$B43)*$P43) | ... N43: =IF($B43="","",SUMIFS(tblTxn[View Amount],tblTxn[Month],N$4,tblTxn[Category],$B43)*$P43) | O43: =IF($B43="","",SUM(C43:N43)) | P43: =IF($B43="",0,IFERROR(IF(INDEX(tblCategories[Type],MATCH($B43,tblCategories[Category],0))="Income",1,-1),-1)) | Q43: =IF(AND($B43<>"",$P43<>1,N($N43)>0),$N43+ROW()/1E+7,-1)
B44: =IFERROR(INDEX(tblCategories[Category],16),"") | C44: =IF($B44="","",SUMIFS(tblTxn[View Amount],tblTxn[Month],C$4,tblTxn[Category],$B44)*$P44) | D44: =IF($B44="","",SUMIFS(tblTxn[View Amount],tblTxn[Month],D$4,tblTxn[Category],$B44)*$P44) | E44: =IF($B44="","",SUMIFS(tblTxn[View Amount],tblTxn[Month],E$4,tblTxn[Category],$B44)*$P44) | F44: =IF($B44="","",SUMIFS(tblTxn[View Amount],tblTxn[Month],F$4,tblTxn[Category],$B44)*$P44) | G44: =IF($B44="","",SUMIFS(tblTxn[View Amount],tblTxn[Month],G$4,tblTxn[Category],$B44)*$P44) | H44: =IF($B44="","",SUMIFS(tblTxn[View Amount],tblTxn[Month],H$4,tblTxn[Category],$B44)*$P44) | I44: =IF($B44="","",SUMIFS(tblTxn[View Amount],tblTxn[Month],I$4,tblTxn[Category],$B44)*$P44) | J44: =IF($B44="","",SUMIFS(tblTxn[View Amount],tblTxn[Month],J$4,tblTxn[Category],$B44)*$P44) | ... N44: =IF($B44="","",SUMIFS(tblTxn[View Amount],tblTxn[Month],N$4,tblTxn[Category],$B44)*$P44) | O44: =IF($B44="","",SUM(C44:N44)) | P44: =IF($B44="",0,IFERROR(IF(INDEX(tblCategories[Type],MATCH($B44,tblCategories[Category],0))="Income",1,-1),-1)) | Q44: =IF(AND($B44<>"",$P44<>1,N($N44)>0),$N44+ROW()/1E+7,-1)
B45: =IFERROR(INDEX(tblCategories[Category],17),"") | C45: =IF($B45="","",SUMIFS(tblTxn[View Amount],tblTxn[Month],C$4,tblTxn[Category],$B45)*$P45) | D45: =IF($B45="","",SUMIFS(tblTxn[View Amount],tblTxn[Month],D$4,tblTxn[Category],$B45)*$P45) | E45: =IF($B45="","",SUMIFS(tblTxn[View Amount],tblTxn[Month],E$4,tblTxn[Category],$B45)*$P45) | F45: =IF($B45="","",SUMIFS(tblTxn[View Amount],tblTxn[Month],F$4,tblTxn[Category],$B45)*$P45) | G45: =IF($B45="","",SUMIFS(tblTxn[View Amount],tblTxn[Month],G$4,tblTxn[Category],$B45)*$P45) | H45: =IF($B45="","",SUMIFS(tblTxn[View Amount],tblTxn[Month],H$4,tblTxn[Category],$B45)*$P45) | I45: =IF($B45="","",SUMIFS(tblTxn[View Amount],tblTxn[Month],I$4,tblTxn[Category],$B45)*$P45) | J45: =IF($B45="","",SUMIFS(tblTxn[View Amount],tblTxn[Month],J$4,tblTxn[Category],$B45)*$P45) | ... N45: =IF($B45="","",SUMIFS(tblTxn[View Amount],tblTxn[Month],N$4,tblTxn[Category],$B45)*$P45) | O45: =IF($B45="","",SUM(C45:N45)) | P45: =IF($B45="",0,IFERROR(IF(INDEX(tblCategories[Type],MATCH($B45,tblCategories[Category],0))="Income",1,-1),-1)) | Q45: =IF(AND($B45<>"",$P45<>1,N($N45)>0),$N45+ROW()/1E+7,-1)
B46: =IFERROR(INDEX(tblCategories[Category],18),"") | C46: =IF($B46="","",SUMIFS(tblTxn[View Amount],tblTxn[Month],C$4,tblTxn[Category],$B46)*$P46) | D46: =IF($B46="","",SUMIFS(tblTxn[View Amount],tblTxn[Month],D$4,tblTxn[Category],$B46)*$P46) | E46: =IF($B46="","",SUMIFS(tblTxn[View Amount],tblTxn[Month],E$4,tblTxn[Category],$B46)*$P46) | F46: =IF($B46="","",SUMIFS(tblTxn[View Amount],tblTxn[Month],F$4,tblTxn[Category],$B46)*$P46) | G46: =IF($B46="","",SUMIFS(tblTxn[View Amount],tblTxn[Month],G$4,tblTxn[Category],$B46)*$P46) | H46: =IF($B46="","",SUMIFS(tblTxn[View Amount],tblTxn[Month],H$4,tblTxn[Category],$B46)*$P46) | I46: =IF($B46="","",SUMIFS(tblTxn[View Amount],tblTxn[Month],I$4,tblTxn[Category],$B46)*$P46) | J46: =IF($B46="","",SUMIFS(tblTxn[View Amount],tblTxn[Month],J$4,tblTxn[Category],$B46)*$P46) | ... N46: =IF($B46="","",SUMIFS(tblTxn[View Amount],tblTxn[Month],N$4,tblTxn[Category],$B46)*$P46) | O46: =IF($B46="","",SUM(C46:N46)) | P46: =IF($B46="",0,IFERROR(IF(INDEX(tblCategories[Type],MATCH($B46,tblCategories[Category],0))="Income",1,-1),-1)) | Q46: =IF(AND($B46<>"",$P46<>1,N($N46)>0),$N46+ROW()/1E+7,-1)
B47: =IFERROR(INDEX(tblCategories[Category],19),"") | C47: =IF($B47="","",SUMIFS(tblTxn[View Amount],tblTxn[Month],C$4,tblTxn[Category],$B47)*$P47) | D47: =IF($B47="","",SUMIFS(tblTxn[View Amount],tblTxn[Month],D$4,tblTxn[Category],$B47)*$P47) | E47: =IF($B47="","",SUMIFS(tblTxn[View Amount],tblTxn[Month],E$4,tblTxn[Category],$B47)*$P47) | F47: =IF($B47="","",SUMIFS(tblTxn[View Amount],tblTxn[Month],F$4,tblTxn[Category],$B47)*$P47) | G47: =IF($B47="","",SUMIFS(tblTxn[View Amount],tblTxn[Month],G$4,tblTxn[Category],$B47)*$P47) | H47: =IF($B47="","",SUMIFS(tblTxn[View Amount],tblTxn[Month],H$4,tblTxn[Category],$B47)*$P47) | I47: =IF($B47="","",SUMIFS(tblTxn[View Amount],tblTxn[Month],I$4,tblTxn[Category],$B47)*$P47) | J47: =IF($B47="","",SUMIFS(tblTxn[View Amount],tblTxn[Month],J$4,tblTxn[Category],$B47)*$P47) | ... N47: =IF($B47="","",SUMIFS(tblTxn[View Amount],tblTxn[Month],N$4,tblTxn[Category],$B47)*$P47) | O47: =IF($B47="","",SUM(C47:N47)) | P47: =IF($B47="",0,IFERROR(IF(INDEX(tblCategories[Type],MATCH($B47,tblCategories[Category],0))="Income",1,-1),-1)) | Q47: =IF(AND($B47<>"",$P47<>1,N($N47)>0),$N47+ROW()/1E+7,-1)
B48: =IFERROR(INDEX(tblCategories[Category],20),"") | C48: =IF($B48="","",SUMIFS(tblTxn[View Amount],tblTxn[Month],C$4,tblTxn[Category],$B48)*$P48) | D48: =IF($B48="","",SUMIFS(tblTxn[View Amount],tblTxn[Month],D$4,tblTxn[Category],$B48)*$P48) | E48: =IF($B48="","",SUMIFS(tblTxn[View Amount],tblTxn[Month],E$4,tblTxn[Category],$B48)*$P48) | F48: =IF($B48="","",SUMIFS(tblTxn[View Amount],tblTxn[Month],F$4,tblTxn[Category],$B48)*$P48) | G48: =IF($B48="","",SUMIFS(tblTxn[View Amount],tblTxn[Month],G$4,tblTxn[Category],$B48)*$P48) | H48: =IF($B48="","",SUMIFS(tblTxn[View Amount],tblTxn[Month],H$4,tblTxn[Category],$B48)*$P48) | I48: =IF($B48="","",SUMIFS(tblTxn[View Amount],tblTxn[Month],I$4,tblTxn[Category],$B48)*$P48) | J48: =IF($B48="","",SUMIFS(tblTxn[View Amount],tblTxn[Month],J$4,tblTxn[Category],$B48)*$P48) | ... N48: =IF($B48="","",SUMIFS(tblTxn[View Amount],tblTxn[Month],N$4,tblTxn[Category],$B48)*$P48) | O48: =IF($B48="","",SUM(C48:N48)) | P48: =IF($B48="",0,IFERROR(IF(INDEX(tblCategories[Type],MATCH($B48,tblCategories[Category],0))="Income",1,-1),-1)) | Q48: =IF(AND($B48<>"",$P48<>1,N($N48)>0),$N48+ROW()/1E+7,-1)
B49: =IFERROR(INDEX(tblCategories[Category],21),"") | C49: =IF($B49="","",SUMIFS(tblTxn[View Amount],tblTxn[Month],C$4,tblTxn[Category],$B49)*$P49) | D49: =IF($B49="","",SUMIFS(tblTxn[View Amount],tblTxn[Month],D$4,tblTxn[Category],$B49)*$P49) | E49: =IF($B49="","",SUMIFS(tblTxn[View Amount],tblTxn[Month],E$4,tblTxn[Category],$B49)*$P49) | F49: =IF($B49="","",SUMIFS(tblTxn[View Amount],tblTxn[Month],F$4,tblTxn[Category],$B49)*$P49) | G49: =IF($B49="","",SUMIFS(tblTxn[View Amount],tblTxn[Month],G$4,tblTxn[Category],$B49)*$P49) | H49: =IF($B49="","",SUMIFS(tblTxn[View Amount],tblTxn[Month],H$4,tblTxn[Category],$B49)*$P49) | I49: =IF($B49="","",SUMIFS(tblTxn[View Amount],tblTxn[Month],I$4,tblTxn[Category],$B49)*$P49) | J49: =IF($B49="","",SUMIFS(tblTxn[View Amount],tblTxn[Month],J$4,tblTxn[Category],$B49)*$P49) | ... N49: =IF($B49="","",SUMIFS(tblTxn[View Amount],tblTxn[Month],N$4,tblTxn[Category],$B49)*$P49) | O49: =IF($B49="","",SUM(C49:N49)) | P49: =IF($B49="",0,IFERROR(IF(INDEX(tblCategories[Type],MATCH($B49,tblCategories[Category],0))="Income",1,-1),-1)) | Q49: =IF(AND($B49<>"",$P49<>1,N($N49)>0),$N49+ROW()/1E+7,-1)
B50: =IFERROR(INDEX(tblCategories[Category],22),"") | C50: =IF($B50="","",SUMIFS(tblTxn[View Amount],tblTxn[Month],C$4,tblTxn[Category],$B50)*$P50) | D50: =IF($B50="","",SUMIFS(tblTxn[View Amount],tblTxn[Month],D$4,tblTxn[Category],$B50)*$P50) | E50: =IF($B50="","",SUMIFS(tblTxn[View Amount],tblTxn[Month],E$4,tblTxn[Category],$B50)*$P50) | F50: =IF($B50="","",SUMIFS(tblTxn[View Amount],tblTxn[Month],F$4,tblTxn[Category],$B50)*$P50) | G50: =IF($B50="","",SUMIFS(tblTxn[View Amount],tblTxn[Month],G$4,tblTxn[Category],$B50)*$P50) | H50: =IF($B50="","",SUMIFS(tblTxn[View Amount],tblTxn[Month],H$4,tblTxn[Category],$B50)*$P50) | I50: =IF($B50="","",SUMIFS(tblTxn[View Amount],tblTxn[Month],I$4,tblTxn[Category],$B50)*$P50) | J50: =IF($B50="","",SUMIFS(tblTxn[View Amount],tblTxn[Month],J$4,tblTxn[Category],$B50)*$P50) | ... N50: =IF($B50="","",SUMIFS(tblTxn[View Amount],tblTxn[Month],N$4,tblTxn[Category],$B50)*$P50) | O50: =IF($B50="","",SUM(C50:N50)) | P50: =IF($B50="",0,IFERROR(IF(INDEX(tblCategories[Type],MATCH($B50,tblCategories[Category],0))="Income",1,-1),-1)) | Q50: =IF(AND($B50<>"",$P50<>1,N($N50)>0),$N50+ROW()/1E+7,-1)
B51: =IFERROR(INDEX(tblCategories[Category],23),"") | C51: =IF($B51="","",SUMIFS(tblTxn[View Amount],tblTxn[Month],C$4,tblTxn[Category],$B51)*$P51) | D51: =IF($B51="","",SUMIFS(tblTxn[View Amount],tblTxn[Month],D$4,tblTxn[Category],$B51)*$P51) | E51: =IF($B51="","",SUMIFS(tblTxn[View Amount],tblTxn[Month],E$4,tblTxn[Category],$B51)*$P51) | F51: =IF($B51="","",SUMIFS(tblTxn[View Amount],tblTxn[Month],F$4,tblTxn[Category],$B51)*$P51) | G51: =IF($B51="","",SUMIFS(tblTxn[View Amount],tblTxn[Month],G$4,tblTxn[Category],$B51)*$P51) | H51: =IF($B51="","",SUMIFS(tblTxn[View Amount],tblTxn[Month],H$4,tblTxn[Category],$B51)*$P51) | I51: =IF($B51="","",SUMIFS(tblTxn[View Amount],tblTxn[Month],I$4,tblTxn[Category],$B51)*$P51) | J51: =IF($B51="","",SUMIFS(tblTxn[View Amount],tblTxn[Month],J$4,tblTxn[Category],$B51)*$P51) | ... N51: =IF($B51="","",SUMIFS(tblTxn[View Amount],tblTxn[Month],N$4,tblTxn[Category],$B51)*$P51) | O51: =IF($B51="","",SUM(C51:N51)) | P51: =IF($B51="",0,IFERROR(IF(INDEX(tblCategories[Type],MATCH($B51,tblCategories[Category],0))="Income",1,-1),-1)) | Q51: =IF(AND($B51<>"",$P51<>1,N($N51)>0),$N51+ROW()/1E+7,-1)
B52: =IFERROR(INDEX(tblCategories[Category],24),"") | C52: =IF($B52="","",SUMIFS(tblTxn[View Amount],tblTxn[Month],C$4,tblTxn[Category],$B52)*$P52) | D52: =IF($B52="","",SUMIFS(tblTxn[View Amount],tblTxn[Month],D$4,tblTxn[Category],$B52)*$P52) | E52: =IF($B52="","",SUMIFS(tblTxn[View Amount],tblTxn[Month],E$4,tblTxn[Category],$B52)*$P52) | F52: =IF($B52="","",SUMIFS(tblTxn[View Amount],tblTxn[Month],F$4,tblTxn[Category],$B52)*$P52) | G52: =IF($B52="","",SUMIFS(tblTxn[View Amount],tblTxn[Month],G$4,tblTxn[Category],$B52)*$P52) | H52: =IF($B52="","",SUMIFS(tblTxn[View Amount],tblTxn[Month],H$4,tblTxn[Category],$B52)*$P52) | I52: =IF($B52="","",SUMIFS(tblTxn[View Amount],tblTxn[Month],I$4,tblTxn[Category],$B52)*$P52) | J52: =IF($B52="","",SUMIFS(tblTxn[View Amount],tblTxn[Month],J$4,tblTxn[Category],$B52)*$P52) | ... N52: =IF($B52="","",SUMIFS(tblTxn[View Amount],tblTxn[Month],N$4,tblTxn[Category],$B52)*$P52) | O52: =IF($B52="","",SUM(C52:N52)) | P52: =IF($B52="",0,IFERROR(IF(INDEX(tblCategories[Type],MATCH($B52,tblCategories[Category],0))="Income",1,-1),-1)) | Q52: =IF(AND($B52<>"",$P52<>1,N($N52)>0),$N52+ROW()/1E+7,-1)
B53: =IFERROR(INDEX(tblCategories[Category],25),"") | C53: =IF($B53="","",SUMIFS(tblTxn[View Amount],tblTxn[Month],C$4,tblTxn[Category],$B53)*$P53) | D53: =IF($B53="","",SUMIFS(tblTxn[View Amount],tblTxn[Month],D$4,tblTxn[Category],$B53)*$P53) | E53: =IF($B53="","",SUMIFS(tblTxn[View Amount],tblTxn[Month],E$4,tblTxn[Category],$B53)*$P53) | F53: =IF($B53="","",SUMIFS(tblTxn[View Amount],tblTxn[Month],F$4,tblTxn[Category],$B53)*$P53) | G53: =IF($B53="","",SUMIFS(tblTxn[View Amount],tblTxn[Month],G$4,tblTxn[Category],$B53)*$P53) | H53: =IF($B53="","",SUMIFS(tblTxn[View Amount],tblTxn[Month],H$4,tblTxn[Category],$B53)*$P53) | I53: =IF($B53="","",SUMIFS(tblTxn[View Amount],tblTxn[Month],I$4,tblTxn[Category],$B53)*$P53) | J53: =IF($B53="","",SUMIFS(tblTxn[View Amount],tblTxn[Month],J$4,tblTxn[Category],$B53)*$P53) | ... N53: =IF($B53="","",SUMIFS(tblTxn[View Amount],tblTxn[Month],N$4,tblTxn[Category],$B53)*$P53) | O53: =IF($B53="","",SUM(C53:N53)) | P53: =IF($B53="",0,IFERROR(IF(INDEX(tblCategories[Type],MATCH($B53,tblCategories[Category],0))="Income",1,-1),-1)) | Q53: =IF(AND($B53<>"",$P53<>1,N($N53)>0),$N53+ROW()/1E+7,-1)
B54: =IFERROR(INDEX(tblCategories[Category],26),"") | C54: =IF($B54="","",SUMIFS(tblTxn[View Amount],tblTxn[Month],C$4,tblTxn[Category],$B54)*$P54) | D54: =IF($B54="","",SUMIFS(tblTxn[View Amount],tblTxn[Month],D$4,tblTxn[Category],$B54)*$P54) | E54: =IF($B54="","",SUMIFS(tblTxn[View Amount],tblTxn[Month],E$4,tblTxn[Category],$B54)*$P54) | F54: =IF($B54="","",SUMIFS(tblTxn[View Amount],tblTxn[Month],F$4,tblTxn[Category],$B54)*$P54) | G54: =IF($B54="","",SUMIFS(tblTxn[View Amount],tblTxn[Month],G$4,tblTxn[Category],$B54)*$P54) | H54: =IF($B54="","",SUMIFS(tblTxn[View Amount],tblTxn[Month],H$4,tblTxn[Category],$B54)*$P54) | I54: =IF($B54="","",SUMIFS(tblTxn[View Amount],tblTxn[Month],I$4,tblTxn[Category],$B54)*$P54) | J54: =IF($B54="","",SUMIFS(tblTxn[View Amount],tblTxn[Month],J$4,tblTxn[Category],$B54)*$P54) | ... N54: =IF($B54="","",SUMIFS(tblTxn[View Amount],tblTxn[Month],N$4,tblTxn[Category],$B54)*$P54) | O54: =IF($B54="","",SUM(C54:N54)) | P54: =IF($B54="",0,IFERROR(IF(INDEX(tblCategories[Type],MATCH($B54,tblCategories[Category],0))="Income",1,-1),-1)) | Q54: =IF(AND($B54<>"",$P54<>1,N($N54)>0),$N54+ROW()/1E+7,-1)
